Workbook

Sheet to do
A1: check value definitions | B1: done
A2: build in-year value dashboard
A3: calibrate baseline | B3: done

Sheet config
A1: Configurable | D1: Fixed
A2: workstreams | B2: done | D2: 5 stage gates
A3: financial impact types | B3: done
A4: initiative tag | B4: done
A5: approval flows
A6: stage gate progression requirement / checklist

Sheet Dashboards
A1: Run rate value of completed initiatives (completed initiative = initiative in G4)
A2: Plan - locked on [selected date]
B3: =DATE(2026,7,1) -> 46204 | C3: =EDATE(B3,1) -> 46235 | D3: =EDATE(C3,1) -> 46266 | E3: =EDATE(D3,1) -> 46296 | F3: =EDATE(E3,1) -> 46327 | G3: =EDATE(F3,1) -> 46357 | H3: =EDATE(G3,1) -> 46388 | I3: =EDATE(H3,1) -> 46419 | J3: =EDATE(I3,1) -> 46447 | ... S3: =EDATE(R3,1) -> 46722
A4: Westmark Region | B4: =SUMIFS('Initiative Summary'!$O$5:$O$25,'Initiative Summary'!$C$5:$C$25,$A4,'Initiative Summary'!$K$5:$K$25,"<="&EOMONTH(B$3,0)) -> 0 | C4: =SUMIFS('Initiative Summary'!$O$5:$O$25,'Initiative Summary'!$C$5:$C$25,$A4,'Initiative Summary'!$K$5:$K$25,"<="&EOMONTH(C$3,0)) -> 0 | D4: =SUMIFS('Initiative Summary'!$O$5:$O$25,'Initiative Summary'!$C$5:$C$25,$A4,'Initiative Summary'!$K$5:$K$25,"<="&EOMONTH(D$3,0)) -> 0 | E4: =SUMIFS('Initiative Summary'!$O$5:$O$25,'Initiative Summary'!$C$5:$C$25,$A4,'Initiative Summary'!$K$5:$K$25,"<="&EOMONTH(E$3,0)) -> 0 | F4: =SUMIFS('Initiative Summary'!$O$5:$O$25,'Initiative Summary'!$C$5:$C$25,$A4,'Initiative Summary'!$K$5:$K$25,"<="&EOMONTH(F$3,0)) -> 1.76 | G4: =SUMIFS('Initiative Summary'!$O$5:$O$25,'Initiative Summary'!$C$5:$C$25,$A4,'Initiative Summary'!$K$5:$K$25,"<="&EOMONTH(G$3,0)) -> 1.84 | H4: =SUMIFS('Initiative Summary'!$O$5:$O$25,'Initiative Summary'!$C$5:$C$25,$A4,'Initiative Summary'!$K$5:$K$25,"<="&EOMONTH(H$3,0)) -> 1.84 | I4: =SUMIFS('Initiative Summary'!$O$5:$O$25,'Initiative Summary'!$C$5:$C$25,$A4,'Initiative Summary'!$K$5:$K$25,"<="&EOMONTH(I$3,0)) -> 1.84 | ... S4: =SUMIFS('Initiative Summary'!$O$5:$O$25,'Initiative Summary'!$C$5:$C$25,$A4,'Initiative Summary'!$K$5:$K$25,"<="&EOMONTH(S$3,0)) -> 4.88
A5: Eastbridge Region | B5: =SUMIFS('Initiative Summary'!$O$5:$O$25,'Initiative Summary'!$C$5:$C$25,$A5,'Initiative Summary'!$K$5:$K$25,"<="&EOMONTH(B$3,0)) -> 0 | C5: =SUMIFS('Initiative Summary'!$O$5:$O$25,'Initiative Summary'!$C$5:$C$25,$A5,'Initiative Summary'!$K$5:$K$25,"<="&EOMONTH(C$3,0)) -> 0 | D5: =SUMIFS('Initiative Summary'!$O$5:$O$25,'Initiative Summary'!$C$5:$C$25,$A5,'Initiative Summary'!$K$5:$K$25,"<="&EOMONTH(D$3,0)) -> 0 | E5: =SUMIFS('Initiative Summary'!$O$5:$O$25,'Initiative Summary'!$C$5:$C$25,$A5,'Initiative Summary'!$K$5:$K$25,"<="&EOMONTH(E$3,0)) -> 1.584 | F5: =SUMIFS('Initiative Summary'!$O$5:$O$25,'Initiative Summary'!$C$5:$C$25,$A5,'Initiative Summary'!$K$5:$K$25,"<="&EOMONTH(F$3,0)) -> 1.584 | G5: =SUMIFS('Initiative Summary'!$O$5:$O$25,'Initiative Summary'!$C$5:$C$25,$A5,'Initiative Summary'!$K$5:$K$25,"<="&EOMONTH(G$3,0)) -> 1.584 | H5: =SUMIFS('Initiative Summary'!$O$5:$O$25,'Initiative Summary'!$C$5:$C$25,$A5,'Initiative Summary'!$K$5:$K$25,"<="&EOMONTH(H$3,0)) -> 1.584 | I5: =SUMIFS('Initiative Summary'!$O$5:$O$25,'Initiative Summary'!$C$5:$C$25,$A5,'Initiative Summary'!$K$5:$K$25,"<="&EOMONTH(I$3,0)) -> 1.584 | ... S5: =SUMIFS('Initiative Summary'!$O$5:$O$25,'Initiative Summary'!$C$5:$C$25,$A5,'Initiative Summary'!$K$5:$K$25,"<="&EOMONTH(S$3,0)) -> 4.762
A6: Northpeak Region | B6: =SUMIFS('Initiative Summary'!$O$5:$O$25,'Initiative Summary'!$C$5:$C$25,$A6,'Initiative Summary'!$K$5:$K$25,"<="&EOMONTH(B$3,0)) -> 0 | C6: =SUMIFS('Initiative Summary'!$O$5:$O$25,'Initiative Summary'!$C$5:$C$25,$A6,'Initiative Summary'!$K$5:$K$25,"<="&EOMONTH(C$3,0)) -> 0 | D6: =SUMIFS('Initiative Summary'!$O$5:$O$25,'Initiative Summary'!$C$5:$C$25,$A6,'Initiative Summary'!$K$5:$K$25,"<="&EOMONTH(D$3,0)) -> 0 | E6: =SUMIFS('Initiative Summary'!$O$5:$O$25,'Initiative Summary'!$C$5:$C$25,$A6,'Initiative Summary'!$K$5:$K$25,"<="&EOMONTH(E$3,0)) -> 0 | F6: =SUMIFS('Initiative Summary'!$O$5:$O$25,'Initiative Summary'!$C$5:$C$25,$A6,'Initiative Summary'!$K$5:$K$25,"<="&EOMONTH(F$3,0)) -> 0 | G6: =SUMIFS('Initiative Summary'!$O$5:$O$25,'Initiative Summary'!$C$5:$C$25,$A6,'Initiative Summary'!$K$5:$K$25,"<="&EOMONTH(G$3,0)) -> 0.088 | H6: =SUMIFS('Initiative Summary'!$O$5:$O$25,'Initiative Summary'!$C$5:$C$25,$A6,'Initiative Summary'!$K$5:$K$25,"<="&EOMONTH(H$3,0)) -> 0.62 | I6: =SUMIFS('Initiative Summary'!$O$5:$O$25,'Initiative Summary'!$C$5:$C$25,$A6,'Initiative Summary'!$K$5:$K$25,"<="&EOMONTH(I$3,0)) -> 0.62 | ... S6: =SUMIFS('Initiative Summary'!$O$5:$O$25,'Initiative Summary'!$C$5:$C$25,$A6,'Initiative Summary'!$K$5:$K$25,"<="&EOMONTH(S$3,0)) -> 4.906
A7: Southgate Region | B7: =SUMIFS('Initiative Summary'!$O$5:$O$25,'Initiative Summary'!$C$5:$C$25,$A7,'Initiative Summary'!$K$5:$K$25,"<="&EOMONTH(B$3,0)) -> 0 | C7: =SUMIFS('Initiative Summary'!$O$5:$O$25,'Initiative Summary'!$C$5:$C$25,$A7,'Initiative Summary'!$K$5:$K$25,"<="&EOMONTH(C$3,0)) -> 0 | D7: =SUMIFS('Initiative Summary'!$O$5:$O$25,'Initiative Summary'!$C$5:$C$25,$A7,'Initiative Summary'!$K$5:$K$25,"<="&EOMONTH(D$3,0)) -> 0 | E7: =SUMIFS('Initiative Summary'!$O$5:$O$25,'Initiative Summary'!$C$5:$C$25,$A7,'Initiative Summary'!$K$5:$K$25,"<="&EOMONTH(E$3,0)) -> 0 | F7: =SUMIFS('Initiative Summary'!$O$5:$O$25,'Initiative Summary'!$C$5:$C$25,$A7,'Initiative Summary'!$K$5:$K$25,"<="&EOMONTH(F$3,0)) -> 0.092 | G7: =SUMIFS('Initiative Summary'!$O$5:$O$25,'Initiative Summary'!$C$5:$C$25,$A7,'Initiative Summary'!$K$5:$K$25,"<="&EOMONTH(G$3,0)) -> 0.092 | H7: =SUMIFS('Initiative Summary'!$O$5:$O$25,'Initiative Summary'!$C$5:$C$25,$A7,'Initiative Summary'!$K$5:$K$25,"<="&EOMONTH(H$3,0)) -> 0.092 | I7: =SUMIFS('Initiative Summary'!$O$5:$O$25,'Initiative Summary'!$C$5:$C$25,$A7,'Initiative Summary'!$K$5:$K$25,"<="&EOMONTH(I$3,0)) -> 1.441 | ... S7: =SUMIFS('Initiative Summary'!$O$5:$O$25,'Initiative Summary'!$C$5:$C$25,$A7,'Initiative Summary'!$K$5:$K$25,"<="&EOMONTH(S$3,0)) -> 3.525
A8: Total | B8: =SUM(B4:B7) -> 0 | C8: =SUM(C4:C7) -> 0 | D8: =SUM(D4:D7) -> 0 | E8: =SUM(E4:E7) -> 1.584 | F8: =SUM(F4:F7) -> 3.436 | G8: =SUM(G4:G7) -> 3.604 | H8: =SUM(H4:H7) -> 4.136 | I8: =SUM(I4:I7) -> 5.485 | ... S8: =SUM(S4:S7) -> 18.073
A10: Actual (based on actual date and value of initiatives completed, regardless of whether they were part of the plan)
B11: =DATE(2026,7,1) -> 46204 | C11: =EDATE(B11,1) -> 46235 | D11: =EDATE(C11,1) -> 46266 | E11: =EDATE(D11,1) -> 46296 | F11: =EDATE(E11,1) -> 46327 | G11: =EDATE(F11,1) -> 46357 | H11: =EDATE(G11,1) -> 46388 | I11: =EDATE(H11,1) -> 46419 | J11: =EDATE(I11,1) -> 46447 | ... S11: =EDATE(R11,1) -> 46722
A12: Westmark Region
A13: Eastbridge Region
A14: Northpeak Region
A15: Southgate Region
A16: Total | B16: =SUM(B12:B15) -> 0 | C16: =SUM(C12:C15) -> 0 | D16: =SUM(D12:D15) -> 0 | E16: =SUM(E12:E15) -> 0 | F16: =SUM(F12:F15) -> 0 | G16: =SUM(G12:G15) -> 0 | H16: =SUM(H12:H15) -> 0 | I16: =SUM(I12:I15) -> 0 | ... S16: =SUM(S12:S15) -> 0
A20: In-year value of initiatives
B21: FY26 | C21: FY27 | D21: FY28 | E21: FY29 | F21: FY30 | H21: =DATE(2026,7,1) -> 46204 | I21: =EDATE(H21,1) -> 46235 | J21: =EDATE(I21,1) -> 46266 | K21: =EDATE(J21,1) -> 46296 | L21: =EDATE(K21,1) -> 46327 | M21: =EDATE(L21,1) -> 46357 | N21: =EDATE(M21,1) -> 46388 | O21: =EDATE(N21,1) -> 46419 | P21: =EDATE(O21,1) -> 46447 | ... BI21: =EDATE(BH21,1) -> 47818
A22: Plan - locked on [selected date - based on initiatives in G3 then]
A23: Revenue (USD m)
A24: Westmark Region | B24: =SUMIFS(Benefits!$S:$S,Benefits!$E:$E,"Revenue",Benefits!$F:$F,"USD",Benefits!$D:$D,"Plan Base",Benefits!$CS:$CS,$A24) -> 0.52 | C24: =SUMIFS(Benefits!$T:$T,Benefits!$E:$E,"Revenue",Benefits!$F:$F,"USD",Benefits!$D:$D,"Plan Base",Benefits!$CS:$CS,$A24) -> 2.32 | D24: =SUMIFS(Benefits!$U:$U,Benefits!$E:$E,"Revenue",Benefits!$F:$F,"USD",Benefits!$D:$D,"Plan Base",Benefits!$CS:$CS,$A24) -> 3.96 | E24: =SUMIFS(Benefits!$V:$V,Benefits!$E:$E,"Revenue",Benefits!$F:$F,"USD",Benefits!$D:$D,"Plan Base",Benefits!$CS:$CS,$A24) -> 3.96 | F24: =SUMIFS(Benefits!$W:$W,Benefits!$E:$E,"Revenue",Benefits!$F:$F,"USD",Benefits!$D:$D,"Plan Base",Benefits!$CS:$CS,$A24) -> 3.96 | H24: =SUMIFS(Benefits!$AD:$AD,Benefits!$E:$E,"Revenue",Benefits!$F:$F,"USD",Benefits!$D:$D,"Plan Base",Benefits!$CS:$CS,$A24) -> 0 | I24: =SUMIFS(Benefits!$AE:$AE,Benefits!$E:$E,"Revenue",Benefits!$F:$F,"USD",Benefits!$D:$D,"Plan Base",Benefits!$CS:$CS,$A24) -> 0 | J24: =SUMIFS(Benefits!$AF:$AF,Benefits!$E:$E,"Revenue",Benefits!$F:$F,"USD",Benefits!$D:$D,"Plan Base",Benefits!$CS:$CS,$A24) -> 0 | K24: =SUMIFS(Benefits!$AG:$AG,Benefits!$E:$E,"Revenue",Benefits!$F:$F,"USD",Benefits!$D:$D,"Plan Base",Benefits!$CS:$CS,$A24) -> 0 | L24: =SUMIFS(Benefits!$AH:$AH,Benefits!$E:$E,"Revenue",Benefits!$F:$F,"USD",Benefits!$D:$D,"Plan Base",Benefits!$CS:$CS,$A24) -> 0 | M24: =SUMIFS(Benefits!$AI:$AI,Benefits!$E:$E,"Revenue",Benefits!$F:$F,"USD",Benefits!$D:$D,"Plan Base",Benefits!$CS:$CS,$A24) -> 0.52 | N24: =SUMIFS(Benefits!$AJ:$AJ,Benefits!$E:$E,"Revenue",Benefits!$F:$F,"USD",Benefits!$D:$D,"Plan Base",Benefits!$CS:$CS,$A24) -> 0.091666667 | O24: =SUMIFS(Benefits!$AK:$AK,Benefits!$E:$E,"Revenue",Benefits!$F:$F,"USD",Benefits!$D:$D,"Plan Base",Benefits!$CS:$CS,$A24) -> 0.091666667 | P24: =SUMIFS(Benefits!$AL:$AL,Benefits!$E:$E,"Revenue",Benefits!$F:$F,"USD",Benefits!$D:$D,"Plan Base",Benefits!$CS:$CS,$A24) -> 0.091666667 | Q24: =SUMIFS(Benefits!$AM:$AM,Benefits!$E:$E,"Revenue",Benefits!$F:$F,"USD",Benefits!$D:$D,"Plan Base",Benefits!$CS:$CS,$A24) -> 0.13611111 | R24: =SUMIFS(Benefits!$AN:$AN,Benefits!$E:$E,"Revenue",Benefits!$F:$F,"USD",Benefits!$D:$D,"Plan Base",Benefits!$CS:$CS,$A24) -> 0.13611111 | S24: =SUMIFS(Benefits!$AO:$AO,Benefits!$E:$E,"Revenue",Benefits!$F:$F,"USD",Benefits!$D:$D,"Plan Base",Benefits!$CS:$CS,$A24) -> 0.13611111 | T24: =SUMIFS(Benefits!$AP:$AP,Benefits!$E:$E,"Revenue",Benefits!$F:$F,"USD",Benefits!$D:$D,"Plan Base",Benefits!$CS:$CS,$A24) -> 0.13611111 | U24: =SUMIFS(Benefits!$AQ:$AQ,Benefits!$E:$E,"Revenue",Benefits!$F:$F,"USD",Benefits!$D:$D,"Plan Base",Benefits!$CS:$CS,$A24) -> 0.13611111 | V24: =SUMIFS(Benefits!$AR:$AR,Benefits!$E:$E,"Revenue",Benefits!$F:$F,"USD",Benefits!$D:$D,"Plan Base",Benefits!$CS:$CS,$A24) -> 0.13611111 | W24: =SUMIFS(Benefits!$AS:$AS,Benefits!$E:$E,"Revenue",Benefits!$F:$F,"USD",Benefits!$D:$D,"Plan Base",Benefits!$CS:$CS,$A24) -> 0.13611111 | X24: =SUMIFS(Benefits!$AT:$AT,Benefits!$E:$E,"Revenue",Benefits!$F:$F,"USD",Benefits!$D:$D,"Plan Base",Benefits!$CS:$CS,$A24) -> 0.13611111 | Y24: =SUMIFS(Benefits!$AU:$AU,Benefits!$E:$E,"Revenue",Benefits!$F:$F,"USD",Benefits!$D:$D,"Plan Base",Benefits!$CS:$CS,$A24) -> 0.95611111 | Z24: =SUMIFS(Benefits!$AV:$AV,Benefits!$E:$E,"Revenue",Benefits!$F:$F,"USD",Benefits!$D:$D,"Plan Base",Benefits!$CS:$CS,$A24) -> 0.33 | AA24: =SUMIFS(Benefits!$AW:$AW,Benefits!$E:$E,"Revenue",Benefits!$F:$F,"USD",Benefits!$D:$D,"Plan Base",Benefits!$CS:$CS,$A24) -> 0.33 | AB24: =SUMIFS(Benefits!$AX:$AX,Benefits!$E:$E,"Revenue",Benefits!$F:$F,"USD",Benefits!$D:$D,"Plan Base",Benefits!$CS:$CS,$A24) -> 0.33 | AC24: =SUMIFS(Benefits!$AY:$AY,Benefits!$E:$E,"Revenue",Benefits!$F:$F,"USD",Benefits!$D:$D,"Plan Base",Benefits!$CS:$CS,$A24) -> 0.33 | AD24: =SUMIFS(Benefits!$AZ:$AZ,Benefits!$E:$E,"Revenue",Benefits!$F:$F,"USD",Benefits!$D:$D,"Plan Base",Benefits!$CS:$CS,$A24) -> 0.33 | AE24: =SUMIFS(Benefits!$BA:$BA,Benefits!$E:$E,"Revenue",Benefits!$F:$F,"USD",Benefits!$D:$D,"Plan Base",Benefits!$CS:$CS,$A24) -> 0.33 | AF24: =SUMIFS(Benefits!$BB:$BB,Benefits!$E:$E,"Revenue",Benefits!$F:$F,"USD",Benefits!$D:$D,"Plan Base",Benefits!$CS:$CS,$A24) -> 0.33 | AG24: =SUMIFS(Benefits!$BC:$BC,Benefits!$E:$E,"Revenue",Benefits!$F:$F,"USD",Benefits!$D:$D,"Plan Base",Benefits!$CS:$CS,$A24) -> 0.33 | AH24: =SUMIFS(Benefits!$BD:$BD,Benefits!$E:$E,"Revenue",Benefits!$F:$F,"USD",Benefits!$D:$D,"Plan Base",Benefits!$CS:$CS,$A24) -> 0.33 | AI24: =SUMIFS(Benefits!$BE:$BE,Benefits!$E:$E,"Revenue",Benefits!$F:$F,"USD",Benefits!$D:$D,"Plan Base",Benefits!$CS:$CS,$A24) -> 0.33 | AJ24: =SUMIFS(Benefits!$BF:$BF,Benefits!$E:$E,"Revenue",Benefits!$F:$F,"USD",Benefits!$D:$D,"Plan Base",Benefits!$CS:$CS,$A24) -> 0.33 | AK24: =SUMIFS(Benefits!$BG:$BG,Benefits!$E:$E,"Revenue",Benefits!$F:$F,"USD",Benefits!$D:$D,"Plan Base",Benefits!$CS:$CS,$A24) -> 0.33 | AL24: =SUMIFS(Benefits!$BH:$BH,Benefits!$E:$E,"Revenue",Benefits!$F:$F,"USD",Benefits!$D:$D,"Plan Base",Benefits!$CS:$CS,$A24) -> 0.33 | AM24: =SUMIFS(Benefits!$BI:$BI,Benefits!$E:$E,"Revenue",Benefits!$F:$F,"USD",Benefits!$D:$D,"Plan Base",Benefits!$CS:$CS,$A24) -> 0.33 | AN24: =SUMIFS(Benefits!$BJ:$BJ,Benefits!$E:$E,"Revenue",Benefits!$F:$F,"USD",Benefits!$D:$D,"Plan Base",Benefits!$CS:$CS,$A24) -> 0.33 | AO24: =SUMIFS(Benefits!$BK:$BK,Benefits!$E:$E,"Revenue",Benefits!$F:$F,"USD",Benefits!$D:$D,"Plan Base",Benefits!$CS:$CS,$A24) -> 0.33 | AP24: =SUMIFS(Benefits!$BL:$BL,Benefits!$E:$E,"Revenue",Benefits!$F:$F,"USD",Benefits!$D:$D,"Plan Base",Benefits!$CS:$CS,$A24) -> 0.33 | AQ24: =SUMIFS(Benefits!$BM:$BM,Benefits!$E:$E,"Revenue",Benefits!$F:$F,"USD",Benefits!$D:$D,"Plan Base",Benefits!$CS:$CS,$A24) -> 0.33 | AR24: =SUMIFS(Benefits!$BN:$BN,Benefits!$E:$E,"Revenue",Benefits!$F:$F,"USD",Benefits!$D:$D,"Plan Base",Benefits!$CS:$CS,$A24) -> 0.33 | AS24: =SUMIFS(Benefits!$BO:$BO,Benefits!$E:$E,"Revenue",Benefits!$F:$F,"USD",Benefits!$D:$D,"Plan Base",Benefits!$CS:$CS,$A24) -> 0.33 | AT24: =SUMIFS(Benefits!$BP:$BP,Benefits!$E:$E,"Revenue",Benefits!$F:$F,"USD",Benefits!$D:$D,"Plan Base",Benefits!$CS:$CS,$A24) -> 0.33 | AU24: =SUMIFS(Benefits!$BQ:$BQ,Benefits!$E:$E,"Revenue",Benefits!$F:$F,"USD",Benefits!$D:$D,"Plan Base",Benefits!$CS:$CS,$A24) -> 0.33 | AV24: =SUMIFS(Benefits!$BR:$BR,Benefits!$E:$E,"Revenue",Benefits!$F:$F,"USD",Benefits!$D:$D,"Plan Base",Benefits!$CS:$CS,$A24) -> 0.33 | AW24: =SUMIFS(Benefits!$BS:$BS,Benefits!$E:$E,"Revenue",Benefits!$F:$F,"USD",Benefits!$D:$D,"Plan Base",Benefits!$CS:$CS,$A24) -> 0.33 | AX24: =SUMIFS(Benefits!$BT:$BT,Benefits!$E:$E,"Revenue",Benefits!$F:$F,"USD",Benefits!$D:$D,"Plan Base",Benefits!$CS:$CS,$A24) -> 0.33 | AY24: =SUMIFS(Benefits!$BU:$BU,Benefits!$E:$E,"Revenue",Benefits!$F:$F,"USD",Benefits!$D:$D,"Plan Base",Benefits!$CS:$CS,$A24) -> 0.33 | AZ24: =SUMIFS(Benefits!$BV:$BV,Benefits!$E:$E,"Revenue",Benefits!$F:$F,"USD",Benefits!$D:$D,"Plan Base",Benefits!$CS:$CS,$A24) -> 0.33 | BA24: =SUMIFS(Benefits!$BW:$BW,Benefits!$E:$E,"Revenue",Benefits!$F:$F,"USD",Benefits!$D:$D,"Plan Base",Benefits!$CS:$CS,$A24) -> 0.33 | BB24: =SUMIFS(Benefits!$BX:$BX,Benefits!$E:$E,"Revenue",Benefits!$F:$F,"USD",Benefits!$D:$D,"Plan Base",Benefits!$CS:$CS,$A24) -> 0.33 | BC24: =SUMIFS(Benefits!$BY:$BY,Benefits!$E:$E,"Revenue",Benefits!$F:$F,"USD",Benefits!$D:$D,"Plan Base",Benefits!$CS:$CS,$A24) -> 0.33 | BD24: =SUMIFS(Benefits!$BZ:$BZ,Benefits!$E:$E,"Revenue",Benefits!$F:$F,"USD",Benefits!$D:$D,"Plan Base",Benefits!$CS:$CS,$A24) -> 0.33 | BE24: =SUMIFS(Benefits!$CA:$CA,Benefits!$E:$E,"Revenue",Benefits!$F:$F,"USD",Benefits!$D:$D,"Plan Base",Benefits!$CS:$CS,$A24) -> 0.33 | BF24: =SUMIFS(Benefits!$CB:$CB,Benefits!$E:$E,"Revenue",Benefits!$F:$F,"USD",Benefits!$D:$D,"Plan Base",Benefits!$CS:$CS,$A24) -> 0.33 | BG24: =SUMIFS(Benefits!$CC:$CC,Benefits!$E:$E,"Revenue",Benefits!$F:$F,"USD",Benefits!$D:$D,"Plan Base",Benefits!$CS:$CS,$A24) -> 0.33 | BH24: =SUMIFS(Benefits!$CD:$CD,Benefits!$E:$E,"Revenue",Benefits!$F:$F,"USD",Benefits!$D:$D,"Plan Base",Benefits!$CS:$CS,$A24) -> 0.33 | BI24: =SUMIFS(Benefits!$CE:$CE,Benefits!$E:$E,"Revenue",Benefits!$F:$F,"USD",Benefits!$D:$D,"Plan Base",Benefits!$CS:$CS,$A24) -> 0.33
A25: Eastbridge Region | B25: =SUMIFS(Benefits!$S:$S,Benefits!$E:$E,"Revenue",Benefits!$F:$F,"USD",Benefits!$D:$D,"Plan Base",Benefits!$CS:$CS,$A25) -> 0 | C25: =SUMIFS(Benefits!$T:$T,Benefits!$E:$E,"Revenue",Benefits!$F:$F,"USD",Benefits!$D:$D,"Plan Base",Benefits!$CS:$CS,$A25) -> 1.385 | D25: =SUMIFS(Benefits!$U:$U,Benefits!$E:$E,"Revenue",Benefits!$F:$F,"USD",Benefits!$D:$D,"Plan Base",Benefits!$CS:$CS,$A25) -> 3.764 | E25: =SUMIFS(Benefits!$V:$V,Benefits!$E:$E,"Revenue",Benefits!$F:$F,"USD",Benefits!$D:$D,"Plan Base",Benefits!$CS:$CS,$A25) -> 3.764 | F25: =SUMIFS(Benefits!$W:$W,Benefits!$E:$E,"Revenue",Benefits!$F:$F,"USD",Benefits!$D:$D,"Plan Base",Benefits!$CS:$CS,$A25) -> 3.764 | H25: =SUMIFS(Benefits!$AD:$AD,Benefits!$E:$E,"Revenue",Benefits!$F:$F,"USD",Benefits!$D:$D,"Plan Base",Benefits!$CS:$CS,$A25) -> 0 | I25: =SUMIFS(Benefits!$AE:$AE,Benefits!$E:$E,"Revenue",Benefits!$F:$F,"USD",Benefits!$D:$D,"Plan Base",Benefits!$CS:$CS,$A25) -> 0 | J25: =SUMIFS(Benefits!$AF:$AF,Benefits!$E:$E,"Revenue",Benefits!$F:$F,"USD",Benefits!$D:$D,"Plan Base",Benefits!$CS:$CS,$A25) -> 0 | K25: =SUMIFS(Benefits!$AG:$AG,Benefits!$E:$E,"Revenue",Benefits!$F:$F,"USD",Benefits!$D:$D,"Plan Base",Benefits!$CS:$CS,$A25) -> 0 | L25: =SUMIFS(Benefits!$AH:$AH,Benefits!$E:$E,"Revenue",Benefits!$F:$F,"USD",Benefits!$D:$D,"Plan Base",Benefits!$CS:$CS,$A25) -> 0 | M25: =SUMIFS(Benefits!$AI:$AI,Benefits!$E:$E,"Revenue",Benefits!$F:$F,"USD",Benefits!$D:$D,"Plan Base",Benefits!$CS:$CS,$A25) -> 0 | N25: =SUMIFS(Benefits!$AJ:$AJ,Benefits!$E:$E,"Revenue",Benefits!$F:$F,"USD",Benefits!$D:$D,"Plan Base",Benefits!$CS:$CS,$A25) -> 0 | O25: =SUMIFS(Benefits!$AK:$AK,Benefits!$E:$E,"Revenue",Benefits!$F:$F,"USD",Benefits!$D:$D,"Plan Base",Benefits!$CS:$CS,$A25) -> 0 | P25: =SUMIFS(Benefits!$AL:$AL,Benefits!$E:$E,"Revenue",Benefits!$F:$F,"USD",Benefits!$D:$D,"Plan Base",Benefits!$CS:$CS,$A25) -> 0 | Q25: =SUMIFS(Benefits!$AM:$AM,Benefits!$E:$E,"Revenue",Benefits!$F:$F,"USD",Benefits!$D:$D,"Plan Base",Benefits!$CS:$CS,$A25) -> 0 | R25: =SUMIFS(Benefits!$AN:$AN,Benefits!$E:$E,"Revenue",Benefits!$F:$F,"USD",Benefits!$D:$D,"Plan Base",Benefits!$CS:$CS,$A25) -> 0 | S25: =SUMIFS(Benefits!$AO:$AO,Benefits!$E:$E,"Revenue",Benefits!$F:$F,"USD",Benefits!$D:$D,"Plan Base",Benefits!$CS:$CS,$A25) -> 0 | T25: =SUMIFS(Benefits!$AP:$AP,Benefits!$E:$E,"Revenue",Benefits!$F:$F,"USD",Benefits!$D:$D,"Plan Base",Benefits!$CS:$CS,$A25) -> 0.15716667 | U25: =SUMIFS(Benefits!$AQ:$AQ,Benefits!$E:$E,"Revenue",Benefits!$F:$F,"USD",Benefits!$D:$D,"Plan Base",Benefits!$CS:$CS,$A25) -> 0.15716667 | V25: =SUMIFS(Benefits!$AR:$AR,Benefits!$E:$E,"Revenue",Benefits!$F:$F,"USD",Benefits!$D:$D,"Plan Base",Benefits!$CS:$CS,$A25) -> 0.26766667 | W25: =SUMIFS(Benefits!$AS:$AS,Benefits!$E:$E,"Revenue",Benefits!$F:$F,"USD",Benefits!$D:$D,"Plan Base",Benefits!$CS:$CS,$A25) -> 0.26766667 | X25: =SUMIFS(Benefits!$AT:$AT,Benefits!$E:$E,"Revenue",Benefits!$F:$F,"USD",Benefits!$D:$D,"Plan Base",Benefits!$CS:$CS,$A25) -> 0.26766667 | Y25: =SUMIFS(Benefits!$AU:$AU,Benefits!$E:$E,"Revenue",Benefits!$F:$F,"USD",Benefits!$D:$D,"Plan Base",Benefits!$CS:$CS,$A25) -> 0.26766667 | Z25: =SUMIFS(Benefits!$AV:$AV,Benefits!$E:$E,"Revenue",Benefits!$F:$F,"USD",Benefits!$D:$D,"Plan Base",Benefits!$CS:$CS,$A25) -> 0.31366667 | AA25: =SUMIFS(Benefits!$AW:$AW,Benefits!$E:$E,"Revenue",Benefits!$F:$F,"USD",Benefits!$D:$D,"Plan Base",Benefits!$CS:$CS,$A25) -> 0.31366667 | AB25: =SUMIFS(Benefits!$AX:$AX,Benefits!$E:$E,"Revenue",Benefits!$F:$F,"USD",Benefits!$D:$D,"Plan Base",Benefits!$CS:$CS,$A25) -> 0.31366667 | AC25: =SUMIFS(Benefits!$AY:$AY,Benefits!$E:$E,"Revenue",Benefits!$F:$F,"USD",Benefits!$D:$D,"Plan Base",Benefits!$CS:$CS,$A25) -> 0.31366667 | AD25: =SUMIFS(Benefits!$AZ:$AZ,Benefits!$E:$E,"Revenue",Benefits!$F:$F,"USD",Benefits!$D:$D,"Plan Base",Benefits!$CS:$CS,$A25) -> 0.31366667 | AE25: =SUMIFS(Benefits!$BA:$BA,Benefits!$E:$E,"Revenue",Benefits!$F:$F,"USD",Benefits!$D:$D,"Plan Base",Benefits!$CS:$CS,$A25) -> 0.31366667 | AF25: =SUMIFS(Benefits!$BB:$BB,Benefits!$E:$E,"Revenue",Benefits!$F:$F,"USD",Benefits!$D:$D,"Plan Base",Benefits!$CS:$CS,$A25) -> 0.31366667 | AG25: =SUMIFS(Benefits!$BC:$BC,Benefits!$E:$E,"Revenue",Benefits!$F:$F,"USD",Benefits!$D:$D,"Plan Base",Benefits!$CS:$CS,$A25) -> 0.31366667 | AH25: =SUMIFS(Benefits!$BD:$BD,Benefits!$E:$E,"Revenue",Benefits!$F:$F,"USD",Benefits!$D:$D,"Plan Base",Benefits!$CS:$CS,$A25) -> 0.31366667 | AI25: =SUMIFS(Benefits!$BE:$BE,Benefits!$E:$E,"Revenue",Benefits!$F:$F,"USD",Benefits!$D:$D,"Plan Base",Benefits!$CS:$CS,$A25) -> 0.31366667 | AJ25: =SUMIFS(Benefits!$BF:$BF,Benefits!$E:$E,"Revenue",Benefits!$F:$F,"USD",Benefits!$D:$D,"Plan Base",Benefits!$CS:$CS,$A25) -> 0.31366667 | AK25: =SUMIFS(Benefits!$BG:$BG,Benefits!$E:$E,"Revenue",Benefits!$F:$F,"USD",Benefits!$D:$D,"Plan Base",Benefits!$CS:$CS,$A25) -> 0.31366667 | AL25: =SUMIFS(Benefits!$BH:$BH,Benefits!$E:$E,"Revenue",Benefits!$F:$F,"USD",Benefits!$D:$D,"Plan Base",Benefits!$CS:$CS,$A25) -> 0.31366667 | AM25: =SUMIFS(Benefits!$BI:$BI,Benefits!$E:$E,"Revenue",Benefits!$F:$F,"USD",Benefits!$D:$D,"Plan Base",Benefits!$CS:$CS,$A25) -> 0.31366667 | AN25: =SUMIFS(Benefits!$BJ:$BJ,Benefits!$E:$E,"Revenue",Benefits!$F:$F,"USD",Benefits!$D:$D,"Plan Base",Benefits!$CS:$CS,$A25) -> 0.31366667 | AO25: =SUMIFS(Benefits!$BK:$BK,Benefits!$E:$E,"Revenue",Benefits!$F:$F,"USD",Benefits!$D:$D,"Plan Base",Benefits!$CS:$CS,$A25) -> 0.31366667 | AP25: =SUMIFS(Benefits!$BL:$BL,Benefits!$E:$E,"Revenue",Benefits!$F:$F,"USD",Benefits!$D:$D,"Plan Base",Benefits!$CS:$CS,$A25) -> 0.31366667 | AQ25: =SUMIFS(Benefits!$BM:$BM,Benefits!$E:$E,"Revenue",Benefits!$F:$F,"USD",Benefits!$D:$D,"Plan Base",Benefits!$CS:$CS,$A25) -> 0.31366667 | AR25: =SUMIFS(Benefits!$BN:$BN,Benefits!$E:$E,"Revenue",Benefits!$F:$F,"USD",Benefits!$D:$D,"Plan Base",Benefits!$CS:$CS,$A25) -> 0.31366667 | AS25: =SUMIFS(Benefits!$BO:$BO,Benefits!$E:$E,"Revenue",Benefits!$F:$F,"USD",Benefits!$D:$D,"Plan Base",Benefits!$CS:$CS,$A25) -> 0.31366667 | AT25: =SUMIFS(Benefits!$BP:$BP,Benefits!$E:$E,"Revenue",Benefits!$F:$F,"USD",Benefits!$D:$D,"Plan Base",Benefits!$CS:$CS,$A25) -> 0.31366667 | AU25: =SUMIFS(Benefits!$BQ:$BQ,Benefits!$E:$E,"Revenue",Benefits!$F:$F,"USD",Benefits!$D:$D,"Plan Base",Benefits!$CS:$CS,$A25) -> 0.31366667 | AV25: =SUMIFS(Benefits!$BR:$BR,Benefits!$E:$E,"Revenue",Benefits!$F:$F,"USD",Benefits!$D:$D,"Plan Base",Benefits!$CS:$CS,$A25) -> 0.31366667 | AW25: =SUMIFS(Benefits!$BS:$BS,Benefits!$E:$E,"Revenue",Benefits!$F:$F,"USD",Benefits!$D:$D,"Plan Base",Benefits!$CS:$CS,$A25) -> 0.31366667 | AX25: =SUMIFS(Benefits!$BT:$BT,Benefits!$E:$E,"Revenue",Benefits!$F:$F,"USD",Benefits!$D:$D,"Plan Base",Benefits!$CS:$CS,$A25) -> 0.31366667 | AY25: =SUMIFS(Benefits!$BU:$BU,Benefits!$E:$E,"Revenue",Benefits!$F:$F,"USD",Benefits!$D:$D,"Plan Base",Benefits!$CS:$CS,$A25) -> 0.31366667 | AZ25: =SUMIFS(Benefits!$BV:$BV,Benefits!$E:$E,"Revenue",Benefits!$F:$F,"USD",Benefits!$D:$D,"Plan Base",Benefits!$CS:$CS,$A25) -> 0.31366667 | BA25: =SUMIFS(Benefits!$BW:$BW,Benefits!$E:$E,"Revenue",Benefits!$F:$F,"USD",Benefits!$D:$D,"Plan Base",Benefits!$CS:$CS,$A25) -> 0.31366667 | BB25: =SUMIFS(Benefits!$BX:$BX,Benefits!$E:$E,"Revenue",Benefits!$F:$F,"USD",Benefits!$D:$D,"Plan Base",Benefits!$CS:$CS,$A25) -> 0.31366667 | BC25: =SUMIFS(Benefits!$BY:$BY,Benefits!$E:$E,"Revenue",Benefits!$F:$F,"USD",Benefits!$D:$D,"Plan Base",Benefits!$CS:$CS,$A25) -> 0.31366667 | BD25: =SUMIFS(Benefits!$BZ:$BZ,Benefits!$E:$E,"Revenue",Benefits!$F:$F,"USD",Benefits!$D:$D,"Plan Base",Benefits!$CS:$CS,$A25) -> 0.31366667 | BE25: =SUMIFS(Benefits!$CA:$CA,Benefits!$E:$E,"Revenue",Benefits!$F:$F,"USD",Benefits!$D:$D,"Plan Base",Benefits!$CS:$CS,$A25) -> 0.31366667 | BF25: =SUMIFS(Benefits!$CB:$CB,Benefits!$E:$E,"Revenue",Benefits!$F:$F,"USD",Benefits!$D:$D,"Plan Base",Benefits!$CS:$CS,$A25) -> 0.31366667 | BG25: =SUMIFS(Benefits!$CC:$CC,Benefits!$E:$E,"Revenue",Benefits!$F:$F,"USD",Benefits!$D:$D,"Plan Base",Benefits!$CS:$CS,$A25) -> 0.31366667 | BH25: =SUMIFS(Benefits!$CD:$CD,Benefits!$E:$E,"Revenue",Benefits!$F:$F,"USD",Benefits!$D:$D,"Plan Base",Benefits!$CS:$CS,$A25) -> 0.31366667 | BI25: =SUMIFS(Benefits!$CE:$CE,Benefits!$E:$E,"Revenue",Benefits!$F:$F,"USD",Benefits!$D:$D,"Plan Base",Benefits!$CS:$CS,$A25) -> 0.31366667
A26: Northpeak Region | B26: =SUMIFS(Benefits!$S:$S,Benefits!$E:$E,"Revenue",Benefits!$F:$F,"USD",Benefits!$D:$D,"Plan Base",Benefits!$CS:$CS,$A26) -> 0.572 | C26: =SUMIFS(Benefits!$T:$T,Benefits!$E:$E,"Revenue",Benefits!$F:$F,"USD",Benefits!$D:$D,"Plan Base",Benefits!$CS:$CS,$A26) -> 2.366 | D26: =SUMIFS(Benefits!$U:$U,Benefits!$E:$E,"Revenue",Benefits!$F:$F,"USD",Benefits!$D:$D,"Plan Base",Benefits!$CS:$CS,$A26) -> 3.678 | E26: =SUMIFS(Benefits!$V:$V,Benefits!$E:$E,"Revenue",Benefits!$F:$F,"USD",Benefits!$D:$D,"Plan Base",Benefits!$CS:$CS,$A26) -> 3.678 | F26: =SUMIFS(Benefits!$W:$W,Benefits!$E:$E,"Revenue",Benefits!$F:$F,"USD",Benefits!$D:$D,"Plan Base",Benefits!$CS:$CS,$A26) -> 3.678 | H26: =SUMIFS(Benefits!$AD:$AD,Benefits!$E:$E,"Revenue",Benefits!$F:$F,"USD",Benefits!$D:$D,"Plan Base",Benefits!$CS:$CS,$A26) -> 0 | I26: =SUMIFS(Benefits!$AE:$AE,Benefits!$E:$E,"Revenue",Benefits!$F:$F,"USD",Benefits!$D:$D,"Plan Base",Benefits!$CS:$CS,$A26) -> 0 | J26: =SUMIFS(Benefits!$AF:$AF,Benefits!$E:$E,"Revenue",Benefits!$F:$F,"USD",Benefits!$D:$D,"Plan Base",Benefits!$CS:$CS,$A26) -> 0 | K26: =SUMIFS(Benefits!$AG:$AG,Benefits!$E:$E,"Revenue",Benefits!$F:$F,"USD",Benefits!$D:$D,"Plan Base",Benefits!$CS:$CS,$A26) -> 0 | L26: =SUMIFS(Benefits!$AH:$AH,Benefits!$E:$E,"Revenue",Benefits!$F:$F,"USD",Benefits!$D:$D,"Plan Base",Benefits!$CS:$CS,$A26) -> 0 | M26: =SUMIFS(Benefits!$AI:$AI,Benefits!$E:$E,"Revenue",Benefits!$F:$F,"USD",Benefits!$D:$D,"Plan Base",Benefits!$CS:$CS,$A26) -> 0.572 | N26: =SUMIFS(Benefits!$AJ:$AJ,Benefits!$E:$E,"Revenue",Benefits!$F:$F,"USD",Benefits!$D:$D,"Plan Base",Benefits!$CS:$CS,$A26) -> 0.10083333 | O26: =SUMIFS(Benefits!$AK:$AK,Benefits!$E:$E,"Revenue",Benefits!$F:$F,"USD",Benefits!$D:$D,"Plan Base",Benefits!$CS:$CS,$A26) -> 0.10083333 | P26: =SUMIFS(Benefits!$AL:$AL,Benefits!$E:$E,"Revenue",Benefits!$F:$F,"USD",Benefits!$D:$D,"Plan Base",Benefits!$CS:$CS,$A26) -> 0.10083333 | Q26: =SUMIFS(Benefits!$AM:$AM,Benefits!$E:$E,"Revenue",Benefits!$F:$F,"USD",Benefits!$D:$D,"Plan Base",Benefits!$CS:$CS,$A26) -> 0.10083333 | R26: =SUMIFS(Benefits!$AN:$AN,Benefits!$E:$E,"Revenue",Benefits!$F:$F,"USD",Benefits!$D:$D,"Plan Base",Benefits!$CS:$CS,$A26) -> 0.10083333 | S26: =SUMIFS(Benefits!$AO:$AO,Benefits!$E:$E,"Revenue",Benefits!$F:$F,"USD",Benefits!$D:$D,"Plan Base",Benefits!$CS:$CS,$A26) -> 0.10083333 | T26: =SUMIFS(Benefits!$AP:$AP,Benefits!$E:$E,"Revenue",Benefits!$F:$F,"USD",Benefits!$D:$D,"Plan Base",Benefits!$CS:$CS,$A26) -> 0.10083333 | U26: =SUMIFS(Benefits!$AQ:$AQ,Benefits!$E:$E,"Revenue",Benefits!$F:$F,"USD",Benefits!$D:$D,"Plan Base",Benefits!$CS:$CS,$A26) -> 0.20083333 | V26: =SUMIFS(Benefits!$AR:$AR,Benefits!$E:$E,"Revenue",Benefits!$F:$F,"USD",Benefits!$D:$D,"Plan Base",Benefits!$CS:$CS,$A26) -> 0.20083333 | W26: =SUMIFS(Benefits!$AS:$AS,Benefits!$E:$E,"Revenue",Benefits!$F:$F,"USD",Benefits!$D:$D,"Plan Base",Benefits!$CS:$CS,$A26) -> 0.4195 | X26: =SUMIFS(Benefits!$AT:$AT,Benefits!$E:$E,"Revenue",Benefits!$F:$F,"USD",Benefits!$D:$D,"Plan Base",Benefits!$CS:$CS,$A26) -> 0.4195 | Y26: =SUMIFS(Benefits!$AU:$AU,Benefits!$E:$E,"Revenue",Benefits!$F:$F,"USD",Benefits!$D:$D,"Plan Base",Benefits!$CS:$CS,$A26) -> 0.4195 | Z26: =SUMIFS(Benefits!$AV:$AV,Benefits!$E:$E,"Revenue",Benefits!$F:$F,"USD",Benefits!$D:$D,"Plan Base",Benefits!$CS:$CS,$A26) -> 0.3065 | AA26: =SUMIFS(Benefits!$AW:$AW,Benefits!$E:$E,"Revenue",Benefits!$F:$F,"USD",Benefits!$D:$D,"Plan Base",Benefits!$CS:$CS,$A26) -> 0.3065 | AB26: =SUMIFS(Benefits!$AX:$AX,Benefits!$E:$E,"Revenue",Benefits!$F:$F,"USD",Benefits!$D:$D,"Plan Base",Benefits!$CS:$CS,$A26) -> 0.3065 | AC26: =SUMIFS(Benefits!$AY:$AY,Benefits!$E:$E,"Revenue",Benefits!$F:$F,"USD",Benefits!$D:$D,"Plan Base",Benefits!$CS:$CS,$A26) -> 0.3065 | AD26: =SUMIFS(Benefits!$AZ:$AZ,Benefits!$E:$E,"Revenue",Benefits!$F:$F,"USD",Benefits!$D:$D,"Plan Base",Benefits!$CS:$CS,$A26) -> 0.3065 | AE26: =SUMIFS(Benefits!$BA:$BA,Benefits!$E:$E,"Revenue",Benefits!$F:$F,"USD",Benefits!$D:$D,"Plan Base",Benefits!$CS:$CS,$A26) -> 0.3065 | AF26: =SUMIFS(Benefits!$BB:$BB,Benefits!$E:$E,"Revenue",Benefits!$F:$F,"USD",Benefits!$D:$D,"Plan Base",Benefits!$CS:$CS,$A26) -> 0.3065 | AG26: =SUMIFS(Benefits!$BC:$BC,Benefits!$E:$E,"Revenue",Benefits!$F:$F,"USD",Benefits!$D:$D,"Plan Base",Benefits!$CS:$CS,$A26) -> 0.3065 | AH26: =SUMIFS(Benefits!$BD:$BD,Benefits!$E:$E,"Revenue",Benefits!$F:$F,"USD",Benefits!$D:$D,"Plan Base",Benefits!$CS:$CS,$A26) -> 0.3065 | AI26: =SUMIFS(Benefits!$BE:$BE,Benefits!$E:$E,"Revenue",Benefits!$F:$F,"USD",Benefits!$D:$D,"Plan Base",Benefits!$CS:$CS,$A26) -> 0.3065 | AJ26: =SUMIFS(Benefits!$BF:$BF,Benefits!$E:$E,"Revenue",Benefits!$F:$F,"USD",Benefits!$D:$D,"Plan Base",Benefits!$CS:$CS,$A26) -> 0.3065 | AK26: =SUMIFS(Benefits!$BG:$BG,Benefits!$E:$E,"Revenue",Benefits!$F:$F,"USD",Benefits!$D:$D,"Plan Base",Benefits!$CS:$CS,$A26) -> 0.3065 | AL26: =SUMIFS(Benefits!$BH:$BH,Benefits!$E:$E,"Revenue",Benefits!$F:$F,"USD",Benefits!$D:$D,"Plan Base",Benefits!$CS:$CS,$A26) -> 0.3065 | AM26: =SUMIFS(Benefits!$BI:$BI,Benefits!$E:$E,"Revenue",Benefits!$F:$F,"USD",Benefits!$D:$D,"Plan Base",Benefits!$CS:$CS,$A26) -> 0.3065 | AN26: =SUMIFS(Benefits!$BJ:$BJ,Benefits!$E:$E,"Revenue",Benefits!$F:$F,"USD",Benefits!$D:$D,"Plan Base",Benefits!$CS:$CS,$A26) -> 0.3065 | AO26: =SUMIFS(Benefits!$BK:$BK,Benefits!$E:$E,"Revenue",Benefits!$F:$F,"USD",Benefits!$D:$D,"Plan Base",Benefits!$CS:$CS,$A26) -> 0.3065 | AP26: =SUMIFS(Benefits!$BL:$BL,Benefits!$E:$E,"Revenue",Benefits!$F:$F,"USD",Benefits!$D:$D,"Plan Base",Benefits!$CS:$CS,$A26) -> 0.3065 | AQ26: =SUMIFS(Benefits!$BM:$BM,Benefits!$E:$E,"Revenue",Benefits!$F:$F,"USD",Benefits!$D:$D,"Plan Base",Benefits!$CS:$CS,$A26) -> 0.3065 | AR26: =SUMIFS(Benefits!$BN:$BN,Benefits!$E:$E,"Revenue",Benefits!$F:$F,"USD",Benefits!$D:$D,"Plan Base",Benefits!$CS:$CS,$A26) -> 0.3065 | AS26: =SUMIFS(Benefits!$BO:$BO,Benefits!$E:$E,"Revenue",Benefits!$F:$F,"USD",Benefits!$D:$D,"Plan Base",Benefits!$CS:$CS,$A26) -> 0.3065 | AT26: =SUMIFS(Benefits!$BP:$BP,Benefits!$E:$E,"Revenue",Benefits!$F:$F,"USD",Benefits!$D:$D,"Plan Base",Benefits!$CS:$CS,$A26) -> 0.3065 | AU26: =SUMIFS(Benefits!$BQ:$BQ,Benefits!$E:$E,"Revenue",Benefits!$F:$F,"USD",Benefits!$D:$D,"Plan Base",Benefits!$CS:$CS,$A26) -> 0.3065 | AV26: =SUMIFS(Benefits!$BR:$BR,Benefits!$E:$E,"Revenue",Benefits!$F:$F,"USD",Benefits!$D:$D,"Plan Base",Benefits!$CS:$CS,$A26) -> 0.3065 | AW26: =SUMIFS(Benefits!$BS:$BS,Benefits!$E:$E,"Revenue",Benefits!$F:$F,"USD",Benefits!$D:$D,"Plan Base",Benefits!$CS:$CS,$A26) -> 0.3065 | AX26: =SUMIFS(Benefits!$BT:$BT,Benefits!$E:$E,"Revenue",Benefits!$F:$F,"USD",Benefits!$D:$D,"Plan Base",Benefits!$CS:$CS,$A26) -> 0.3065 | AY26: =SUMIFS(Benefits!$BU:$BU,Benefits!$E:$E,"Revenue",Benefits!$F:$F,"USD",Benefits!$D:$D,"Plan Base",Benefits!$CS:$CS,$A26) -> 0.3065 | AZ26: =SUMIFS(Benefits!$BV:$BV,Benefits!$E:$E,"Revenue",Benefits!$F:$F,"USD",Benefits!$D:$D,"Plan Base",Benefits!$CS:$CS,$A26) -> 0.3065 | BA26: =SUMIFS(Benefits!$BW:$BW,Benefits!$E:$E,"Revenue",Benefits!$F:$F,"USD",Benefits!$D:$D,"Plan Base",Benefits!$CS:$CS,$A26) -> 0.3065 | BB26: =SUMIFS(Benefits!$BX:$BX,Benefits!$E:$E,"Revenue",Benefits!$F:$F,"USD",Benefits!$D:$D,"Plan Base",Benefits!$CS:$CS,$A26) -> 0.3065 | BC26: =SUMIFS(Benefits!$BY:$BY,Benefits!$E:$E,"Revenue",Benefits!$F:$F,"USD",Benefits!$D:$D,"Plan Base",Benefits!$CS:$CS,$A26) -> 0.3065 | BD26: =SUMIFS(Benefits!$BZ:$BZ,Benefits!$E:$E,"Revenue",Benefits!$F:$F,"USD",Benefits!$D:$D,"Plan Base",Benefits!$CS:$CS,$A26) -> 0.3065 | BE26: =SUMIFS(Benefits!$CA:$CA,Benefits!$E:$E,"Revenue",Benefits!$F:$F,"USD",Benefits!$D:$D,"Plan Base",Benefits!$CS:$CS,$A26) -> 0.3065 | BF26: =SUMIFS(Benefits!$CB:$CB,Benefits!$E:$E,"Revenue",Benefits!$F:$F,"USD",Benefits!$D:$D,"Plan Base",Benefits!$CS:$CS,$A26) -> 0.3065 | BG26: =SUMIFS(Benefits!$CC:$CC,Benefits!$E:$E,"Revenue",Benefits!$F:$F,"USD",Benefits!$D:$D,"Plan Base",Benefits!$CS:$CS,$A26) -> 0.3065 | BH26: =SUMIFS(Benefits!$CD:$CD,Benefits!$E:$E,"Revenue",Benefits!$F:$F,"USD",Benefits!$D:$D,"Plan Base",Benefits!$CS:$CS,$A26) -> 0.3065 | BI26: =SUMIFS(Benefits!$CE:$CE,Benefits!$E:$E,"Revenue",Benefits!$F:$F,"USD",Benefits!$D:$D,"Plan Base",Benefits!$CS:$CS,$A26) -> 0.3065
A27: Southgate Region | B27: =SUMIFS(Benefits!$S:$S,Benefits!$E:$E,"Revenue",Benefits!$F:$F,"USD",Benefits!$D:$D,"Plan Base",Benefits!$CS:$CS,$A27) -> 0.598 | C27: =SUMIFS(Benefits!$T:$T,Benefits!$E:$E,"Revenue",Benefits!$F:$F,"USD",Benefits!$D:$D,"Plan Base",Benefits!$CS:$CS,$A27) -> 2.044 | D27: =SUMIFS(Benefits!$U:$U,Benefits!$E:$E,"Revenue",Benefits!$F:$F,"USD",Benefits!$D:$D,"Plan Base",Benefits!$CS:$CS,$A27) -> 3.602 | E27: =SUMIFS(Benefits!$V:$V,Benefits!$E:$E,"Revenue",Benefits!$F:$F,"USD",Benefits!$D:$D,"Plan Base",Benefits!$CS:$CS,$A27) -> 3.602 | F27: =SUMIFS(Benefits!$W:$W,Benefits!$E:$E,"Revenue",Benefits!$F:$F,"USD",Benefits!$D:$D,"Plan Base",Benefits!$CS:$CS,$A27) -> 3.602 | H27: =SUMIFS(Benefits!$AD:$AD,Benefits!$E:$E,"Revenue",Benefits!$F:$F,"USD",Benefits!$D:$D,"Plan Base",Benefits!$CS:$CS,$A27) -> 0 | I27: =SUMIFS(Benefits!$AE:$AE,Benefits!$E:$E,"Revenue",Benefits!$F:$F,"USD",Benefits!$D:$D,"Plan Base",Benefits!$CS:$CS,$A27) -> 0 | J27: =SUMIFS(Benefits!$AF:$AF,Benefits!$E:$E,"Revenue",Benefits!$F:$F,"USD",Benefits!$D:$D,"Plan Base",Benefits!$CS:$CS,$A27) -> 0 | K27: =SUMIFS(Benefits!$AG:$AG,Benefits!$E:$E,"Revenue",Benefits!$F:$F,"USD",Benefits!$D:$D,"Plan Base",Benefits!$CS:$CS,$A27) -> 0 | L27: =SUMIFS(Benefits!$AH:$AH,Benefits!$E:$E,"Revenue",Benefits!$F:$F,"USD",Benefits!$D:$D,"Plan Base",Benefits!$CS:$CS,$A27) -> 0.299 | M27: =SUMIFS(Benefits!$AI:$AI,Benefits!$E:$E,"Revenue",Benefits!$F:$F,"USD",Benefits!$D:$D,"Plan Base",Benefits!$CS:$CS,$A27) -> 0.299 | N27: =SUMIFS(Benefits!$AJ:$AJ,Benefits!$E:$E,"Revenue",Benefits!$F:$F,"USD",Benefits!$D:$D,"Plan Base",Benefits!$CS:$CS,$A27) -> 0.10541667 | O27: =SUMIFS(Benefits!$AK:$AK,Benefits!$E:$E,"Revenue",Benefits!$F:$F,"USD",Benefits!$D:$D,"Plan Base",Benefits!$CS:$CS,$A27) -> 0.17623485 | P27: =SUMIFS(Benefits!$AL:$AL,Benefits!$E:$E,"Revenue",Benefits!$F:$F,"USD",Benefits!$D:$D,"Plan Base",Benefits!$CS:$CS,$A27) -> 0.17623485 | Q27: =SUMIFS(Benefits!$AM:$AM,Benefits!$E:$E,"Revenue",Benefits!$F:$F,"USD",Benefits!$D:$D,"Plan Base",Benefits!$CS:$CS,$A27) -> 0.17623485 | R27: =SUMIFS(Benefits!$AN:$AN,Benefits!$E:$E,"Revenue",Benefits!$F:$F,"USD",Benefits!$D:$D,"Plan Base",Benefits!$CS:$CS,$A27) -> 0.17623485 | S27: =SUMIFS(Benefits!$AO:$AO,Benefits!$E:$E,"Revenue",Benefits!$F:$F,"USD",Benefits!$D:$D,"Plan Base",Benefits!$CS:$CS,$A27) -> 0.17623485 | T27: =SUMIFS(Benefits!$AP:$AP,Benefits!$E:$E,"Revenue",Benefits!$F:$F,"USD",Benefits!$D:$D,"Plan Base",Benefits!$CS:$CS,$A27) -> 0.17623485 | U27: =SUMIFS(Benefits!$AQ:$AQ,Benefits!$E:$E,"Revenue",Benefits!$F:$F,"USD",Benefits!$D:$D,"Plan Base",Benefits!$CS:$CS,$A27) -> 0.17623485 | V27: =SUMIFS(Benefits!$AR:$AR,Benefits!$E:$E,"Revenue",Benefits!$F:$F,"USD",Benefits!$D:$D,"Plan Base",Benefits!$CS:$CS,$A27) -> 0.17623485 | W27: =SUMIFS(Benefits!$AS:$AS,Benefits!$E:$E,"Revenue",Benefits!$F:$F,"USD",Benefits!$D:$D,"Plan Base",Benefits!$CS:$CS,$A27) -> 0.17623485 | X27: =SUMIFS(Benefits!$AT:$AT,Benefits!$E:$E,"Revenue",Benefits!$F:$F,"USD",Benefits!$D:$D,"Plan Base",Benefits!$CS:$CS,$A27) -> 0.17623485 | Y27: =SUMIFS(Benefits!$AU:$AU,Benefits!$E:$E,"Revenue",Benefits!$F:$F,"USD",Benefits!$D:$D,"Plan Base",Benefits!$CS:$CS,$A27) -> 0.17623485 | Z27: =SUMIFS(Benefits!$AV:$AV,Benefits!$E:$E,"Revenue",Benefits!$F:$F,"USD",Benefits!$D:$D,"Plan Base",Benefits!$CS:$CS,$A27) -> 0.30016667 | AA27: =SUMIFS(Benefits!$AW:$AW,Benefits!$E:$E,"Revenue",Benefits!$F:$F,"USD",Benefits!$D:$D,"Plan Base",Benefits!$CS:$CS,$A27) -> 0.30016667 | AB27: =SUMIFS(Benefits!$AX:$AX,Benefits!$E:$E,"Revenue",Benefits!$F:$F,"USD",Benefits!$D:$D,"Plan Base",Benefits!$CS:$CS,$A27) -> 0.30016667 | AC27: =SUMIFS(Benefits!$AY:$AY,Benefits!$E:$E,"Revenue",Benefits!$F:$F,"USD",Benefits!$D:$D,"Plan Base",Benefits!$CS:$CS,$A27) -> 0.30016667 | AD27: =SUMIFS(Benefits!$AZ:$AZ,Benefits!$E:$E,"Revenue",Benefits!$F:$F,"USD",Benefits!$D:$D,"Plan Base",Benefits!$CS:$CS,$A27) -> 0.30016667 | AE27: =SUMIFS(Benefits!$BA:$BA,Benefits!$E:$E,"Revenue",Benefits!$F:$F,"USD",Benefits!$D:$D,"Plan Base",Benefits!$CS:$CS,$A27) -> 0.30016667 | AF27: =SUMIFS(Benefits!$BB:$BB,Benefits!$E:$E,"Revenue",Benefits!$F:$F,"USD",Benefits!$D:$D,"Plan Base",Benefits!$CS:$CS,$A27) -> 0.30016667 | AG27: =SUMIFS(Benefits!$BC:$BC,Benefits!$E:$E,"Revenue",Benefits!$F:$F,"USD",Benefits!$D:$D,"Plan Base",Benefits!$CS:$CS,$A27) -> 0.30016667 | AH27: =SUMIFS(Benefits!$BD:$BD,Benefits!$E:$E,"Revenue",Benefits!$F:$F,"USD",Benefits!$D:$D,"Plan Base",Benefits!$CS:$CS,$A27) -> 0.30016667 | AI27: =SUMIFS(Benefits!$BE:$BE,Benefits!$E:$E,"Revenue",Benefits!$F:$F,"USD",Benefits!$D:$D,"Plan Base",Benefits!$CS:$CS,$A27) -> 0.30016667 | AJ27: =SUMIFS(Benefits!$BF:$BF,Benefits!$E:$E,"Revenue",Benefits!$F:$F,"USD",Benefits!$D:$D,"Plan Base",Benefits!$CS:$CS,$A27) -> 0.30016667 | AK27: =SUMIFS(Benefits!$BG:$BG,Benefits!$E:$E,"Revenue",Benefits!$F:$F,"USD",Benefits!$D:$D,"Plan Base",Benefits!$CS:$CS,$A27) -> 0.30016667 | AL27: =SUMIFS(Benefits!$BH:$BH,Benefits!$E:$E,"Revenue",Benefits!$F:$F,"USD",Benefits!$D:$D,"Plan Base",Benefits!$CS:$CS,$A27) -> 0.30016667 | AM27: =SUMIFS(Benefits!$BI:$BI,Benefits!$E:$E,"Revenue",Benefits!$F:$F,"USD",Benefits!$D:$D,"Plan Base",Benefits!$CS:$CS,$A27) -> 0.30016667 | AN27: =SUMIFS(Benefits!$BJ:$BJ,Benefits!$E:$E,"Revenue",Benefits!$F:$F,"USD",Benefits!$D:$D,"Plan Base",Benefits!$CS:$CS,$A27) -> 0.30016667 | AO27: =SUMIFS(Benefits!$BK:$BK,Benefits!$E:$E,"Revenue",Benefits!$F:$F,"USD",Benefits!$D:$D,"Plan Base",Benefits!$CS:$CS,$A27) -> 0.30016667 | AP27: =SUMIFS(Benefits!$BL:$BL,Benefits!$E:$E,"Revenue",Benefits!$F:$F,"USD",Benefits!$D:$D,"Plan Base",Benefits!$CS:$CS,$A27) -> 0.30016667 | AQ27: =SUMIFS(Benefits!$BM:$BM,Benefits!$E:$E,"Revenue",Benefits!$F:$F,"USD",Benefits!$D:$D,"Plan Base",Benefits!$CS:$CS,$A27) -> 0.30016667 | AR27: =SUMIFS(Benefits!$BN:$BN,Benefits!$E:$E,"Revenue",Benefits!$F:$F,"USD",Benefits!$D:$D,"Plan Base",Benefits!$CS:$CS,$A27) -> 0.30016667 | AS27: =SUMIFS(Benefits!$BO:$BO,Benefits!$E:$E,"Revenue",Benefits!$F:$F,"USD",Benefits!$D:$D,"Plan Base",Benefits!$CS:$CS,$A27) -> 0.30016667 | AT27: =SUMIFS(Benefits!$BP:$BP,Benefits!$E:$E,"Revenue",Benefits!$F:$F,"USD",Benefits!$D:$D,"Plan Base",Benefits!$CS:$CS,$A27) -> 0.30016667 | AU27: =SUMIFS(Benefits!$BQ:$BQ,Benefits!$E:$E,"Revenue",Benefits!$F:$F,"USD",Benefits!$D:$D,"Plan Base",Benefits!$CS:$CS,$A27) -> 0.30016667 | AV27: =SUMIFS(Benefits!$BR:$BR,Benefits!$E:$E,"Revenue",Benefits!$F:$F,"USD",Benefits!$D:$D,"Plan Base",Benefits!$CS:$CS,$A27) -> 0.30016667 | AW27: =SUMIFS(Benefits!$BS:$BS,Benefits!$E:$E,"Revenue",Benefits!$F:$F,"USD",Benefits!$D:$D,"Plan Base",Benefits!$CS:$CS,$A27) -> 0.30016667 | AX27: =SUMIFS(Benefits!$BT:$BT,Benefits!$E:$E,"Revenue",Benefits!$F:$F,"USD",Benefits!$D:$D,"Plan Base",Benefits!$CS:$CS,$A27) -> 0.30016667 | AY27: =SUMIFS(Benefits!$BU:$BU,Benefits!$E:$E,"Revenue",Benefits!$F:$F,"USD",Benefits!$D:$D,"Plan Base",Benefits!$CS:$CS,$A27) -> 0.30016667 | AZ27: =SUMIFS(Benefits!$BV:$BV,Benefits!$E:$E,"Revenue",Benefits!$F:$F,"USD",Benefits!$D:$D,"Plan Base",Benefits!$CS:$CS,$A27) -> 0.30016667 | BA27: =SUMIFS(Benefits!$BW:$BW,Benefits!$E:$E,"Revenue",Benefits!$F:$F,"USD",Benefits!$D:$D,"Plan Base",Benefits!$CS:$CS,$A27) -> 0.30016667 | BB27: =SUMIFS(Benefits!$BX:$BX,Benefits!$E:$E,"Revenue",Benefits!$F:$F,"USD",Benefits!$D:$D,"Plan Base",Benefits!$CS:$CS,$A27) -> 0.30016667 | BC27: =SUMIFS(Benefits!$BY:$BY,Benefits!$E:$E,"Revenue",Benefits!$F:$F,"USD",Benefits!$D:$D,"Plan Base",Benefits!$CS:$CS,$A27) -> 0.30016667 | BD27: =SUMIFS(Benefits!$BZ:$BZ,Benefits!$E:$E,"Revenue",Benefits!$F:$F,"USD",Benefits!$D:$D,"Plan Base",Benefits!$CS:$CS,$A27) -> 0.30016667 | BE27: =SUMIFS(Benefits!$CA:$CA,Benefits!$E:$E,"Revenue",Benefits!$F:$F,"USD",Benefits!$D:$D,"Plan Base",Benefits!$CS:$CS,$A27) -> 0.30016667 | BF27: =SUMIFS(Benefits!$CB:$CB,Benefits!$E:$E,"Revenue",Benefits!$F:$F,"USD",Benefits!$D:$D,"Plan Base",Benefits!$CS:$CS,$A27) -> 0.30016667 | BG27: =SUMIFS(Benefits!$CC:$CC,Benefits!$E:$E,"Revenue",Benefits!$F:$F,"USD",Benefits!$D:$D,"Plan Base",Benefits!$CS:$CS,$A27) -> 0.30016667 | BH27: =SUMIFS(Benefits!$CD:$CD,Benefits!$E:$E,"Revenue",Benefits!$F:$F,"USD",Benefits!$D:$D,"Plan Base",Benefits!$CS:$CS,$A27) -> 0.30016667 | BI27: =SUMIFS(Benefits!$CE:$CE,Benefits!$E:$E,"Revenue",Benefits!$F:$F,"USD",Benefits!$D:$D,"Plan Base",Benefits!$CS:$CS,$A27) -> 0.30016667
A28: Total Revenue | B28: =SUM(B24:B27) -> 1.69 | C28: =SUM(C24:C27) -> 8.115 | D28: =SUM(D24:D27) -> 15.004 | E28: =SUM(E24:E27) -> 15.004 | F28: =SUM(F24:F27) -> 15.004 | H28: =SUM(H24:H27) -> 0 | I28: =SUM(I24:I27) -> 0 | J28: =SUM(J24:J27) -> 0 | K28: =SUM(K24:K27) -> 0 | L28: =SUM(L24:L27) -> 0.299 | M28: =SUM(M24:M27) -> 1.391 | N28: =SUM(N24:N27) -> 0.29791667 | O28: =SUM(O24:O27) -> 0.36873485 | ... BI28: =SUM(BI24:BI27) -> 1.2503333
A29: Gross Margin (USD m)
A30: Westmark Region | B30: =SUMIFS(Benefits!$S:$S,Benefits!$E:$E,"Gross Margin",Benefits!$F:$F,"USD",Benefits!$D:$D,"Plan Base",Benefits!$CS:$CS,$A30) -> 1.52 | C30: =SUMIFS(Benefits!$T:$T,Benefits!$E:$E,"Gross Margin",Benefits!$F:$F,"USD",Benefits!$D:$D,"Plan Base",Benefits!$CS:$CS,$A30) -> 4.34 | D30: =SUMIFS(Benefits!$U:$U,Benefits!$E:$E,"Gross Margin",Benefits!$F:$F,"USD",Benefits!$D:$D,"Plan Base",Benefits!$CS:$CS,$A30) -> 5.78 | E30: =SUMIFS(Benefits!$V:$V,Benefits!$E:$E,"Gross Margin",Benefits!$F:$F,"USD",Benefits!$D:$D,"Plan Base",Benefits!$CS:$CS,$A30) -> 5.78 | F30: =SUMIFS(Benefits!$W:$W,Benefits!$E:$E,"Gross Margin",Benefits!$F:$F,"USD",Benefits!$D:$D,"Plan Base",Benefits!$CS:$CS,$A30) -> 5.78 | H30: =SUMIFS(Benefits!$AD:$AD,Benefits!$E:$E,"Gross Margin",Benefits!$F:$F,"USD",Benefits!$D:$D,"Plan Base",Benefits!$CS:$CS,$A30) -> 0 | I30: =SUMIFS(Benefits!$AE:$AE,Benefits!$E:$E,"Gross Margin",Benefits!$F:$F,"USD",Benefits!$D:$D,"Plan Base",Benefits!$CS:$CS,$A30) -> 0 | J30: =SUMIFS(Benefits!$AF:$AF,Benefits!$E:$E,"Gross Margin",Benefits!$F:$F,"USD",Benefits!$D:$D,"Plan Base",Benefits!$CS:$CS,$A30) -> 0 | K30: =SUMIFS(Benefits!$AG:$AG,Benefits!$E:$E,"Gross Margin",Benefits!$F:$F,"USD",Benefits!$D:$D,"Plan Base",Benefits!$CS:$CS,$A30) -> 0 | L30: =SUMIFS(Benefits!$AH:$AH,Benefits!$E:$E,"Gross Margin",Benefits!$F:$F,"USD",Benefits!$D:$D,"Plan Base",Benefits!$CS:$CS,$A30) -> 0.62 | M30: =SUMIFS(Benefits!$AI:$AI,Benefits!$E:$E,"Gross Margin",Benefits!$F:$F,"USD",Benefits!$D:$D,"Plan Base",Benefits!$CS:$CS,$A30) -> 0.9 | N30: =SUMIFS(Benefits!$AJ:$AJ,Benefits!$E:$E,"Gross Margin",Benefits!$F:$F,"USD",Benefits!$D:$D,"Plan Base",Benefits!$CS:$CS,$A30) -> 0.215 | O30: =SUMIFS(Benefits!$AK:$AK,Benefits!$E:$E,"Gross Margin",Benefits!$F:$F,"USD",Benefits!$D:$D,"Plan Base",Benefits!$CS:$CS,$A30) -> 0.215 | P30: =SUMIFS(Benefits!$AL:$AL,Benefits!$E:$E,"Gross Margin",Benefits!$F:$F,"USD",Benefits!$D:$D,"Plan Base",Benefits!$CS:$CS,$A30) -> 0.277 | Q30: =SUMIFS(Benefits!$AM:$AM,Benefits!$E:$E,"Gross Margin",Benefits!$F:$F,"USD",Benefits!$D:$D,"Plan Base",Benefits!$CS:$CS,$A30) -> 0.30366667 | R30: =SUMIFS(Benefits!$AN:$AN,Benefits!$E:$E,"Gross Margin",Benefits!$F:$F,"USD",Benefits!$D:$D,"Plan Base",Benefits!$CS:$CS,$A30) -> 0.30366667 | S30: =SUMIFS(Benefits!$AO:$AO,Benefits!$E:$E,"Gross Margin",Benefits!$F:$F,"USD",Benefits!$D:$D,"Plan Base",Benefits!$CS:$CS,$A30) -> 0.30366667 | T30: =SUMIFS(Benefits!$AP:$AP,Benefits!$E:$E,"Gross Margin",Benefits!$F:$F,"USD",Benefits!$D:$D,"Plan Base",Benefits!$CS:$CS,$A30) -> 0.30366667 | U30: =SUMIFS(Benefits!$AQ:$AQ,Benefits!$E:$E,"Gross Margin",Benefits!$F:$F,"USD",Benefits!$D:$D,"Plan Base",Benefits!$CS:$CS,$A30) -> 0.30366667 | V30: =SUMIFS(Benefits!$AR:$AR,Benefits!$E:$E,"Gross Margin",Benefits!$F:$F,"USD",Benefits!$D:$D,"Plan Base",Benefits!$CS:$CS,$A30) -> 0.40866667 | W30: =SUMIFS(Benefits!$AS:$AS,Benefits!$E:$E,"Gross Margin",Benefits!$F:$F,"USD",Benefits!$D:$D,"Plan Base",Benefits!$CS:$CS,$A30) -> 0.40866667 | X30: =SUMIFS(Benefits!$AT:$AT,Benefits!$E:$E,"Gross Margin",Benefits!$F:$F,"USD",Benefits!$D:$D,"Plan Base",Benefits!$CS:$CS,$A30) -> 0.40866667 | Y30: =SUMIFS(Benefits!$AU:$AU,Benefits!$E:$E,"Gross Margin",Benefits!$F:$F,"USD",Benefits!$D:$D,"Plan Base",Benefits!$CS:$CS,$A30) -> 0.88866667 | Z30: =SUMIFS(Benefits!$AV:$AV,Benefits!$E:$E,"Gross Margin",Benefits!$F:$F,"USD",Benefits!$D:$D,"Plan Base",Benefits!$CS:$CS,$A30) -> 0.48166667 | AA30: =SUMIFS(Benefits!$AW:$AW,Benefits!$E:$E,"Gross Margin",Benefits!$F:$F,"USD",Benefits!$D:$D,"Plan Base",Benefits!$CS:$CS,$A30) -> 0.48166667 | AB30: =SUMIFS(Benefits!$AX:$AX,Benefits!$E:$E,"Gross Margin",Benefits!$F:$F,"USD",Benefits!$D:$D,"Plan Base",Benefits!$CS:$CS,$A30) -> 0.48166667 | AC30: =SUMIFS(Benefits!$AY:$AY,Benefits!$E:$E,"Gross Margin",Benefits!$F:$F,"USD",Benefits!$D:$D,"Plan Base",Benefits!$CS:$CS,$A30) -> 0.48166667 | AD30: =SUMIFS(Benefits!$AZ:$AZ,Benefits!$E:$E,"Gross Margin",Benefits!$F:$F,"USD",Benefits!$D:$D,"Plan Base",Benefits!$CS:$CS,$A30) -> 0.48166667 | AE30: =SUMIFS(Benefits!$BA:$BA,Benefits!$E:$E,"Gross Margin",Benefits!$F:$F,"USD",Benefits!$D:$D,"Plan Base",Benefits!$CS:$CS,$A30) -> 0.48166667 | AF30: =SUMIFS(Benefits!$BB:$BB,Benefits!$E:$E,"Gross Margin",Benefits!$F:$F,"USD",Benefits!$D:$D,"Plan Base",Benefits!$CS:$CS,$A30) -> 0.48166667 | AG30: =SUMIFS(Benefits!$BC:$BC,Benefits!$E:$E,"Gross Margin",Benefits!$F:$F,"USD",Benefits!$D:$D,"Plan Base",Benefits!$CS:$CS,$A30) -> 0.48166667 | AH30: =SUMIFS(Benefits!$BD:$BD,Benefits!$E:$E,"Gross Margin",Benefits!$F:$F,"USD",Benefits!$D:$D,"Plan Base",Benefits!$CS:$CS,$A30) -> 0.48166667 | AI30: =SUMIFS(Benefits!$BE:$BE,Benefits!$E:$E,"Gross Margin",Benefits!$F:$F,"USD",Benefits!$D:$D,"Plan Base",Benefits!$CS:$CS,$A30) -> 0.48166667 | AJ30: =SUMIFS(Benefits!$BF:$BF,Benefits!$E:$E,"Gross Margin",Benefits!$F:$F,"USD",Benefits!$D:$D,"Plan Base",Benefits!$CS:$CS,$A30) -> 0.48166667 | AK30: =SUMIFS(Benefits!$BG:$BG,Benefits!$E:$E,"Gross Margin",Benefits!$F:$F,"USD",Benefits!$D:$D,"Plan Base",Benefits!$CS:$CS,$A30) -> 0.48166667 | AL30: =SUMIFS(Benefits!$BH:$BH,Benefits!$E:$E,"Gross Margin",Benefits!$F:$F,"USD",Benefits!$D:$D,"Plan Base",Benefits!$CS:$CS,$A30) -> 0.48166667 | AM30: =SUMIFS(Benefits!$BI:$BI,Benefits!$E:$E,"Gross Margin",Benefits!$F:$F,"USD",Benefits!$D:$D,"Plan Base",Benefits!$CS:$CS,$A30) -> 0.48166667 | AN30: =SUMIFS(Benefits!$BJ:$BJ,Benefits!$E:$E,"Gross Margin",Benefits!$F:$F,"USD",Benefits!$D:$D,"Plan Base",Benefits!$CS:$CS,$A30) -> 0.48166667 | AO30: =SUMIFS(Benefits!$BK:$BK,Benefits!$E:$E,"Gross Margin",Benefits!$F:$F,"USD",Benefits!$D:$D,"Plan Base",Benefits!$CS:$CS,$A30) -> 0.48166667 | AP30: =SUMIFS(Benefits!$BL:$BL,Benefits!$E:$E,"Gross Margin",Benefits!$F:$F,"USD",Benefits!$D:$D,"Plan Base",Benefits!$CS:$CS,$A30) -> 0.48166667 | AQ30: =SUMIFS(Benefits!$BM:$BM,Benefits!$E:$E,"Gross Margin",Benefits!$F:$F,"USD",Benefits!$D:$D,"Plan Base",Benefits!$CS:$CS,$A30) -> 0.48166667 | AR30: =SUMIFS(Benefits!$BN:$BN,Benefits!$E:$E,"Gross Margin",Benefits!$F:$F,"USD",Benefits!$D:$D,"Plan Base",Benefits!$CS:$CS,$A30) -> 0.48166667 | AS30: =SUMIFS(Benefits!$BO:$BO,Benefits!$E:$E,"Gross Margin",Benefits!$F:$F,"USD",Benefits!$D:$D,"Plan Base",Benefits!$CS:$CS,$A30) -> 0.48166667 | AT30: =SUMIFS(Benefits!$BP:$BP,Benefits!$E:$E,"Gross Margin",Benefits!$F:$F,"USD",Benefits!$D:$D,"Plan Base",Benefits!$CS:$CS,$A30) -> 0.48166667 | AU30: =SUMIFS(Benefits!$BQ:$BQ,Benefits!$E:$E,"Gross Margin",Benefits!$F:$F,"USD",Benefits!$D:$D,"Plan Base",Benefits!$CS:$CS,$A30) -> 0.48166667 | AV30: =SUMIFS(Benefits!$BR:$BR,Benefits!$E:$E,"Gross Margin",Benefits!$F:$F,"USD",Benefits!$D:$D,"Plan Base",Benefits!$CS:$CS,$A30) -> 0.48166667 | AW30: =SUMIFS(Benefits!$BS:$BS,Benefits!$E:$E,"Gross Margin",Benefits!$F:$F,"USD",Benefits!$D:$D,"Plan Base",Benefits!$CS:$CS,$A30) -> 0.48166667 | AX30: =SUMIFS(Benefits!$BT:$BT,Benefits!$E:$E,"Gross Margin",Benefits!$F:$F,"USD",Benefits!$D:$D,"Plan Base",Benefits!$CS:$CS,$A30) -> 0.48166667 | AY30: =SUMIFS(Benefits!$BU:$BU,Benefits!$E:$E,"Gross Margin",Benefits!$F:$F,"USD",Benefits!$D:$D,"Plan Base",Benefits!$CS:$CS,$A30) -> 0.48166667 | AZ30: =SUMIFS(Benefits!$BV:$BV,Benefits!$E:$E,"Gross Margin",Benefits!$F:$F,"USD",Benefits!$D:$D,"Plan Base",Benefits!$CS:$CS,$A30) -> 0.48166667 | BA30: =SUMIFS(Benefits!$BW:$BW,Benefits!$E:$E,"Gross Margin",Benefits!$F:$F,"USD",Benefits!$D:$D,"Plan Base",Benefits!$CS:$CS,$A30) -> 0.48166667 | BB30: =SUMIFS(Benefits!$BX:$BX,Benefits!$E:$E,"Gross Margin",Benefits!$F:$F,"USD",Benefits!$D:$D,"Plan Base",Benefits!$CS:$CS,$A30) -> 0.48166667 | BC30: =SUMIFS(Benefits!$BY:$BY,Benefits!$E:$E,"Gross Margin",Benefits!$F:$F,"USD",Benefits!$D:$D,"Plan Base",Benefits!$CS:$CS,$A30) -> 0.48166667 | BD30: =SUMIFS(Benefits!$BZ:$BZ,Benefits!$E:$E,"Gross Margin",Benefits!$F:$F,"USD",Benefits!$D:$D,"Plan Base",Benefits!$CS:$CS,$A30) -> 0.48166667 | BE30: =SUMIFS(Benefits!$CA:$CA,Benefits!$E:$E,"Gross Margin",Benefits!$F:$F,"USD",Benefits!$D:$D,"Plan Base",Benefits!$CS:$CS,$A30) -> 0.48166667 | BF30: =SUMIFS(Benefits!$CB:$CB,Benefits!$E:$E,"Gross Margin",Benefits!$F:$F,"USD",Benefits!$D:$D,"Plan Base",Benefits!$CS:$CS,$A30) -> 0.48166667 | BG30: =SUMIFS(Benefits!$CC:$CC,Benefits!$E:$E,"Gross Margin",Benefits!$F:$F,"USD",Benefits!$D:$D,"Plan Base",Benefits!$CS:$CS,$A30) -> 0.48166667 | BH30: =SUMIFS(Benefits!$CD:$CD,Benefits!$E:$E,"Gross Margin",Benefits!$F:$F,"USD",Benefits!$D:$D,"Plan Base",Benefits!$CS:$CS,$A30) -> 0.48166667 | BI30: =SUMIFS(Benefits!$CE:$CE,Benefits!$E:$E,"Gross Margin",Benefits!$F:$F,"USD",Benefits!$D:$D,"Plan Base",Benefits!$CS:$CS,$A30) -> 0.48166667
A31: Eastbridge Region | B31: =SUMIFS(Benefits!$S:$S,Benefits!$E:$E,"Gross Margin",Benefits!$F:$F,"USD",Benefits!$D:$D,"Plan Base",Benefits!$CS:$CS,$A31) -> 1.116 | C31: =SUMIFS(Benefits!$T:$T,Benefits!$E:$E,"Gross Margin",Benefits!$F:$F,"USD",Benefits!$D:$D,"Plan Base",Benefits!$CS:$CS,$A31) -> 3.577 | D31: =SUMIFS(Benefits!$U:$U,Benefits!$E:$E,"Gross Margin",Benefits!$F:$F,"USD",Benefits!$D:$D,"Plan Base",Benefits!$CS:$CS,$A31) -> 5.567 | E31: =SUMIFS(Benefits!$V:$V,Benefits!$E:$E,"Gross Margin",Benefits!$F:$F,"USD",Benefits!$D:$D,"Plan Base",Benefits!$CS:$CS,$A31) -> 5.567 | F31: =SUMIFS(Benefits!$W:$W,Benefits!$E:$E,"Gross Margin",Benefits!$F:$F,"USD",Benefits!$D:$D,"Plan Base",Benefits!$CS:$CS,$A31) -> 5.567 | H31: =SUMIFS(Benefits!$AD:$AD,Benefits!$E:$E,"Gross Margin",Benefits!$F:$F,"USD",Benefits!$D:$D,"Plan Base",Benefits!$CS:$CS,$A31) -> 0 | I31: =SUMIFS(Benefits!$AE:$AE,Benefits!$E:$E,"Gross Margin",Benefits!$F:$F,"USD",Benefits!$D:$D,"Plan Base",Benefits!$CS:$CS,$A31) -> 0 | J31: =SUMIFS(Benefits!$AF:$AF,Benefits!$E:$E,"Gross Margin",Benefits!$F:$F,"USD",Benefits!$D:$D,"Plan Base",Benefits!$CS:$CS,$A31) -> 0 | K31: =SUMIFS(Benefits!$AG:$AG,Benefits!$E:$E,"Gross Margin",Benefits!$F:$F,"USD",Benefits!$D:$D,"Plan Base",Benefits!$CS:$CS,$A31) -> 0.372 | L31: =SUMIFS(Benefits!$AH:$AH,Benefits!$E:$E,"Gross Margin",Benefits!$F:$F,"USD",Benefits!$D:$D,"Plan Base",Benefits!$CS:$CS,$A31) -> 0.372 | M31: =SUMIFS(Benefits!$AI:$AI,Benefits!$E:$E,"Gross Margin",Benefits!$F:$F,"USD",Benefits!$D:$D,"Plan Base",Benefits!$CS:$CS,$A31) -> 0.372 | N31: =SUMIFS(Benefits!$AJ:$AJ,Benefits!$E:$E,"Gross Margin",Benefits!$F:$F,"USD",Benefits!$D:$D,"Plan Base",Benefits!$CS:$CS,$A31) -> 0.1395 | O31: =SUMIFS(Benefits!$AK:$AK,Benefits!$E:$E,"Gross Margin",Benefits!$F:$F,"USD",Benefits!$D:$D,"Plan Base",Benefits!$CS:$CS,$A31) -> 0.1395 | P31: =SUMIFS(Benefits!$AL:$AL,Benefits!$E:$E,"Gross Margin",Benefits!$F:$F,"USD",Benefits!$D:$D,"Plan Base",Benefits!$CS:$CS,$A31) -> 0.1395 | Q31: =SUMIFS(Benefits!$AM:$AM,Benefits!$E:$E,"Gross Margin",Benefits!$F:$F,"USD",Benefits!$D:$D,"Plan Base",Benefits!$CS:$CS,$A31) -> 0.19083333 | R31: =SUMIFS(Benefits!$AN:$AN,Benefits!$E:$E,"Gross Margin",Benefits!$F:$F,"USD",Benefits!$D:$D,"Plan Base",Benefits!$CS:$CS,$A31) -> 0.19083333 | S31: =SUMIFS(Benefits!$AO:$AO,Benefits!$E:$E,"Gross Margin",Benefits!$F:$F,"USD",Benefits!$D:$D,"Plan Base",Benefits!$CS:$CS,$A31) -> 0.19083333 | T31: =SUMIFS(Benefits!$AP:$AP,Benefits!$E:$E,"Gross Margin",Benefits!$F:$F,"USD",Benefits!$D:$D,"Plan Base",Benefits!$CS:$CS,$A31) -> 0.28283333 | U31: =SUMIFS(Benefits!$AQ:$AQ,Benefits!$E:$E,"Gross Margin",Benefits!$F:$F,"USD",Benefits!$D:$D,"Plan Base",Benefits!$CS:$CS,$A31) -> 0.28283333 | V31: =SUMIFS(Benefits!$AR:$AR,Benefits!$E:$E,"Gross Margin",Benefits!$F:$F,"USD",Benefits!$D:$D,"Plan Base",Benefits!$CS:$CS,$A31) -> 0.34233333 | W31: =SUMIFS(Benefits!$AS:$AS,Benefits!$E:$E,"Gross Margin",Benefits!$F:$F,"USD",Benefits!$D:$D,"Plan Base",Benefits!$CS:$CS,$A31) -> 0.34233333 | X31: =SUMIFS(Benefits!$AT:$AT,Benefits!$E:$E,"Gross Margin",Benefits!$F:$F,"USD",Benefits!$D:$D,"Plan Base",Benefits!$CS:$CS,$A31) -> 0.34233333 | Y31: =SUMIFS(Benefits!$AU:$AU,Benefits!$E:$E,"Gross Margin",Benefits!$F:$F,"USD",Benefits!$D:$D,"Plan Base",Benefits!$CS:$CS,$A31) -> 0.99333333 | Z31: =SUMIFS(Benefits!$AV:$AV,Benefits!$E:$E,"Gross Margin",Benefits!$F:$F,"USD",Benefits!$D:$D,"Plan Base",Benefits!$CS:$CS,$A31) -> 0.46391667 | AA31: =SUMIFS(Benefits!$AW:$AW,Benefits!$E:$E,"Gross Margin",Benefits!$F:$F,"USD",Benefits!$D:$D,"Plan Base",Benefits!$CS:$CS,$A31) -> 0.46391667 | AB31: =SUMIFS(Benefits!$AX:$AX,Benefits!$E:$E,"Gross Margin",Benefits!$F:$F,"USD",Benefits!$D:$D,"Plan Base",Benefits!$CS:$CS,$A31) -> 0.46391667 | AC31: =SUMIFS(Benefits!$AY:$AY,Benefits!$E:$E,"Gross Margin",Benefits!$F:$F,"USD",Benefits!$D:$D,"Plan Base",Benefits!$CS:$CS,$A31) -> 0.46391667 | AD31: =SUMIFS(Benefits!$AZ:$AZ,Benefits!$E:$E,"Gross Margin",Benefits!$F:$F,"USD",Benefits!$D:$D,"Plan Base",Benefits!$CS:$CS,$A31) -> 0.46391667 | AE31: =SUMIFS(Benefits!$BA:$BA,Benefits!$E:$E,"Gross Margin",Benefits!$F:$F,"USD",Benefits!$D:$D,"Plan Base",Benefits!$CS:$CS,$A31) -> 0.46391667 | AF31: =SUMIFS(Benefits!$BB:$BB,Benefits!$E:$E,"Gross Margin",Benefits!$F:$F,"USD",Benefits!$D:$D,"Plan Base",Benefits!$CS:$CS,$A31) -> 0.46391667 | AG31: =SUMIFS(Benefits!$BC:$BC,Benefits!$E:$E,"Gross Margin",Benefits!$F:$F,"USD",Benefits!$D:$D,"Plan Base",Benefits!$CS:$CS,$A31) -> 0.46391667 | AH31: =SUMIFS(Benefits!$BD:$BD,Benefits!$E:$E,"Gross Margin",Benefits!$F:$F,"USD",Benefits!$D:$D,"Plan Base",Benefits!$CS:$CS,$A31) -> 0.46391667 | AI31: =SUMIFS(Benefits!$BE:$BE,Benefits!$E:$E,"Gross Margin",Benefits!$F:$F,"USD",Benefits!$D:$D,"Plan Base",Benefits!$CS:$CS,$A31) -> 0.46391667 | AJ31: =SUMIFS(Benefits!$BF:$BF,Benefits!$E:$E,"Gross Margin",Benefits!$F:$F,"USD",Benefits!$D:$D,"Plan Base",Benefits!$CS:$CS,$A31) -> 0.46391667 | AK31: =SUMIFS(Benefits!$BG:$BG,Benefits!$E:$E,"Gross Margin",Benefits!$F:$F,"USD",Benefits!$D:$D,"Plan Base",Benefits!$CS:$CS,$A31) -> 0.46391667 | AL31: =SUMIFS(Benefits!$BH:$BH,Benefits!$E:$E,"Gross Margin",Benefits!$F:$F,"USD",Benefits!$D:$D,"Plan Base",Benefits!$CS:$CS,$A31) -> 0.46391667 | AM31: =SUMIFS(Benefits!$BI:$BI,Benefits!$E:$E,"Gross Margin",Benefits!$F:$F,"USD",Benefits!$D:$D,"Plan Base",Benefits!$CS:$CS,$A31) -> 0.46391667 | AN31: =SUMIFS(Benefits!$BJ:$BJ,Benefits!$E:$E,"Gross Margin",Benefits!$F:$F,"USD",Benefits!$D:$D,"Plan Base",Benefits!$CS:$CS,$A31) -> 0.46391667 | AO31: =SUMIFS(Benefits!$BK:$BK,Benefits!$E:$E,"Gross Margin",Benefits!$F:$F,"USD",Benefits!$D:$D,"Plan Base",Benefits!$CS:$CS,$A31) -> 0.46391667 | AP31: =SUMIFS(Benefits!$BL:$BL,Benefits!$E:$E,"Gross Margin",Benefits!$F:$F,"USD",Benefits!$D:$D,"Plan Base",Benefits!$CS:$CS,$A31) -> 0.46391667 | AQ31: =SUMIFS(Benefits!$BM:$BM,Benefits!$E:$E,"Gross Margin",Benefits!$F:$F,"USD",Benefits!$D:$D,"Plan Base",Benefits!$CS:$CS,$A31) -> 0.46391667 | AR31: =SUMIFS(Benefits!$BN:$BN,Benefits!$E:$E,"Gross Margin",Benefits!$F:$F,"USD",Benefits!$D:$D,"Plan Base",Benefits!$CS:$CS,$A31) -> 0.46391667 | AS31: =SUMIFS(Benefits!$BO:$BO,Benefits!$E:$E,"Gross Margin",Benefits!$F:$F,"USD",Benefits!$D:$D,"Plan Base",Benefits!$CS:$CS,$A31) -> 0.46391667 | AT31: =SUMIFS(Benefits!$BP:$BP,Benefits!$E:$E,"Gross Margin",Benefits!$F:$F,"USD",Benefits!$D:$D,"Plan Base",Benefits!$CS:$CS,$A31) -> 0.46391667 | AU31: =SUMIFS(Benefits!$BQ:$BQ,Benefits!$E:$E,"Gross Margin",Benefits!$F:$F,"USD",Benefits!$D:$D,"Plan Base",Benefits!$CS:$CS,$A31) -> 0.46391667 | AV31: =SUMIFS(Benefits!$BR:$BR,Benefits!$E:$E,"Gross Margin",Benefits!$F:$F,"USD",Benefits!$D:$D,"Plan Base",Benefits!$CS:$CS,$A31) -> 0.46391667 | AW31: =SUMIFS(Benefits!$BS:$BS,Benefits!$E:$E,"Gross Margin",Benefits!$F:$F,"USD",Benefits!$D:$D,"Plan Base",Benefits!$CS:$CS,$A31) -> 0.46391667 | AX31: =SUMIFS(Benefits!$BT:$BT,Benefits!$E:$E,"Gross Margin",Benefits!$F:$F,"USD",Benefits!$D:$D,"Plan Base",Benefits!$CS:$CS,$A31) -> 0.46391667 | AY31: =SUMIFS(Benefits!$BU:$BU,Benefits!$E:$E,"Gross Margin",Benefits!$F:$F,"USD",Benefits!$D:$D,"Plan Base",Benefits!$CS:$CS,$A31) -> 0.46391667 | AZ31: =SUMIFS(Benefits!$BV:$BV,Benefits!$E:$E,"Gross Margin",Benefits!$F:$F,"USD",Benefits!$D:$D,"Plan Base",Benefits!$CS:$CS,$A31) -> 0.46391667 | BA31: =SUMIFS(Benefits!$BW:$BW,Benefits!$E:$E,"Gross Margin",Benefits!$F:$F,"USD",Benefits!$D:$D,"Plan Base",Benefits!$CS:$CS,$A31) -> 0.46391667 | BB31: =SUMIFS(Benefits!$BX:$BX,Benefits!$E:$E,"Gross Margin",Benefits!$F:$F,"USD",Benefits!$D:$D,"Plan Base",Benefits!$CS:$CS,$A31) -> 0.46391667 | BC31: =SUMIFS(Benefits!$BY:$BY,Benefits!$E:$E,"Gross Margin",Benefits!$F:$F,"USD",Benefits!$D:$D,"Plan Base",Benefits!$CS:$CS,$A31) -> 0.46391667 | BD31: =SUMIFS(Benefits!$BZ:$BZ,Benefits!$E:$E,"Gross Margin",Benefits!$F:$F,"USD",Benefits!$D:$D,"Plan Base",Benefits!$CS:$CS,$A31) -> 0.46391667 | BE31: =SUMIFS(Benefits!$CA:$CA,Benefits!$E:$E,"Gross Margin",Benefits!$F:$F,"USD",Benefits!$D:$D,"Plan Base",Benefits!$CS:$CS,$A31) -> 0.46391667 | BF31: =SUMIFS(Benefits!$CB:$CB,Benefits!$E:$E,"Gross Margin",Benefits!$F:$F,"USD",Benefits!$D:$D,"Plan Base",Benefits!$CS:$CS,$A31) -> 0.46391667 | BG31: =SUMIFS(Benefits!$CC:$CC,Benefits!$E:$E,"Gross Margin",Benefits!$F:$F,"USD",Benefits!$D:$D,"Plan Base",Benefits!$CS:$CS,$A31) -> 0.46391667 | BH31: =SUMIFS(Benefits!$CD:$CD,Benefits!$E:$E,"Gross Margin",Benefits!$F:$F,"USD",Benefits!$D:$D,"Plan Base",Benefits!$CS:$CS,$A31) -> 0.46391667 | BI31: =SUMIFS(Benefits!$CE:$CE,Benefits!$E:$E,"Gross Margin",Benefits!$F:$F,"USD",Benefits!$D:$D,"Plan Base",Benefits!$CS:$CS,$A31) -> 0.46391667
A32: Northpeak Region | B32: =SUMIFS(Benefits!$S:$S,Benefits!$E:$E,"Gross Margin",Benefits!$F:$F,"USD",Benefits!$D:$D,"Plan Base",Benefits!$CS:$CS,$A32) -> 0.308 | C32: =SUMIFS(Benefits!$T:$T,Benefits!$E:$E,"Gross Margin",Benefits!$F:$F,"USD",Benefits!$D:$D,"Plan Base",Benefits!$CS:$CS,$A32) -> 3.921 | D32: =SUMIFS(Benefits!$U:$U,Benefits!$E:$E,"Gross Margin",Benefits!$F:$F,"USD",Benefits!$D:$D,"Plan Base",Benefits!$CS:$CS,$A32) -> 5.877 | E32: =SUMIFS(Benefits!$V:$V,Benefits!$E:$E,"Gross Margin",Benefits!$F:$F,"USD",Benefits!$D:$D,"Plan Base",Benefits!$CS:$CS,$A32) -> 5.877 | F32: =SUMIFS(Benefits!$W:$W,Benefits!$E:$E,"Gross Margin",Benefits!$F:$F,"USD",Benefits!$D:$D,"Plan Base",Benefits!$CS:$CS,$A32) -> 5.877 | H32: =SUMIFS(Benefits!$AD:$AD,Benefits!$E:$E,"Gross Margin",Benefits!$F:$F,"USD",Benefits!$D:$D,"Plan Base",Benefits!$CS:$CS,$A32) -> 0 | I32: =SUMIFS(Benefits!$AE:$AE,Benefits!$E:$E,"Gross Margin",Benefits!$F:$F,"USD",Benefits!$D:$D,"Plan Base",Benefits!$CS:$CS,$A32) -> 0 | J32: =SUMIFS(Benefits!$AF:$AF,Benefits!$E:$E,"Gross Margin",Benefits!$F:$F,"USD",Benefits!$D:$D,"Plan Base",Benefits!$CS:$CS,$A32) -> 0 | K32: =SUMIFS(Benefits!$AG:$AG,Benefits!$E:$E,"Gross Margin",Benefits!$F:$F,"USD",Benefits!$D:$D,"Plan Base",Benefits!$CS:$CS,$A32) -> 0 | L32: =SUMIFS(Benefits!$AH:$AH,Benefits!$E:$E,"Gross Margin",Benefits!$F:$F,"USD",Benefits!$D:$D,"Plan Base",Benefits!$CS:$CS,$A32) -> 0 | M32: =SUMIFS(Benefits!$AI:$AI,Benefits!$E:$E,"Gross Margin",Benefits!$F:$F,"USD",Benefits!$D:$D,"Plan Base",Benefits!$CS:$CS,$A32) -> 0.308 | N32: =SUMIFS(Benefits!$AJ:$AJ,Benefits!$E:$E,"Gross Margin",Benefits!$F:$F,"USD",Benefits!$D:$D,"Plan Base",Benefits!$CS:$CS,$A32) -> 0.09925 | O32: =SUMIFS(Benefits!$AK:$AK,Benefits!$E:$E,"Gross Margin",Benefits!$F:$F,"USD",Benefits!$D:$D,"Plan Base",Benefits!$CS:$CS,$A32) -> 0.09925 | P32: =SUMIFS(Benefits!$AL:$AL,Benefits!$E:$E,"Gross Margin",Benefits!$F:$F,"USD",Benefits!$D:$D,"Plan Base",Benefits!$CS:$CS,$A32) -> 0.09925 | Q32: =SUMIFS(Benefits!$AM:$AM,Benefits!$E:$E,"Gross Margin",Benefits!$F:$F,"USD",Benefits!$D:$D,"Plan Base",Benefits!$CS:$CS,$A32) -> 0.09925 | R32: =SUMIFS(Benefits!$AN:$AN,Benefits!$E:$E,"Gross Margin",Benefits!$F:$F,"USD",Benefits!$D:$D,"Plan Base",Benefits!$CS:$CS,$A32) -> 0.28525 | S32: =SUMIFS(Benefits!$AO:$AO,Benefits!$E:$E,"Gross Margin",Benefits!$F:$F,"USD",Benefits!$D:$D,"Plan Base",Benefits!$CS:$CS,$A32) -> 0.36496429 | T32: =SUMIFS(Benefits!$AP:$AP,Benefits!$E:$E,"Gross Margin",Benefits!$F:$F,"USD",Benefits!$D:$D,"Plan Base",Benefits!$CS:$CS,$A32) -> 0.36496429 | U32: =SUMIFS(Benefits!$AQ:$AQ,Benefits!$E:$E,"Gross Margin",Benefits!$F:$F,"USD",Benefits!$D:$D,"Plan Base",Benefits!$CS:$CS,$A32) -> 0.42496429 | V32: =SUMIFS(Benefits!$AR:$AR,Benefits!$E:$E,"Gross Margin",Benefits!$F:$F,"USD",Benefits!$D:$D,"Plan Base",Benefits!$CS:$CS,$A32) -> 0.42496429 | W32: =SUMIFS(Benefits!$AS:$AS,Benefits!$E:$E,"Gross Margin",Benefits!$F:$F,"USD",Benefits!$D:$D,"Plan Base",Benefits!$CS:$CS,$A32) -> 0.55296429 | X32: =SUMIFS(Benefits!$AT:$AT,Benefits!$E:$E,"Gross Margin",Benefits!$F:$F,"USD",Benefits!$D:$D,"Plan Base",Benefits!$CS:$CS,$A32) -> 0.55296429 | Y32: =SUMIFS(Benefits!$AU:$AU,Benefits!$E:$E,"Gross Margin",Benefits!$F:$F,"USD",Benefits!$D:$D,"Plan Base",Benefits!$CS:$CS,$A32) -> 0.55296429 | Z32: =SUMIFS(Benefits!$AV:$AV,Benefits!$E:$E,"Gross Margin",Benefits!$F:$F,"USD",Benefits!$D:$D,"Plan Base",Benefits!$CS:$CS,$A32) -> 0.48975 | AA32: =SUMIFS(Benefits!$AW:$AW,Benefits!$E:$E,"Gross Margin",Benefits!$F:$F,"USD",Benefits!$D:$D,"Plan Base",Benefits!$CS:$CS,$A32) -> 0.48975 | AB32: =SUMIFS(Benefits!$AX:$AX,Benefits!$E:$E,"Gross Margin",Benefits!$F:$F,"USD",Benefits!$D:$D,"Plan Base",Benefits!$CS:$CS,$A32) -> 0.48975 | AC32: =SUMIFS(Benefits!$AY:$AY,Benefits!$E:$E,"Gross Margin",Benefits!$F:$F,"USD",Benefits!$D:$D,"Plan Base",Benefits!$CS:$CS,$A32) -> 0.48975 | AD32: =SUMIFS(Benefits!$AZ:$AZ,Benefits!$E:$E,"Gross Margin",Benefits!$F:$F,"USD",Benefits!$D:$D,"Plan Base",Benefits!$CS:$CS,$A32) -> 0.48975 | AE32: =SUMIFS(Benefits!$BA:$BA,Benefits!$E:$E,"Gross Margin",Benefits!$F:$F,"USD",Benefits!$D:$D,"Plan Base",Benefits!$CS:$CS,$A32) -> 0.48975 | AF32: =SUMIFS(Benefits!$BB:$BB,Benefits!$E:$E,"Gross Margin",Benefits!$F:$F,"USD",Benefits!$D:$D,"Plan Base",Benefits!$CS:$CS,$A32) -> 0.48975 | AG32: =SUMIFS(Benefits!$BC:$BC,Benefits!$E:$E,"Gross Margin",Benefits!$F:$F,"USD",Benefits!$D:$D,"Plan Base",Benefits!$CS:$CS,$A32) -> 0.48975 | AH32: =SUMIFS(Benefits!$BD:$BD,Benefits!$E:$E,"Gross Margin",Benefits!$F:$F,"USD",Benefits!$D:$D,"Plan Base",Benefits!$CS:$CS,$A32) -> 0.48975 | AI32: =SUMIFS(Benefits!$BE:$BE,Benefits!$E:$E,"Gross Margin",Benefits!$F:$F,"USD",Benefits!$D:$D,"Plan Base",Benefits!$CS:$CS,$A32) -> 0.48975 | AJ32: =SUMIFS(Benefits!$BF:$BF,Benefits!$E:$E,"Gross Margin",Benefits!$F:$F,"USD",Benefits!$D:$D,"Plan Base",Benefits!$CS:$CS,$A32) -> 0.48975 | AK32: =SUMIFS(Benefits!$BG:$BG,Benefits!$E:$E,"Gross Margin",Benefits!$F:$F,"USD",Benefits!$D:$D,"Plan Base",Benefits!$CS:$CS,$A32) -> 0.48975 | AL32: =SUMIFS(Benefits!$BH:$BH,Benefits!$E:$E,"Gross Margin",Benefits!$F:$F,"USD",Benefits!$D:$D,"Plan Base",Benefits!$CS:$CS,$A32) -> 0.48975 | AM32: =SUMIFS(Benefits!$BI:$BI,Benefits!$E:$E,"Gross Margin",Benefits!$F:$F,"USD",Benefits!$D:$D,"Plan Base",Benefits!$CS:$CS,$A32) -> 0.48975 | AN32: =SUMIFS(Benefits!$BJ:$BJ,Benefits!$E:$E,"Gross Margin",Benefits!$F:$F,"USD",Benefits!$D:$D,"Plan Base",Benefits!$CS:$CS,$A32) -> 0.48975 | AO32: =SUMIFS(Benefits!$BK:$BK,Benefits!$E:$E,"Gross Margin",Benefits!$F:$F,"USD",Benefits!$D:$D,"Plan Base",Benefits!$CS:$CS,$A32) -> 0.48975 | AP32: =SUMIFS(Benefits!$BL:$BL,Benefits!$E:$E,"Gross Margin",Benefits!$F:$F,"USD",Benefits!$D:$D,"Plan Base",Benefits!$CS:$CS,$A32) -> 0.48975 | AQ32: =SUMIFS(Benefits!$BM:$BM,Benefits!$E:$E,"Gross Margin",Benefits!$F:$F,"USD",Benefits!$D:$D,"Plan Base",Benefits!$CS:$CS,$A32) -> 0.48975 | AR32: =SUMIFS(Benefits!$BN:$BN,Benefits!$E:$E,"Gross Margin",Benefits!$F:$F,"USD",Benefits!$D:$D,"Plan Base",Benefits!$CS:$CS,$A32) -> 0.48975 | AS32: =SUMIFS(Benefits!$BO:$BO,Benefits!$E:$E,"Gross Margin",Benefits!$F:$F,"USD",Benefits!$D:$D,"Plan Base",Benefits!$CS:$CS,$A32) -> 0.48975 | AT32: =SUMIFS(Benefits!$BP:$BP,Benefits!$E:$E,"Gross Margin",Benefits!$F:$F,"USD",Benefits!$D:$D,"Plan Base",Benefits!$CS:$CS,$A32) -> 0.48975 | AU32: =SUMIFS(Benefits!$BQ:$BQ,Benefits!$E:$E,"Gross Margin",Benefits!$F:$F,"USD",Benefits!$D:$D,"Plan Base",Benefits!$CS:$CS,$A32) -> 0.48975 | AV32: =SUMIFS(Benefits!$BR:$BR,Benefits!$E:$E,"Gross Margin",Benefits!$F:$F,"USD",Benefits!$D:$D,"Plan Base",Benefits!$CS:$CS,$A32) -> 0.48975 | AW32: =SUMIFS(Benefits!$BS:$BS,Benefits!$E:$E,"Gross Margin",Benefits!$F:$F,"USD",Benefits!$D:$D,"Plan Base",Benefits!$CS:$CS,$A32) -> 0.48975 | AX32: =SUMIFS(Benefits!$BT:$BT,Benefits!$E:$E,"Gross Margin",Benefits!$F:$F,"USD",Benefits!$D:$D,"Plan Base",Benefits!$CS:$CS,$A32) -> 0.48975 | AY32: =SUMIFS(Benefits!$BU:$BU,Benefits!$E:$E,"Gross Margin",Benefits!$F:$F,"USD",Benefits!$D:$D,"Plan Base",Benefits!$CS:$CS,$A32) -> 0.48975 | AZ32: =SUMIFS(Benefits!$BV:$BV,Benefits!$E:$E,"Gross Margin",Benefits!$F:$F,"USD",Benefits!$D:$D,"Plan Base",Benefits!$CS:$CS,$A32) -> 0.48975 | BA32: =SUMIFS(Benefits!$BW:$BW,Benefits!$E:$E,"Gross Margin",Benefits!$F:$F,"USD",Benefits!$D:$D,"Plan Base",Benefits!$CS:$CS,$A32) -> 0.48975 | BB32: =SUMIFS(Benefits!$BX:$BX,Benefits!$E:$E,"Gross Margin",Benefits!$F:$F,"USD",Benefits!$D:$D,"Plan Base",Benefits!$CS:$CS,$A32) -> 0.48975 | BC32: =SUMIFS(Benefits!$BY:$BY,Benefits!$E:$E,"Gross Margin",Benefits!$F:$F,"USD",Benefits!$D:$D,"Plan Base",Benefits!$CS:$CS,$A32) -> 0.48975 | BD32: =SUMIFS(Benefits!$BZ:$BZ,Benefits!$E:$E,"Gross Margin",Benefits!$F:$F,"USD",Benefits!$D:$D,"Plan Base",Benefits!$CS:$CS,$A32) -> 0.48975 | BE32: =SUMIFS(Benefits!$CA:$CA,Benefits!$E:$E,"Gross Margin",Benefits!$F:$F,"USD",Benefits!$D:$D,"Plan Base",Benefits!$CS:$CS,$A32) -> 0.48975 | BF32: =SUMIFS(Benefits!$CB:$CB,Benefits!$E:$E,"Gross Margin",Benefits!$F:$F,"USD",Benefits!$D:$D,"Plan Base",Benefits!$CS:$CS,$A32) -> 0.48975 | BG32: =SUMIFS(Benefits!$CC:$CC,Benefits!$E:$E,"Gross Margin",Benefits!$F:$F,"USD",Benefits!$D:$D,"Plan Base",Benefits!$CS:$CS,$A32) -> 0.48975 | BH32: =SUMIFS(Benefits!$CD:$CD,Benefits!$E:$E,"Gross Margin",Benefits!$F:$F,"USD",Benefits!$D:$D,"Plan Base",Benefits!$CS:$CS,$A32) -> 0.48975 | BI32: =SUMIFS(Benefits!$CE:$CE,Benefits!$E:$E,"Gross Margin",Benefits!$F:$F,"USD",Benefits!$D:$D,"Plan Base",Benefits!$CS:$CS,$A32) -> 0.48975
A33: Southgate Region | B33: =SUMIFS(Benefits!$S:$S,Benefits!$E:$E,"Gross Margin",Benefits!$F:$F,"USD",Benefits!$D:$D,"Plan Base",Benefits!$CS:$CS,$A33) -> 0.322 | C33: =SUMIFS(Benefits!$T:$T,Benefits!$E:$E,"Gross Margin",Benefits!$F:$F,"USD",Benefits!$D:$D,"Plan Base",Benefits!$CS:$CS,$A33) -> 2.779 | D33: =SUMIFS(Benefits!$U:$U,Benefits!$E:$E,"Gross Margin",Benefits!$F:$F,"USD",Benefits!$D:$D,"Plan Base",Benefits!$CS:$CS,$A33) -> 4.409 | E33: =SUMIFS(Benefits!$V:$V,Benefits!$E:$E,"Gross Margin",Benefits!$F:$F,"USD",Benefits!$D:$D,"Plan Base",Benefits!$CS:$CS,$A33) -> 4.409 | F33: =SUMIFS(Benefits!$W:$W,Benefits!$E:$E,"Gross Margin",Benefits!$F:$F,"USD",Benefits!$D:$D,"Plan Base",Benefits!$CS:$CS,$A33) -> 4.409 | H33: =SUMIFS(Benefits!$AD:$AD,Benefits!$E:$E,"Gross Margin",Benefits!$F:$F,"USD",Benefits!$D:$D,"Plan Base",Benefits!$CS:$CS,$A33) -> 0 | I33: =SUMIFS(Benefits!$AE:$AE,Benefits!$E:$E,"Gross Margin",Benefits!$F:$F,"USD",Benefits!$D:$D,"Plan Base",Benefits!$CS:$CS,$A33) -> 0 | J33: =SUMIFS(Benefits!$AF:$AF,Benefits!$E:$E,"Gross Margin",Benefits!$F:$F,"USD",Benefits!$D:$D,"Plan Base",Benefits!$CS:$CS,$A33) -> 0 | K33: =SUMIFS(Benefits!$AG:$AG,Benefits!$E:$E,"Gross Margin",Benefits!$F:$F,"USD",Benefits!$D:$D,"Plan Base",Benefits!$CS:$CS,$A33) -> 0 | L33: =SUMIFS(Benefits!$AH:$AH,Benefits!$E:$E,"Gross Margin",Benefits!$F:$F,"USD",Benefits!$D:$D,"Plan Base",Benefits!$CS:$CS,$A33) -> 0.161 | M33: =SUMIFS(Benefits!$AI:$AI,Benefits!$E:$E,"Gross Margin",Benefits!$F:$F,"USD",Benefits!$D:$D,"Plan Base",Benefits!$CS:$CS,$A33) -> 0.161 | N33: =SUMIFS(Benefits!$AJ:$AJ,Benefits!$E:$E,"Gross Margin",Benefits!$F:$F,"USD",Benefits!$D:$D,"Plan Base",Benefits!$CS:$CS,$A33) -> 0.069 | O33: =SUMIFS(Benefits!$AK:$AK,Benefits!$E:$E,"Gross Margin",Benefits!$F:$F,"USD",Benefits!$D:$D,"Plan Base",Benefits!$CS:$CS,$A33) -> 0.11045455 | P33: =SUMIFS(Benefits!$AL:$AL,Benefits!$E:$E,"Gross Margin",Benefits!$F:$F,"USD",Benefits!$D:$D,"Plan Base",Benefits!$CS:$CS,$A33) -> 0.11045455 | Q33: =SUMIFS(Benefits!$AM:$AM,Benefits!$E:$E,"Gross Margin",Benefits!$F:$F,"USD",Benefits!$D:$D,"Plan Base",Benefits!$CS:$CS,$A33) -> 0.11045455 | R33: =SUMIFS(Benefits!$AN:$AN,Benefits!$E:$E,"Gross Margin",Benefits!$F:$F,"USD",Benefits!$D:$D,"Plan Base",Benefits!$CS:$CS,$A33) -> 0.11045455 | S33: =SUMIFS(Benefits!$AO:$AO,Benefits!$E:$E,"Gross Margin",Benefits!$F:$F,"USD",Benefits!$D:$D,"Plan Base",Benefits!$CS:$CS,$A33) -> 0.26102597 | T33: =SUMIFS(Benefits!$AP:$AP,Benefits!$E:$E,"Gross Margin",Benefits!$F:$F,"USD",Benefits!$D:$D,"Plan Base",Benefits!$CS:$CS,$A33) -> 0.26102597 | U33: =SUMIFS(Benefits!$AQ:$AQ,Benefits!$E:$E,"Gross Margin",Benefits!$F:$F,"USD",Benefits!$D:$D,"Plan Base",Benefits!$CS:$CS,$A33) -> 0.26102597 | V33: =SUMIFS(Benefits!$AR:$AR,Benefits!$E:$E,"Gross Margin",Benefits!$F:$F,"USD",Benefits!$D:$D,"Plan Base",Benefits!$CS:$CS,$A33) -> 0.26102597 | W33: =SUMIFS(Benefits!$AS:$AS,Benefits!$E:$E,"Gross Margin",Benefits!$F:$F,"USD",Benefits!$D:$D,"Plan Base",Benefits!$CS:$CS,$A33) -> 0.26102597 | X33: =SUMIFS(Benefits!$AT:$AT,Benefits!$E:$E,"Gross Margin",Benefits!$F:$F,"USD",Benefits!$D:$D,"Plan Base",Benefits!$CS:$CS,$A33) -> 0.48152597 | Y33: =SUMIFS(Benefits!$AU:$AU,Benefits!$E:$E,"Gross Margin",Benefits!$F:$F,"USD",Benefits!$D:$D,"Plan Base",Benefits!$CS:$CS,$A33) -> 0.48152597 | Z33: =SUMIFS(Benefits!$AV:$AV,Benefits!$E:$E,"Gross Margin",Benefits!$F:$F,"USD",Benefits!$D:$D,"Plan Base",Benefits!$CS:$CS,$A33) -> 0.36741667 | AA33: =SUMIFS(Benefits!$AW:$AW,Benefits!$E:$E,"Gross Margin",Benefits!$F:$F,"USD",Benefits!$D:$D,"Plan Base",Benefits!$CS:$CS,$A33) -> 0.36741667 | AB33: =SUMIFS(Benefits!$AX:$AX,Benefits!$E:$E,"Gross Margin",Benefits!$F:$F,"USD",Benefits!$D:$D,"Plan Base",Benefits!$CS:$CS,$A33) -> 0.36741667 | AC33: =SUMIFS(Benefits!$AY:$AY,Benefits!$E:$E,"Gross Margin",Benefits!$F:$F,"USD",Benefits!$D:$D,"Plan Base",Benefits!$CS:$CS,$A33) -> 0.36741667 | AD33: =SUMIFS(Benefits!$AZ:$AZ,Benefits!$E:$E,"Gross Margin",Benefits!$F:$F,"USD",Benefits!$D:$D,"Plan Base",Benefits!$CS:$CS,$A33) -> 0.36741667 | AE33: =SUMIFS(Benefits!$BA:$BA,Benefits!$E:$E,"Gross Margin",Benefits!$F:$F,"USD",Benefits!$D:$D,"Plan Base",Benefits!$CS:$CS,$A33) -> 0.36741667 | AF33: =SUMIFS(Benefits!$BB:$BB,Benefits!$E:$E,"Gross Margin",Benefits!$F:$F,"USD",Benefits!$D:$D,"Plan Base",Benefits!$CS:$CS,$A33) -> 0.36741667 | AG33: =SUMIFS(Benefits!$BC:$BC,Benefits!$E:$E,"Gross Margin",Benefits!$F:$F,"USD",Benefits!$D:$D,"Plan Base",Benefits!$CS:$CS,$A33) -> 0.36741667 | AH33: =SUMIFS(Benefits!$BD:$BD,Benefits!$E:$E,"Gross Margin",Benefits!$F:$F,"USD",Benefits!$D:$D,"Plan Base",Benefits!$CS:$CS,$A33) -> 0.36741667 | AI33: =SUMIFS(Benefits!$BE:$BE,Benefits!$E:$E,"Gross Margin",Benefits!$F:$F,"USD",Benefits!$D:$D,"Plan Base",Benefits!$CS:$CS,$A33) -> 0.36741667 | AJ33: =SUMIFS(Benefits!$BF:$BF,Benefits!$E:$E,"Gross Margin",Benefits!$F:$F,"USD",Benefits!$D:$D,"Plan Base",Benefits!$CS:$CS,$A33) -> 0.36741667 | AK33: =SUMIFS(Benefits!$BG:$BG,Benefits!$E:$E,"Gross Margin",Benefits!$F:$F,"USD",Benefits!$D:$D,"Plan Base",Benefits!$CS:$CS,$A33) -> 0.36741667 | AL33: =SUMIFS(Benefits!$BH:$BH,Benefits!$E:$E,"Gross Margin",Benefits!$F:$F,"USD",Benefits!$D:$D,"Plan Base",Benefits!$CS:$CS,$A33) -> 0.36741667 | AM33: =SUMIFS(Benefits!$BI:$BI,Benefits!$E:$E,"Gross Margin",Benefits!$F:$F,"USD",Benefits!$D:$D,"Plan Base",Benefits!$CS:$CS,$A33) -> 0.36741667 | AN33: =SUMIFS(Benefits!$BJ:$BJ,Benefits!$E:$E,"Gross Margin",Benefits!$F:$F,"USD",Benefits!$D:$D,"Plan Base",Benefits!$CS:$CS,$A33) -> 0.36741667 | AO33: =SUMIFS(Benefits!$BK:$BK,Benefits!$E:$E,"Gross Margin",Benefits!$F:$F,"USD",Benefits!$D:$D,"Plan Base",Benefits!$CS:$CS,$A33) -> 0.36741667 | AP33: =SUMIFS(Benefits!$BL:$BL,Benefits!$E:$E,"Gross Margin",Benefits!$F:$F,"USD",Benefits!$D:$D,"Plan Base",Benefits!$CS:$CS,$A33) -> 0.36741667 | AQ33: =SUMIFS(Benefits!$BM:$BM,Benefits!$E:$E,"Gross Margin",Benefits!$F:$F,"USD",Benefits!$D:$D,"Plan Base",Benefits!$CS:$CS,$A33) -> 0.36741667 | AR33: =SUMIFS(Benefits!$BN:$BN,Benefits!$E:$E,"Gross Margin",Benefits!$F:$F,"USD",Benefits!$D:$D,"Plan Base",Benefits!$CS:$CS,$A33) -> 0.36741667 | AS33: =SUMIFS(Benefits!$BO:$BO,Benefits!$E:$E,"Gross Margin",Benefits!$F:$F,"USD",Benefits!$D:$D,"Plan Base",Benefits!$CS:$CS,$A33) -> 0.36741667 | AT33: =SUMIFS(Benefits!$BP:$BP,Benefits!$E:$E,"Gross Margin",Benefits!$F:$F,"USD",Benefits!$D:$D,"Plan Base",Benefits!$CS:$CS,$A33) -> 0.36741667 | AU33: =SUMIFS(Benefits!$BQ:$BQ,Benefits!$E:$E,"Gross Margin",Benefits!$F:$F,"USD",Benefits!$D:$D,"Plan Base",Benefits!$CS:$CS,$A33) -> 0.36741667 | AV33: =SUMIFS(Benefits!$BR:$BR,Benefits!$E:$E,"Gross Margin",Benefits!$F:$F,"USD",Benefits!$D:$D,"Plan Base",Benefits!$CS:$CS,$A33) -> 0.36741667 | AW33: =SUMIFS(Benefits!$BS:$BS,Benefits!$E:$E,"Gross Margin",Benefits!$F:$F,"USD",Benefits!$D:$D,"Plan Base",Benefits!$CS:$CS,$A33) -> 0.36741667 | AX33: =SUMIFS(Benefits!$BT:$BT,Benefits!$E:$E,"Gross Margin",Benefits!$F:$F,"USD",Benefits!$D:$D,"Plan Base",Benefits!$CS:$CS,$A33) -> 0.36741667 | AY33: =SUMIFS(Benefits!$BU:$BU,Benefits!$E:$E,"Gross Margin",Benefits!$F:$F,"USD",Benefits!$D:$D,"Plan Base",Benefits!$CS:$CS,$A33) -> 0.36741667 | AZ33: =SUMIFS(Benefits!$BV:$BV,Benefits!$E:$E,"Gross Margin",Benefits!$F:$F,"USD",Benefits!$D:$D,"Plan Base",Benefits!$CS:$CS,$A33) -> 0.36741667 | BA33: =SUMIFS(Benefits!$BW:$BW,Benefits!$E:$E,"Gross Margin",Benefits!$F:$F,"USD",Benefits!$D:$D,"Plan Base",Benefits!$CS:$CS,$A33) -> 0.36741667 | BB33: =SUMIFS(Benefits!$BX:$BX,Benefits!$E:$E,"Gross Margin",Benefits!$F:$F,"USD",Benefits!$D:$D,"Plan Base",Benefits!$CS:$CS,$A33) -> 0.36741667 | BC33: =SUMIFS(Benefits!$BY:$BY,Benefits!$E:$E,"Gross Margin",Benefits!$F:$F,"USD",Benefits!$D:$D,"Plan Base",Benefits!$CS:$CS,$A33) -> 0.36741667 | BD33: =SUMIFS(Benefits!$BZ:$BZ,Benefits!$E:$E,"Gross Margin",Benefits!$F:$F,"USD",Benefits!$D:$D,"Plan Base",Benefits!$CS:$CS,$A33) -> 0.36741667 | BE33: =SUMIFS(Benefits!$CA:$CA,Benefits!$E:$E,"Gross Margin",Benefits!$F:$F,"USD",Benefits!$D:$D,"Plan Base",Benefits!$CS:$CS,$A33) -> 0.36741667 | BF33: =SUMIFS(Benefits!$CB:$CB,Benefits!$E:$E,"Gross Margin",Benefits!$F:$F,"USD",Benefits!$D:$D,"Plan Base",Benefits!$CS:$CS,$A33) -> 0.36741667 | BG33: =SUMIFS(Benefits!$CC:$CC,Benefits!$E:$E,"Gross Margin",Benefits!$F:$F,"USD",Benefits!$D:$D,"Plan Base",Benefits!$CS:$CS,$A33) -> 0.36741667 | BH33: =SUMIFS(Benefits!$CD:$CD,Benefits!$E:$E,"Gross Margin",Benefits!$F:$F,"USD",Benefits!$D:$D,"Plan Base",Benefits!$CS:$CS,$A33) -> 0.36741667 | BI33: =SUMIFS(Benefits!$CE:$CE,Benefits!$E:$E,"Gross Margin",Benefits!$F:$F,"USD",Benefits!$D:$D,"Plan Base",Benefits!$CS:$CS,$A33) -> 0.36741667
A34: Total Gross Margin | B34: =SUM(B30:B33) -> 3.266 | C34: =SUM(C30:C33) -> 14.617 | D34: =SUM(D30:D33) -> 21.633 | E34: =SUM(E30:E33) -> 21.633 | F34: =SUM(F30:F33) -> 21.633 | H34: =SUM(H30:H33) -> 0 | I34: =SUM(I30:I33) -> 0 | J34: =SUM(J30:J33) -> 0 | K34: =SUM(K30:K33) -> 0.372 | L34: =SUM(L30:L33) -> 1.153 | M34: =SUM(M30:M33) -> 1.741 | N34: =SUM(N30:N33) -> 0.52275 | O34: =SUM(O30:O33) -> 0.56420455 | ... BI34: =SUM(BI30:BI33) -> 1.80275
A35: Cost Plan (USD m)
A36: Westmark Region | B36: =SUMIFS(Costs!$AB:$AB,Costs!$D:$D,"Plan",Costs!$DB:$DB,$A36) -> 0.72 | C36: =SUMIFS(Costs!$AC:$AC,Costs!$D:$D,"Plan",Costs!$DB:$DB,$A36) -> 0.9 | D36: =SUMIFS(Costs!$AD:$AD,Costs!$D:$D,"Plan",Costs!$DB:$DB,$A36) -> 0.9 | E36: =SUMIFS(Costs!$AE:$AE,Costs!$D:$D,"Plan",Costs!$DB:$DB,$A36) -> 0.9 | F36: =SUMIFS(Costs!$AF:$AF,Costs!$D:$D,"Plan",Costs!$DB:$DB,$A36) -> 0.9 | H36: =SUMIFS(Costs!$AM:$AM,Costs!$D:$D,"Plan",Costs!$DB:$DB,$A36) -> 0 | I36: =SUMIFS(Costs!$AN:$AN,Costs!$D:$D,"Plan",Costs!$DB:$DB,$A36) -> 0 | J36: =SUMIFS(Costs!$AO:$AO,Costs!$D:$D,"Plan",Costs!$DB:$DB,$A36) -> 0 | K36: =SUMIFS(Costs!$AP:$AP,Costs!$D:$D,"Plan",Costs!$DB:$DB,$A36) -> 0 | L36: =SUMIFS(Costs!$AQ:$AQ,Costs!$D:$D,"Plan",Costs!$DB:$DB,$A36) -> 0.05 | M36: =SUMIFS(Costs!$AR:$AR,Costs!$D:$D,"Plan",Costs!$DB:$DB,$A36) -> 0.67 | N36: =SUMIFS(Costs!$AS:$AS,Costs!$D:$D,"Plan",Costs!$DB:$DB,$A36) -> 0.061666667 | O36: =SUMIFS(Costs!$AT:$AT,Costs!$D:$D,"Plan",Costs!$DB:$DB,$A36) -> 0.061666667 | P36: =SUMIFS(Costs!$AU:$AU,Costs!$D:$D,"Plan",Costs!$DB:$DB,$A36) -> 0.071666667 | Q36: =SUMIFS(Costs!$AV:$AV,Costs!$D:$D,"Plan",Costs!$DB:$DB,$A36) -> 0.071666667 | R36: =SUMIFS(Costs!$AW:$AW,Costs!$D:$D,"Plan",Costs!$DB:$DB,$A36) -> 0.071666667 | S36: =SUMIFS(Costs!$AX:$AX,Costs!$D:$D,"Plan",Costs!$DB:$DB,$A36) -> 0.071666667 | T36: =SUMIFS(Costs!$AY:$AY,Costs!$D:$D,"Plan",Costs!$DB:$DB,$A36) -> 0.071666667 | U36: =SUMIFS(Costs!$AZ:$AZ,Costs!$D:$D,"Plan",Costs!$DB:$DB,$A36) -> 0.071666667 | V36: =SUMIFS(Costs!$BA:$BA,Costs!$D:$D,"Plan",Costs!$DB:$DB,$A36) -> 0.086666667 | W36: =SUMIFS(Costs!$BB:$BB,Costs!$D:$D,"Plan",Costs!$DB:$DB,$A36) -> 0.086666667 | X36: =SUMIFS(Costs!$BC:$BC,Costs!$D:$D,"Plan",Costs!$DB:$DB,$A36) -> 0.086666667 | Y36: =SUMIFS(Costs!$BD:$BD,Costs!$D:$D,"Plan",Costs!$DB:$DB,$A36) -> 0.086666667 | Z36: =SUMIFS(Costs!$BE:$BE,Costs!$D:$D,"Plan",Costs!$DB:$DB,$A36) -> 0.075 | AA36: =SUMIFS(Costs!$BF:$BF,Costs!$D:$D,"Plan",Costs!$DB:$DB,$A36) -> 0.075 | AB36: =SUMIFS(Costs!$BG:$BG,Costs!$D:$D,"Plan",Costs!$DB:$DB,$A36) -> 0.075 | AC36: =SUMIFS(Costs!$BH:$BH,Costs!$D:$D,"Plan",Costs!$DB:$DB,$A36) -> 0.075 | AD36: =SUMIFS(Costs!$BI:$BI,Costs!$D:$D,"Plan",Costs!$DB:$DB,$A36) -> 0.075 | AE36: =SUMIFS(Costs!$BJ:$BJ,Costs!$D:$D,"Plan",Costs!$DB:$DB,$A36) -> 0.075 | AF36: =SUMIFS(Costs!$BK:$BK,Costs!$D:$D,"Plan",Costs!$DB:$DB,$A36) -> 0.075 | AG36: =SUMIFS(Costs!$BL:$BL,Costs!$D:$D,"Plan",Costs!$DB:$DB,$A36) -> 0.075 | AH36: =SUMIFS(Costs!$BM:$BM,Costs!$D:$D,"Plan",Costs!$DB:$DB,$A36) -> 0.075 | AI36: =SUMIFS(Costs!$BN:$BN,Costs!$D:$D,"Plan",Costs!$DB:$DB,$A36) -> 0.075 | AJ36: =SUMIFS(Costs!$BO:$BO,Costs!$D:$D,"Plan",Costs!$DB:$DB,$A36) -> 0.075 | AK36: =SUMIFS(Costs!$BP:$BP,Costs!$D:$D,"Plan",Costs!$DB:$DB,$A36) -> 0.075 | AL36: =SUMIFS(Costs!$BQ:$BQ,Costs!$D:$D,"Plan",Costs!$DB:$DB,$A36) -> 0.075 | AM36: =SUMIFS(Costs!$BR:$BR,Costs!$D:$D,"Plan",Costs!$DB:$DB,$A36) -> 0.075 | AN36: =SUMIFS(Costs!$BS:$BS,Costs!$D:$D,"Plan",Costs!$DB:$DB,$A36) -> 0.075 | AO36: =SUMIFS(Costs!$BT:$BT,Costs!$D:$D,"Plan",Costs!$DB:$DB,$A36) -> 0.075 | AP36: =SUMIFS(Costs!$BU:$BU,Costs!$D:$D,"Plan",Costs!$DB:$DB,$A36) -> 0.075 | AQ36: =SUMIFS(Costs!$BV:$BV,Costs!$D:$D,"Plan",Costs!$DB:$DB,$A36) -> 0.075 | AR36: =SUMIFS(Costs!$BW:$BW,Costs!$D:$D,"Plan",Costs!$DB:$DB,$A36) -> 0.075 | AS36: =SUMIFS(Costs!$BX:$BX,Costs!$D:$D,"Plan",Costs!$DB:$DB,$A36) -> 0.075 | AT36: =SUMIFS(Costs!$BY:$BY,Costs!$D:$D,"Plan",Costs!$DB:$DB,$A36) -> 0.075 | AU36: =SUMIFS(Costs!$BZ:$BZ,Costs!$D:$D,"Plan",Costs!$DB:$DB,$A36) -> 0.075 | AV36: =SUMIFS(Costs!$CA:$CA,Costs!$D:$D,"Plan",Costs!$DB:$DB,$A36) -> 0.075 | AW36: =SUMIFS(Costs!$CB:$CB,Costs!$D:$D,"Plan",Costs!$DB:$DB,$A36) -> 0.075 | AX36: =SUMIFS(Costs!$CC:$CC,Costs!$D:$D,"Plan",Costs!$DB:$DB,$A36) -> 0.075 | AY36: =SUMIFS(Costs!$CD:$CD,Costs!$D:$D,"Plan",Costs!$DB:$DB,$A36) -> 0.075 | AZ36: =SUMIFS(Costs!$CE:$CE,Costs!$D:$D,"Plan",Costs!$DB:$DB,$A36) -> 0.075 | BA36: =SUMIFS(Costs!$CF:$CF,Costs!$D:$D,"Plan",Costs!$DB:$DB,$A36) -> 0.075 | BB36: =SUMIFS(Costs!$CG:$CG,Costs!$D:$D,"Plan",Costs!$DB:$DB,$A36) -> 0.075 | BC36: =SUMIFS(Costs!$CH:$CH,Costs!$D:$D,"Plan",Costs!$DB:$DB,$A36) -> 0.075 | BD36: =SUMIFS(Costs!$CI:$CI,Costs!$D:$D,"Plan",Costs!$DB:$DB,$A36) -> 0.075 | BE36: =SUMIFS(Costs!$CJ:$CJ,Costs!$D:$D,"Plan",Costs!$DB:$DB,$A36) -> 0.075 | BF36: =SUMIFS(Costs!$CK:$CK,Costs!$D:$D,"Plan",Costs!$DB:$DB,$A36) -> 0.075 | BG36: =SUMIFS(Costs!$CL:$CL,Costs!$D:$D,"Plan",Costs!$DB:$DB,$A36) -> 0.075 | BH36: =SUMIFS(Costs!$CM:$CM,Costs!$D:$D,"Plan",Costs!$DB:$DB,$A36) -> 0.075 | BI36: =SUMIFS(Costs!$CN:$CN,Costs!$D:$D,"Plan",Costs!$DB:$DB,$A36) -> 0.075
A37: Eastbridge Region | B37: =SUMIFS(Costs!$AB:$AB,Costs!$D:$D,"Plan",Costs!$DB:$DB,$A37) -> 0.09 | C37: =SUMIFS(Costs!$AC:$AC,Costs!$D:$D,"Plan",Costs!$DB:$DB,$A37) -> 0.788 | D37: =SUMIFS(Costs!$AD:$AD,Costs!$D:$D,"Plan",Costs!$DB:$DB,$A37) -> 0.805 | E37: =SUMIFS(Costs!$AE:$AE,Costs!$D:$D,"Plan",Costs!$DB:$DB,$A37) -> 0.805 | F37: =SUMIFS(Costs!$AF:$AF,Costs!$D:$D,"Plan",Costs!$DB:$DB,$A37) -> 0.805 | H37: =SUMIFS(Costs!$AM:$AM,Costs!$D:$D,"Plan",Costs!$DB:$DB,$A37) -> 0 | I37: =SUMIFS(Costs!$AN:$AN,Costs!$D:$D,"Plan",Costs!$DB:$DB,$A37) -> 0 | J37: =SUMIFS(Costs!$AO:$AO,Costs!$D:$D,"Plan",Costs!$DB:$DB,$A37) -> 0 | K37: =SUMIFS(Costs!$AP:$AP,Costs!$D:$D,"Plan",Costs!$DB:$DB,$A37) -> 0.03 | L37: =SUMIFS(Costs!$AQ:$AQ,Costs!$D:$D,"Plan",Costs!$DB:$DB,$A37) -> 0.03 | M37: =SUMIFS(Costs!$AR:$AR,Costs!$D:$D,"Plan",Costs!$DB:$DB,$A37) -> 0.03 | N37: =SUMIFS(Costs!$AS:$AS,Costs!$D:$D,"Plan",Costs!$DB:$DB,$A37) -> 0.0075 | O37: =SUMIFS(Costs!$AT:$AT,Costs!$D:$D,"Plan",Costs!$DB:$DB,$A37) -> 0.0075 | P37: =SUMIFS(Costs!$AU:$AU,Costs!$D:$D,"Plan",Costs!$DB:$DB,$A37) -> 0.0075 | Q37: =SUMIFS(Costs!$AV:$AV,Costs!$D:$D,"Plan",Costs!$DB:$DB,$A37) -> 0.014833333 | R37: =SUMIFS(Costs!$AW:$AW,Costs!$D:$D,"Plan",Costs!$DB:$DB,$A37) -> 0.014833333 | S37: =SUMIFS(Costs!$AX:$AX,Costs!$D:$D,"Plan",Costs!$DB:$DB,$A37) -> 0.014833333 | T37: =SUMIFS(Costs!$AY:$AY,Costs!$D:$D,"Plan",Costs!$DB:$DB,$A37) -> 0.014833333 | U37: =SUMIFS(Costs!$AZ:$AZ,Costs!$D:$D,"Plan",Costs!$DB:$DB,$A37) -> 0.014833333 | V37: =SUMIFS(Costs!$BA:$BA,Costs!$D:$D,"Plan",Costs!$DB:$DB,$A37) -> 0.14658333 | W37: =SUMIFS(Costs!$BB:$BB,Costs!$D:$D,"Plan",Costs!$DB:$DB,$A37) -> 0.14658333 | X37: =SUMIFS(Costs!$BC:$BC,Costs!$D:$D,"Plan",Costs!$DB:$DB,$A37) -> 0.14658333 | Y37: =SUMIFS(Costs!$BD:$BD,Costs!$D:$D,"Plan",Costs!$DB:$DB,$A37) -> 0.25158333 | Z37: =SUMIFS(Costs!$BE:$BE,Costs!$D:$D,"Plan",Costs!$DB:$DB,$A37) -> 0.067083333 | AA37: =SUMIFS(Costs!$BF:$BF,Costs!$D:$D,"Plan",Costs!$DB:$DB,$A37) -> 0.067083333 | AB37: =SUMIFS(Costs!$BG:$BG,Costs!$D:$D,"Plan",Costs!$DB:$DB,$A37) -> 0.067083333 | AC37: =SUMIFS(Costs!$BH:$BH,Costs!$D:$D,"Plan",Costs!$DB:$DB,$A37) -> 0.067083333 | AD37: =SUMIFS(Costs!$BI:$BI,Costs!$D:$D,"Plan",Costs!$DB:$DB,$A37) -> 0.067083333 | AE37: =SUMIFS(Costs!$BJ:$BJ,Costs!$D:$D,"Plan",Costs!$DB:$DB,$A37) -> 0.067083333 | AF37: =SUMIFS(Costs!$BK:$BK,Costs!$D:$D,"Plan",Costs!$DB:$DB,$A37) -> 0.067083333 | AG37: =SUMIFS(Costs!$BL:$BL,Costs!$D:$D,"Plan",Costs!$DB:$DB,$A37) -> 0.067083333 | AH37: =SUMIFS(Costs!$BM:$BM,Costs!$D:$D,"Plan",Costs!$DB:$DB,$A37) -> 0.067083333 | AI37: =SUMIFS(Costs!$BN:$BN,Costs!$D:$D,"Plan",Costs!$DB:$DB,$A37) -> 0.067083333 | AJ37: =SUMIFS(Costs!$BO:$BO,Costs!$D:$D,"Plan",Costs!$DB:$DB,$A37) -> 0.067083333 | AK37: =SUMIFS(Costs!$BP:$BP,Costs!$D:$D,"Plan",Costs!$DB:$DB,$A37) -> 0.067083333 | AL37: =SUMIFS(Costs!$BQ:$BQ,Costs!$D:$D,"Plan",Costs!$DB:$DB,$A37) -> 0.067083333 | AM37: =SUMIFS(Costs!$BR:$BR,Costs!$D:$D,"Plan",Costs!$DB:$DB,$A37) -> 0.067083333 | AN37: =SUMIFS(Costs!$BS:$BS,Costs!$D:$D,"Plan",Costs!$DB:$DB,$A37) -> 0.067083333 | AO37: =SUMIFS(Costs!$BT:$BT,Costs!$D:$D,"Plan",Costs!$DB:$DB,$A37) -> 0.067083333 | AP37: =SUMIFS(Costs!$BU:$BU,Costs!$D:$D,"Plan",Costs!$DB:$DB,$A37) -> 0.067083333 | AQ37: =SUMIFS(Costs!$BV:$BV,Costs!$D:$D,"Plan",Costs!$DB:$DB,$A37) -> 0.067083333 | AR37: =SUMIFS(Costs!$BW:$BW,Costs!$D:$D,"Plan",Costs!$DB:$DB,$A37) -> 0.067083333 | AS37: =SUMIFS(Costs!$BX:$BX,Costs!$D:$D,"Plan",Costs!$DB:$DB,$A37) -> 0.067083333 | AT37: =SUMIFS(Costs!$BY:$BY,Costs!$D:$D,"Plan",Costs!$DB:$DB,$A37) -> 0.067083333 | AU37: =SUMIFS(Costs!$BZ:$BZ,Costs!$D:$D,"Plan",Costs!$DB:$DB,$A37) -> 0.067083333 | AV37: =SUMIFS(Costs!$CA:$CA,Costs!$D:$D,"Plan",Costs!$DB:$DB,$A37) -> 0.067083333 | AW37: =SUMIFS(Costs!$CB:$CB,Costs!$D:$D,"Plan",Costs!$DB:$DB,$A37) -> 0.067083333 | AX37: =SUMIFS(Costs!$CC:$CC,Costs!$D:$D,"Plan",Costs!$DB:$DB,$A37) -> 0.067083333 | AY37: =SUMIFS(Costs!$CD:$CD,Costs!$D:$D,"Plan",Costs!$DB:$DB,$A37) -> 0.067083333 | AZ37: =SUMIFS(Costs!$CE:$CE,Costs!$D:$D,"Plan",Costs!$DB:$DB,$A37) -> 0.067083333 | BA37: =SUMIFS(Costs!$CF:$CF,Costs!$D:$D,"Plan",Costs!$DB:$DB,$A37) -> 0.067083333 | BB37: =SUMIFS(Costs!$CG:$CG,Costs!$D:$D,"Plan",Costs!$DB:$DB,$A37) -> 0.067083333 | BC37: =SUMIFS(Costs!$CH:$CH,Costs!$D:$D,"Plan",Costs!$DB:$DB,$A37) -> 0.067083333 | BD37: =SUMIFS(Costs!$CI:$CI,Costs!$D:$D,"Plan",Costs!$DB:$DB,$A37) -> 0.067083333 | BE37: =SUMIFS(Costs!$CJ:$CJ,Costs!$D:$D,"Plan",Costs!$DB:$DB,$A37) -> 0.067083333 | BF37: =SUMIFS(Costs!$CK:$CK,Costs!$D:$D,"Plan",Costs!$DB:$DB,$A37) -> 0.067083333 | BG37: =SUMIFS(Costs!$CL:$CL,Costs!$D:$D,"Plan",Costs!$DB:$DB,$A37) -> 0.067083333 | BH37: =SUMIFS(Costs!$CM:$CM,Costs!$D:$D,"Plan",Costs!$DB:$DB,$A37) -> 0.067083333 | BI37: =SUMIFS(Costs!$CN:$CN,Costs!$D:$D,"Plan",Costs!$DB:$DB,$A37) -> 0.067083333
A38: Northpeak Region | B38: =SUMIFS(Costs!$AB:$AB,Costs!$D:$D,"Plan",Costs!$DB:$DB,$A38) -> 0.682 | C38: =SUMIFS(Costs!$AC:$AC,Costs!$D:$D,"Plan",Costs!$DB:$DB,$A38) -> 0.971 | D38: =SUMIFS(Costs!$AD:$AD,Costs!$D:$D,"Plan",Costs!$DB:$DB,$A38) -> 0.971 | E38: =SUMIFS(Costs!$AE:$AE,Costs!$D:$D,"Plan",Costs!$DB:$DB,$A38) -> 0.971 | F38: =SUMIFS(Costs!$AF:$AF,Costs!$D:$D,"Plan",Costs!$DB:$DB,$A38) -> 0.971 | H38: =SUMIFS(Costs!$AM:$AM,Costs!$D:$D,"Plan",Costs!$DB:$DB,$A38) -> 0 | I38: =SUMIFS(Costs!$AN:$AN,Costs!$D:$D,"Plan",Costs!$DB:$DB,$A38) -> 0 | J38: =SUMIFS(Costs!$AO:$AO,Costs!$D:$D,"Plan",Costs!$DB:$DB,$A38) -> 0 | K38: =SUMIFS(Costs!$AP:$AP,Costs!$D:$D,"Plan",Costs!$DB:$DB,$A38) -> 0 | L38: =SUMIFS(Costs!$AQ:$AQ,Costs!$D:$D,"Plan",Costs!$DB:$DB,$A38) -> 0 | M38: =SUMIFS(Costs!$AR:$AR,Costs!$D:$D,"Plan",Costs!$DB:$DB,$A38) -> 0.682 | N38: =SUMIFS(Costs!$AS:$AS,Costs!$D:$D,"Plan",Costs!$DB:$DB,$A38) -> 0.063416667 | O38: =SUMIFS(Costs!$AT:$AT,Costs!$D:$D,"Plan",Costs!$DB:$DB,$A38) -> 0.063416667 | P38: =SUMIFS(Costs!$AU:$AU,Costs!$D:$D,"Plan",Costs!$DB:$DB,$A38) -> 0.063416667 | Q38: =SUMIFS(Costs!$AV:$AV,Costs!$D:$D,"Plan",Costs!$DB:$DB,$A38) -> 0.063416667 | R38: =SUMIFS(Costs!$AW:$AW,Costs!$D:$D,"Plan",Costs!$DB:$DB,$A38) -> 0.078416667 | S38: =SUMIFS(Costs!$AX:$AX,Costs!$D:$D,"Plan",Costs!$DB:$DB,$A38) -> 0.09127381 | T38: =SUMIFS(Costs!$AY:$AY,Costs!$D:$D,"Plan",Costs!$DB:$DB,$A38) -> 0.09127381 | U38: =SUMIFS(Costs!$AZ:$AZ,Costs!$D:$D,"Plan",Costs!$DB:$DB,$A38) -> 0.09127381 | V38: =SUMIFS(Costs!$BA:$BA,Costs!$D:$D,"Plan",Costs!$DB:$DB,$A38) -> 0.09127381 | W38: =SUMIFS(Costs!$BB:$BB,Costs!$D:$D,"Plan",Costs!$DB:$DB,$A38) -> 0.09127381 | X38: =SUMIFS(Costs!$BC:$BC,Costs!$D:$D,"Plan",Costs!$DB:$DB,$A38) -> 0.09127381 | Y38: =SUMIFS(Costs!$BD:$BD,Costs!$D:$D,"Plan",Costs!$DB:$DB,$A38) -> 0.09127381 | Z38: =SUMIFS(Costs!$BE:$BE,Costs!$D:$D,"Plan",Costs!$DB:$DB,$A38) -> 0.080916667 | AA38: =SUMIFS(Costs!$BF:$BF,Costs!$D:$D,"Plan",Costs!$DB:$DB,$A38) -> 0.080916667 | AB38: =SUMIFS(Costs!$BG:$BG,Costs!$D:$D,"Plan",Costs!$DB:$DB,$A38) -> 0.080916667 | AC38: =SUMIFS(Costs!$BH:$BH,Costs!$D:$D,"Plan",Costs!$DB:$DB,$A38) -> 0.080916667 | AD38: =SUMIFS(Costs!$BI:$BI,Costs!$D:$D,"Plan",Costs!$DB:$DB,$A38) -> 0.080916667 | AE38: =SUMIFS(Costs!$BJ:$BJ,Costs!$D:$D,"Plan",Costs!$DB:$DB,$A38) -> 0.080916667 | AF38: =SUMIFS(Costs!$BK:$BK,Costs!$D:$D,"Plan",Costs!$DB:$DB,$A38) -> 0.080916667 | AG38: =SUMIFS(Costs!$BL:$BL,Costs!$D:$D,"Plan",Costs!$DB:$DB,$A38) -> 0.080916667 | AH38: =SUMIFS(Costs!$BM:$BM,Costs!$D:$D,"Plan",Costs!$DB:$DB,$A38) -> 0.080916667 | AI38: =SUMIFS(Costs!$BN:$BN,Costs!$D:$D,"Plan",Costs!$DB:$DB,$A38) -> 0.080916667 | AJ38: =SUMIFS(Costs!$BO:$BO,Costs!$D:$D,"Plan",Costs!$DB:$DB,$A38) -> 0.080916667 | AK38: =SUMIFS(Costs!$BP:$BP,Costs!$D:$D,"Plan",Costs!$DB:$DB,$A38) -> 0.080916667 | AL38: =SUMIFS(Costs!$BQ:$BQ,Costs!$D:$D,"Plan",Costs!$DB:$DB,$A38) -> 0.080916667 | AM38: =SUMIFS(Costs!$BR:$BR,Costs!$D:$D,"Plan",Costs!$DB:$DB,$A38) -> 0.080916667 | AN38: =SUMIFS(Costs!$BS:$BS,Costs!$D:$D,"Plan",Costs!$DB:$DB,$A38) -> 0.080916667 | AO38: =SUMIFS(Costs!$BT:$BT,Costs!$D:$D,"Plan",Costs!$DB:$DB,$A38) -> 0.080916667 | AP38: =SUMIFS(Costs!$BU:$BU,Costs!$D:$D,"Plan",Costs!$DB:$DB,$A38) -> 0.080916667 | AQ38: =SUMIFS(Costs!$BV:$BV,Costs!$D:$D,"Plan",Costs!$DB:$DB,$A38) -> 0.080916667 | AR38: =SUMIFS(Costs!$BW:$BW,Costs!$D:$D,"Plan",Costs!$DB:$DB,$A38) -> 0.080916667 | AS38: =SUMIFS(Costs!$BX:$BX,Costs!$D:$D,"Plan",Costs!$DB:$DB,$A38) -> 0.080916667 | AT38: =SUMIFS(Costs!$BY:$BY,Costs!$D:$D,"Plan",Costs!$DB:$DB,$A38) -> 0.080916667 | AU38: =SUMIFS(Costs!$BZ:$BZ,Costs!$D:$D,"Plan",Costs!$DB:$DB,$A38) -> 0.080916667 | AV38: =SUMIFS(Costs!$CA:$CA,Costs!$D:$D,"Plan",Costs!$DB:$DB,$A38) -> 0.080916667 | AW38: =SUMIFS(Costs!$CB:$CB,Costs!$D:$D,"Plan",Costs!$DB:$DB,$A38) -> 0.080916667 | AX38: =SUMIFS(Costs!$CC:$CC,Costs!$D:$D,"Plan",Costs!$DB:$DB,$A38) -> 0.080916667 | AY38: =SUMIFS(Costs!$CD:$CD,Costs!$D:$D,"Plan",Costs!$DB:$DB,$A38) -> 0.080916667 | AZ38: =SUMIFS(Costs!$CE:$CE,Costs!$D:$D,"Plan",Costs!$DB:$DB,$A38) -> 0.080916667 | BA38: =SUMIFS(Costs!$CF:$CF,Costs!$D:$D,"Plan",Costs!$DB:$DB,$A38) -> 0.080916667 | BB38: =SUMIFS(Costs!$CG:$CG,Costs!$D:$D,"Plan",Costs!$DB:$DB,$A38) -> 0.080916667 | BC38: =SUMIFS(Costs!$CH:$CH,Costs!$D:$D,"Plan",Costs!$DB:$DB,$A38) -> 0.080916667 | BD38: =SUMIFS(Costs!$CI:$CI,Costs!$D:$D,"Plan",Costs!$DB:$DB,$A38) -> 0.080916667 | BE38: =SUMIFS(Costs!$CJ:$CJ,Costs!$D:$D,"Plan",Costs!$DB:$DB,$A38) -> 0.080916667 | BF38: =SUMIFS(Costs!$CK:$CK,Costs!$D:$D,"Plan",Costs!$DB:$DB,$A38) -> 0.080916667 | BG38: =SUMIFS(Costs!$CL:$CL,Costs!$D:$D,"Plan",Costs!$DB:$DB,$A38) -> 0.080916667 | BH38: =SUMIFS(Costs!$CM:$CM,Costs!$D:$D,"Plan",Costs!$DB:$DB,$A38) -> 0.080916667 | BI38: =SUMIFS(Costs!$CN:$CN,Costs!$D:$D,"Plan",Costs!$DB:$DB,$A38) -> 0.080916667
A39: Southgate Region | B39: =SUMIFS(Costs!$AB:$AB,Costs!$D:$D,"Plan",Costs!$DB:$DB,$A39) -> 0.713 | C39: =SUMIFS(Costs!$AC:$AC,Costs!$D:$D,"Plan",Costs!$DB:$DB,$A39) -> 0.884 | D39: =SUMIFS(Costs!$AD:$AD,Costs!$D:$D,"Plan",Costs!$DB:$DB,$A39) -> 0.884 | E39: =SUMIFS(Costs!$AE:$AE,Costs!$D:$D,"Plan",Costs!$DB:$DB,$A39) -> 0.884 | F39: =SUMIFS(Costs!$AF:$AF,Costs!$D:$D,"Plan",Costs!$DB:$DB,$A39) -> 0.884 | H39: =SUMIFS(Costs!$AM:$AM,Costs!$D:$D,"Plan",Costs!$DB:$DB,$A39) -> 0 | I39: =SUMIFS(Costs!$AN:$AN,Costs!$D:$D,"Plan",Costs!$DB:$DB,$A39) -> 0 | J39: =SUMIFS(Costs!$AO:$AO,Costs!$D:$D,"Plan",Costs!$DB:$DB,$A39) -> 0 | K39: =SUMIFS(Costs!$AP:$AP,Costs!$D:$D,"Plan",Costs!$DB:$DB,$A39) -> 0 | L39: =SUMIFS(Costs!$AQ:$AQ,Costs!$D:$D,"Plan",Costs!$DB:$DB,$A39) -> 0.3565 | M39: =SUMIFS(Costs!$AR:$AR,Costs!$D:$D,"Plan",Costs!$DB:$DB,$A39) -> 0.3565 | N39: =SUMIFS(Costs!$AS:$AS,Costs!$D:$D,"Plan",Costs!$DB:$DB,$A39) -> 0.061333333 | O39: =SUMIFS(Costs!$AT:$AT,Costs!$D:$D,"Plan",Costs!$DB:$DB,$A39) -> 0.061333333 | P39: =SUMIFS(Costs!$AU:$AU,Costs!$D:$D,"Plan",Costs!$DB:$DB,$A39) -> 0.061333333 | Q39: =SUMIFS(Costs!$AV:$AV,Costs!$D:$D,"Plan",Costs!$DB:$DB,$A39) -> 0.061333333 | R39: =SUMIFS(Costs!$AW:$AW,Costs!$D:$D,"Plan",Costs!$DB:$DB,$A39) -> 0.061333333 | S39: =SUMIFS(Costs!$AX:$AX,Costs!$D:$D,"Plan",Costs!$DB:$DB,$A39) -> 0.07347619 | T39: =SUMIFS(Costs!$AY:$AY,Costs!$D:$D,"Plan",Costs!$DB:$DB,$A39) -> 0.07347619 | U39: =SUMIFS(Costs!$AZ:$AZ,Costs!$D:$D,"Plan",Costs!$DB:$DB,$A39) -> 0.07347619 | V39: =SUMIFS(Costs!$BA:$BA,Costs!$D:$D,"Plan",Costs!$DB:$DB,$A39) -> 0.07347619 | W39: =SUMIFS(Costs!$BB:$BB,Costs!$D:$D,"Plan",Costs!$DB:$DB,$A39) -> 0.07347619 | X39: =SUMIFS(Costs!$BC:$BC,Costs!$D:$D,"Plan",Costs!$DB:$DB,$A39) -> 0.10497619 | Y39: =SUMIFS(Costs!$BD:$BD,Costs!$D:$D,"Plan",Costs!$DB:$DB,$A39) -> 0.10497619 | Z39: =SUMIFS(Costs!$BE:$BE,Costs!$D:$D,"Plan",Costs!$DB:$DB,$A39) -> 0.073666667 | AA39: =SUMIFS(Costs!$BF:$BF,Costs!$D:$D,"Plan",Costs!$DB:$DB,$A39) -> 0.073666667 | AB39: =SUMIFS(Costs!$BG:$BG,Costs!$D:$D,"Plan",Costs!$DB:$DB,$A39) -> 0.073666667 | AC39: =SUMIFS(Costs!$BH:$BH,Costs!$D:$D,"Plan",Costs!$DB:$DB,$A39) -> 0.073666667 | AD39: =SUMIFS(Costs!$BI:$BI,Costs!$D:$D,"Plan",Costs!$DB:$DB,$A39) -> 0.073666667 | AE39: =SUMIFS(Costs!$BJ:$BJ,Costs!$D:$D,"Plan",Costs!$DB:$DB,$A39) -> 0.073666667 | AF39: =SUMIFS(Costs!$BK:$BK,Costs!$D:$D,"Plan",Costs!$DB:$DB,$A39) -> 0.073666667 | AG39: =SUMIFS(Costs!$BL:$BL,Costs!$D:$D,"Plan",Costs!$DB:$DB,$A39) -> 0.073666667 | AH39: =SUMIFS(Costs!$BM:$BM,Costs!$D:$D,"Plan",Costs!$DB:$DB,$A39) -> 0.073666667 | AI39: =SUMIFS(Costs!$BN:$BN,Costs!$D:$D,"Plan",Costs!$DB:$DB,$A39) -> 0.073666667 | AJ39: =SUMIFS(Costs!$BO:$BO,Costs!$D:$D,"Plan",Costs!$DB:$DB,$A39) -> 0.073666667 | AK39: =SUMIFS(Costs!$BP:$BP,Costs!$D:$D,"Plan",Costs!$DB:$DB,$A39) -> 0.073666667 | AL39: =SUMIFS(Costs!$BQ:$BQ,Costs!$D:$D,"Plan",Costs!$DB:$DB,$A39) -> 0.073666667 | AM39: =SUMIFS(Costs!$BR:$BR,Costs!$D:$D,"Plan",Costs!$DB:$DB,$A39) -> 0.073666667 | AN39: =SUMIFS(Costs!$BS:$BS,Costs!$D:$D,"Plan",Costs!$DB:$DB,$A39) -> 0.073666667 | AO39: =SUMIFS(Costs!$BT:$BT,Costs!$D:$D,"Plan",Costs!$DB:$DB,$A39) -> 0.073666667 | AP39: =SUMIFS(Costs!$BU:$BU,Costs!$D:$D,"Plan",Costs!$DB:$DB,$A39) -> 0.073666667 | AQ39: =SUMIFS(Costs!$BV:$BV,Costs!$D:$D,"Plan",Costs!$DB:$DB,$A39) -> 0.073666667 | AR39: =SUMIFS(Costs!$BW:$BW,Costs!$D:$D,"Plan",Costs!$DB:$DB,$A39) -> 0.073666667 | AS39: =SUMIFS(Costs!$BX:$BX,Costs!$D:$D,"Plan",Costs!$DB:$DB,$A39) -> 0.073666667 | AT39: =SUMIFS(Costs!$BY:$BY,Costs!$D:$D,"Plan",Costs!$DB:$DB,$A39) -> 0.073666667 | AU39: =SUMIFS(Costs!$BZ:$BZ,Costs!$D:$D,"Plan",Costs!$DB:$DB,$A39) -> 0.073666667 | AV39: =SUMIFS(Costs!$CA:$CA,Costs!$D:$D,"Plan",Costs!$DB:$DB,$A39) -> 0.073666667 | AW39: =SUMIFS(Costs!$CB:$CB,Costs!$D:$D,"Plan",Costs!$DB:$DB,$A39) -> 0.073666667 | AX39: =SUMIFS(Costs!$CC:$CC,Costs!$D:$D,"Plan",Costs!$DB:$DB,$A39) -> 0.073666667 | AY39: =SUMIFS(Costs!$CD:$CD,Costs!$D:$D,"Plan",Costs!$DB:$DB,$A39) -> 0.073666667 | AZ39: =SUMIFS(Costs!$CE:$CE,Costs!$D:$D,"Plan",Costs!$DB:$DB,$A39) -> 0.073666667 | BA39: =SUMIFS(Costs!$CF:$CF,Costs!$D:$D,"Plan",Costs!$DB:$DB,$A39) -> 0.073666667 | BB39: =SUMIFS(Costs!$CG:$CG,Costs!$D:$D,"Plan",Costs!$DB:$DB,$A39) -> 0.073666667 | BC39: =SUMIFS(Costs!$CH:$CH,Costs!$D:$D,"Plan",Costs!$DB:$DB,$A39) -> 0.073666667 | BD39: =SUMIFS(Costs!$CI:$CI,Costs!$D:$D,"Plan",Costs!$DB:$DB,$A39) -> 0.073666667 | BE39: =SUMIFS(Costs!$CJ:$CJ,Costs!$D:$D,"Plan",Costs!$DB:$DB,$A39) -> 0.073666667 | BF39: =SUMIFS(Costs!$CK:$CK,Costs!$D:$D,"Plan",Costs!$DB:$DB,$A39) -> 0.073666667 | BG39: =SUMIFS(Costs!$CL:$CL,Costs!$D:$D,"Plan",Costs!$DB:$DB,$A39) -> 0.073666667 | BH39: =SUMIFS(Costs!$CM:$CM,Costs!$D:$D,"Plan",Costs!$DB:$DB,$A39) -> 0.073666667 | BI39: =SUMIFS(Costs!$CN:$CN,Costs!$D:$D,"Plan",Costs!$DB:$DB,$A39) -> 0.073666667
A40: Total Cost Plan | B40: =SUM(B36:B39) -> 2.205 | C40: =SUM(C36:C39) -> 3.543 | D40: =SUM(D36:D39) -> 3.56 | E40: =SUM(E36:E39) -> 3.56 | F40: =SUM(F36:F39) -> 3.56 | H40: =SUM(H36:H39) -> 0 | I40: =SUM(I36:I39) -> 0 | J40: =SUM(J36:J39) -> 0 | K40: =SUM(K36:K39) -> 0.03 | L40: =SUM(L36:L39) -> 0.4365 | M40: =SUM(M36:M39) -> 1.7385 | N40: =SUM(N36:N39) -> 0.19391667 | O40: =SUM(O36:O39) -> 0.19391667 | ... BI40: =SUM(BI36:BI39) -> 0.29666667
A41: Net Value (USD m)
A42: Westmark Region | B42: =B30-B36 -> 0.8 | C42: =C30-C36 -> 3.44 | D42: =D30-D36 -> 4.88 | E42: =E30-E36 -> 4.88 | F42: =F30-F36 -> 4.88 | H42: =H30-H36 -> 0 | I42: =I30-I36 -> 0 | J42: =J30-J36 -> 0 | K42: =K30-K36 -> 0 | L42: =L30-L36 -> 0.57 | M42: =M30-M36 -> 0.23 | N42: =N30-N36 -> 0.15333333 | O42: =O30-O36 -> 0.15333333 | ... BI42: =BI30-BI36 -> 0.40666667
A43: Eastbridge Region | B43: =B31-B37 -> 1.026 | C43: =C31-C37 -> 2.789 | D43: =D31-D37 -> 4.762 | E43: =E31-E37 -> 4.762 | F43: =F31-F37 -> 4.762 | H43: =H31-H37 -> 0 | I43: =I31-I37 -> 0 | J43: =J31-J37 -> 0 | K43: =K31-K37 -> 0.342 | L43: =L31-L37 -> 0.342 | M43: =M31-M37 -> 0.342 | N43: =N31-N37 -> 0.132 | O43: =O31-O37 -> 0.132 | ... BI43: =BI31-BI37 -> 0.39683333
A44: Northpeak Region | B44: =B32-B38 -> -0.374 | C44: =C32-C38 -> 2.95 | D44: =D32-D38 -> 4.906 | E44: =E32-E38 -> 4.906 | F44: =F32-F38 -> 4.906 | H44: =H32-H38 -> 0 | I44: =I32-I38 -> 0 | J44: =J32-J38 -> 0 | K44: =K32-K38 -> 0 | L44: =L32-L38 -> 0 | M44: =M32-M38 -> -0.374 | N44: =N32-N38 -> 0.035833333 | O44: =O32-O38 -> 0.035833333 | ... BI44: =BI32-BI38 -> 0.40883333
A45: Southgate Region | B45: =B33-B39 -> -0.391 | C45: =C33-C39 -> 1.895 | D45: =D33-D39 -> 3.525 | E45: =E33-E39 -> 3.525 | F45: =F33-F39 -> 3.525 | H45: =H33-H39 -> 0 | I45: =I33-I39 -> 0 | J45: =J33-J39 -> 0 | K45: =K33-K39 -> 0 | L45: =L33-L39 -> -0.1955 | M45: =M33-M39 -> -0.1955 | N45: =N33-N39 -> 0.0076666667 | O45: =O33-O39 -> 0.049121212 | ... BI45: =BI33-BI39 -> 0.29375
A46: Total Net Value | B46: =SUM(B42:B45) -> 1.061 | C46: =SUM(C42:C45) -> 11.074 | D46: =SUM(D42:D45) -> 18.073 | E46: =SUM(E42:E45) -> 18.073 | F46: =SUM(F42:F45) -> 18.073 | H46: =SUM(H42:H45) -> 0 | I46: =SUM(I42:I45) -> 0 | J46: =SUM(J42:J45) -> 0 | K46: =SUM(K42:K45) -> 0.342 | L46: =SUM(L42:L45) -> 0.7165 | M46: =SUM(M42:M45) -> 0.0025 | N46: =SUM(N42:N45) -> 0.32883333 | O46: =SUM(O42:O45) -> 0.37028788 | ... BI46: =SUM(BI42:BI45) -> 1.5060833
A48: Actual [regardless of which initiatives delivered it]
A49: Revenue (USD m)
A50: Westmark Region
A51: Eastbridge Region
A52: Northpeak Region
A53: Southgate Region
A54: Total Revenue
A55: Gross Margin (USD m)
A56: Westmark Region
A57: Eastbridge Region
A58: Northpeak Region
A59: Southgate Region
... A72: Total Net Value

Sheet Initiative Summary
A1: Initiative Portfolio — Consolidated Overview
A2: 4 regions · 21 initiatives · USD m, plan basis · value columns reflect the selected Base Year and Case
K3: Base Run Rate Year ▶ | L3: FY28 | M3: Case ▶ | N3: Base
A4: Reference | B4: Initiative | C4: Workstream | D4: Business Units | E4: Type | F4: Tag | G4: Stage | H4: RAG | I4: Priority | J4: Owner | K4: Planned Completion | L4: Revenue (USD m) | M4: Gross Margin (USD m) | N4: Cost Plan (USD m) | O4: Net Value (USD m) | P4: Revenue FY25 Base (USD m) | Q4: Gross Margin FY25 Base (USD m) | R4: Cost Plan FY25 Base (USD m) | S4: Net Value FY25 Base (USD m) | T4: Mile- stones | U4: KPIs | V4: Risks | W4: Actions | X4: Updates
A5: TOR-1 | B5: CAL Accounting System Integration & Automation | C5: Westmark Region | D5: CAL | E5: cost_reduction | F5: automation | G5: 3 | H5: green | I5: high | J5: Dana Reyes | K5: 46647 | L5: {=INDEX('Financial Summary'!$D:$J,MATCH($A5,'Financial Summary'!$A:$A,0)+0+IF($N$3="High",1,0),MATCH($L$3,'Financial Summary'!$D$2:$J$2,0))} -> 0 | M5: {=INDEX('Financial Summary'!$D:$J,MATCH($A5,'Financial Summary'!$A:$A,0)+3+IF($N$3="High",1,0),MATCH($L$3,'Financial Summary'!$D$2:$J$2,0))} -> 0.62 | N5: {=INDEX('Financial Summary'!$D:$J,MATCH($A5,'Financial Summary'!$A:$A,0)+7,MATCH($L$3,'Financial Summary'!$D$2:$J$2,0))} -> 0.06 | O5: {=INDEX('Financial Summary'!$D:$J,MATCH($A5,'Financial Summary'!$A:$A,0)+10+IF($N$3="High",1,0),MATCH($L$3,'Financial Summary'!$D$2:$J$2,0))} -> 0.56 | P5: {=INDEX('Financial Summary'!$D:$K,MATCH($A5,'Financial Summary'!$A:$A,0)+0,MATCH("FY25",'Financial Summary'!$D$2:$K$2,0))} -> 0 | Q5: {=INDEX('Financial Summary'!$D:$K,MATCH($A5,'Financial Summary'!$A:$A,0)+3,MATCH("FY25",'Financial Summary'!$D$2:$K$2,0))} -> 2.192 | R5: {=INDEX('Financial Summary'!$D:$K,MATCH($A5,'Financial Summary'!$A:$A,0)+7,MATCH("FY25",'Financial Summary'!$D$2:$K$2,0))} -> 0.295 | S5: {=INDEX('Financial Summary'!$D:$K,MATCH($A5,'Financial Summary'!$A:$A,0)+10,MATCH("FY25",'Financial Summary'!$D$2:$K$2,0))} -> 1.897 | T5: =COUNTIF(Milestones!$A:$A,$A5) -> 15 | U5: =COUNTIF(KPIs!$A:$A,$A5) -> 12 | V5: =COUNTIF(Risks!$A:$A,$A5) -> 3 | W5: =COUNTIF('Action Items'!$A:$A,$A5) -> 0 | X5: =COUNTIF('Status Updates'!$A:$A,$A5) -> 3
A6: TOR-2 | B6: CAL CoSec System Implementation, Integration & Automation | C6: Westmark Region | D6: CAL | E6: cost_reduction | F6: automation | G6: 3 | H6: green | I6: high | J6: Olivia Tan | K6: 46462 | L6: {=INDEX('Financial Summary'!$D:$J,MATCH($A6,'Financial Summary'!$A:$A,0)+0+IF($N$3="High",1,0),MATCH($L$3,'Financial Summary'!$D$2:$J$2,0))} -> 0 | M6: {=INDEX('Financial Summary'!$D:$J,MATCH($A6,'Financial Summary'!$A:$A,0)+3+IF($N$3="High",1,0),MATCH($L$3,'Financial Summary'!$D$2:$J$2,0))} -> 0.92 | N6: {=INDEX('Financial Summary'!$D:$J,MATCH($A6,'Financial Summary'!$A:$A,0)+7,MATCH($L$3,'Financial Summary'!$D$2:$J$2,0))} -> 0.1 | O6: {=INDEX('Financial Summary'!$D:$J,MATCH($A6,'Financial Summary'!$A:$A,0)+10+IF($N$3="High",1,0),MATCH($L$3,'Financial Summary'!$D$2:$J$2,0))} -> 0.82 | P6: {=INDEX('Financial Summary'!$D:$K,MATCH($A6,'Financial Summary'!$A:$A,0)+0,MATCH("FY25",'Financial Summary'!$D$2:$K$2,0))} -> 0 | Q6: {=INDEX('Financial Summary'!$D:$K,MATCH($A6,'Financial Summary'!$A:$A,0)+3,MATCH("FY25",'Financial Summary'!$D$2:$K$2,0))} -> 3.1 | R6: {=INDEX('Financial Summary'!$D:$K,MATCH($A6,'Financial Summary'!$A:$A,0)+7,MATCH("FY25",'Financial Summary'!$D$2:$K$2,0))} -> 0.322 | S6: {=INDEX('Financial Summary'!$D:$K,MATCH($A6,'Financial Summary'!$A:$A,0)+10,MATCH("FY25",'Financial Summary'!$D$2:$K$2,0))} -> 2.778 | T6: =COUNTIF(Milestones!$A:$A,$A6) -> 20 | U6: =COUNTIF(KPIs!$A:$A,$A6) -> 9 | V6: =COUNTIF(Risks!$A:$A,$A6) -> 3 | W6: =COUNTIF('Action Items'!$A:$A,$A6) -> 0 | X6: =COUNTIF('Status Updates'!$A:$A,$A6) -> 1
A7: TOR-3 | B7: Offshoring to Tavel SSC (+ Automation) - Tax | C7: Westmark Region | D7: CAL | E7: cost_reduction | F7: offshoring | G7: 3 | H7: green | I7: high | J7: Marcus Lee | K7: 46350 | L7: {=INDEX('Financial Summary'!$D:$J,MATCH($A7,'Financial Summary'!$A:$A,0)+0+IF($N$3="High",1,0),MATCH($L$3,'Financial Summary'!$D$2:$J$2,0))} -> 0 | M7: {=INDEX('Financial Summary'!$D:$J,MATCH($A7,'Financial Summary'!$A:$A,0)+3+IF($N$3="High",1,0),MATCH($L$3,'Financial Summary'!$D$2:$J$2,0))} -> 1.86 | N7: {=INDEX('Financial Summary'!$D:$J,MATCH($A7,'Financial Summary'!$A:$A,0)+7,MATCH($L$3,'Financial Summary'!$D$2:$J$2,0))} -> 0.1 | O7: {=INDEX('Financial Summary'!$D:$J,MATCH($A7,'Financial Summary'!$A:$A,0)+10+IF($N$3="High",1,0),MATCH($L$3,'Financial Summary'!$D$2:$J$2,0))} -> 1.76 | P7: {=INDEX('Financial Summary'!$D:$K,MATCH($A7,'Financial Summary'!$A:$A,0)+0,MATCH("FY25",'Financial Summary'!$D$2:$K$2,0))} -> 0 | Q7: {=INDEX('Financial Summary'!$D:$K,MATCH($A7,'Financial Summary'!$A:$A,0)+3,MATCH("FY25",'Financial Summary'!$D$2:$K$2,0))} -> 8.652 | R7: {=INDEX('Financial Summary'!$D:$K,MATCH($A7,'Financial Summary'!$A:$A,0)+7,MATCH("FY25",'Financial Summary'!$D$2:$K$2,0))} -> 0.406 | S7: {=INDEX('Financial Summary'!$D:$K,MATCH($A7,'Financial Summary'!$A:$A,0)+10,MATCH("FY25",'Financial Summary'!$D$2:$K$2,0))} -> 8.246 | T7: =COUNTIF(Milestones!$A:$A,$A7) -> 14 | U7: =COUNTIF(KPIs!$A:$A,$A7) -> 21 | V7: =COUNTIF(Risks!$A:$A,$A7) -> 3 | W7: =COUNTIF('Action Items'!$A:$A,$A7) -> 0 | X7: =COUNTIF('Status Updates'!$A:$A,$A7) -> 0
A8: TOR-4 | B8: Verland-Norvia New Logos - FDI | C8: Westmark Region | D8: VER | E8: revenue | F8: commercial | G8: 3 | H8: green | I8: high | J8: Lukas Brandt | K8: 46357 | L8: {=INDEX('Financial Summary'!$D:$J,MATCH($A8,'Financial Summary'!$A:$A,0)+0+IF($N$3="High",1,0),MATCH($L$3,'Financial Summary'!$D$2:$J$2,0))} -> 1.1 | M8: {=INDEX('Financial Summary'!$D:$J,MATCH($A8,'Financial Summary'!$A:$A,0)+3+IF($N$3="High",1,0),MATCH($L$3,'Financial Summary'!$D$2:$J$2,0))} -> 0.72 | N8: {=INDEX('Financial Summary'!$D:$J,MATCH($A8,'Financial Summary'!$A:$A,0)+7,MATCH($L$3,'Financial Summary'!$D$2:$J$2,0))} -> 0.64 | O8: {=INDEX('Financial Summary'!$D:$J,MATCH($A8,'Financial Summary'!$A:$A,0)+10+IF($N$3="High",1,0),MATCH($L$3,'Financial Summary'!$D$2:$J$2,0))} -> 0.08 | P8: {=INDEX('Financial Summary'!$D:$K,MATCH($A8,'Financial Summary'!$A:$A,0)+0,MATCH("FY25",'Financial Summary'!$D$2:$K$2,0))} -> 3.961 | Q8: {=INDEX('Financial Summary'!$D:$K,MATCH($A8,'Financial Summary'!$A:$A,0)+3,MATCH("FY25",'Financial Summary'!$D$2:$K$2,0))} -> 3.016 | R8: {=INDEX('Financial Summary'!$D:$K,MATCH($A8,'Financial Summary'!$A:$A,0)+7,MATCH("FY25",'Financial Summary'!$D$2:$K$2,0))} -> 1.961 | S8: {=INDEX('Financial Summary'!$D:$K,MATCH($A8,'Financial Summary'!$A:$A,0)+10,MATCH("FY25",'Financial Summary'!$D$2:$K$2,0))} -> 1.055 | T8: =COUNTIF(Milestones!$A:$A,$A8) -> 10 | U8: =COUNTIF(KPIs!$A:$A,$A8) -> 9 | V8: =COUNTIF(Risks!$A:$A,$A8) -> 0 | W8: =COUNTIF('Action Items'!$A:$A,$A8) -> 0 | X8: =COUNTIF('Status Updates'!$A:$A,$A8) -> 0
A9: TOR-5 | B9: Advisory - Geographical Expansion | C9: Westmark Region | D9: CAL | E9: revenue | F9: commercial | G9: 3 | H9: green | I9: high | J9: Grace Liang | K9: 46745 | L9: {=INDEX('Financial Summary'!$D:$J,MATCH($A9,'Financial Summary'!$A:$A,0)+0+IF($N$3="High",1,0),MATCH($L$3,'Financial Summary'!$D$2:$J$2,0))} -> 2.46 | M9: {=INDEX('Financial Summary'!$D:$J,MATCH($A9,'Financial Summary'!$A:$A,0)+3+IF($N$3="High",1,0),MATCH($L$3,'Financial Summary'!$D$2:$J$2,0))} -> 1.42 | N9: {=INDEX('Financial Summary'!$D:$J,MATCH($A9,'Financial Summary'!$A:$A,0)+7,MATCH($L$3,'Financial Summary'!$D$2:$J$2,0))} -> 0 | O9: {=INDEX('Financial Summary'!$D:$J,MATCH($A9,'Financial Summary'!$A:$A,0)+10+IF($N$3="High",1,0),MATCH($L$3,'Financial Summary'!$D$2:$J$2,0))} -> 1.42 | P9: {=INDEX('Financial Summary'!$D:$K,MATCH($A9,'Financial Summary'!$A:$A,0)+0,MATCH("FY25",'Financial Summary'!$D$2:$K$2,0))} -> 10.967 | Q9: {=INDEX('Financial Summary'!$D:$K,MATCH($A9,'Financial Summary'!$A:$A,0)+3,MATCH("FY25",'Financial Summary'!$D$2:$K$2,0))} -> 6.12 | R9: {=INDEX('Financial Summary'!$D:$K,MATCH($A9,'Financial Summary'!$A:$A,0)+7,MATCH("FY25",'Financial Summary'!$D$2:$K$2,0))} -> 0 | S9: {=INDEX('Financial Summary'!$D:$K,MATCH($A9,'Financial Summary'!$A:$A,0)+10,MATCH("FY25",'Financial Summary'!$D$2:$K$2,0))} -> 6.12 | T9: =COUNTIF(Milestones!$A:$A,$A9) -> 10 | U9: =COUNTIF(KPIs!$A:$A,$A9) -> 9 | V9: =COUNTIF(Risks!$A:$A,$A9) -> 0 | W9: =COUNTIF('Action Items'!$A:$A,$A9) -> 0 | X9: =COUNTIF('Status Updates'!$A:$A,$A9) -> 0
A10: TOR-6 | B10: [GROUP] Revenue Retention: Reinvent CSM for Proactive Churn Management (Westmark) | C10: Westmark Region | D10: GROUP, CAL, VER | E10: revenue | F10: commercial | G10: 3 | H10: green | I10: high | J10: Julien Moreau | K10: 46501 | L10: {=INDEX('Financial Summary'!$D:$J,MATCH($A10,'Financial Summary'!$A:$A,0)+0+IF($N$3="High",1,0),MATCH($L$3,'Financial Summary'!$D$2:$J$2,0))} -> 0.4 | M10: {=INDEX('Financial Summary'!$D:$J,MATCH($A10,'Financial Summary'!$A:$A,0)+3+IF($N$3="High",1,0),MATCH($L$3,'Financial Summary'!$D$2:$J$2,0))} -> 0.24 | N10: {=INDEX('Financial Summary'!$D:$J,MATCH($A10,'Financial Summary'!$A:$A,0)+7,MATCH($L$3,'Financial Summary'!$D$2:$J$2,0))} -> 0 | O10: {=INDEX('Financial Summary'!$D:$J,MATCH($A10,'Financial Summary'!$A:$A,0)+10+IF($N$3="High",1,0),MATCH($L$3,'Financial Summary'!$D$2:$J$2,0))} -> 0.24 | P10: {=INDEX('Financial Summary'!$D:$K,MATCH($A10,'Financial Summary'!$A:$A,0)+0,MATCH("FY25",'Financial Summary'!$D$2:$K$2,0))} -> 1.545 | Q10: {=INDEX('Financial Summary'!$D:$K,MATCH($A10,'Financial Summary'!$A:$A,0)+3,MATCH("FY25",'Financial Summary'!$D$2:$K$2,0))} -> 1.024 | R10: {=INDEX('Financial Summary'!$D:$K,MATCH($A10,'Financial Summary'!$A:$A,0)+7,MATCH("FY25",'Financial Summary'!$D$2:$K$2,0))} -> 0 | S10: {=INDEX('Financial Summary'!$D:$K,MATCH($A10,'Financial Summary'!$A:$A,0)+10,MATCH("FY25",'Financial Summary'!$D$2:$K$2,0))} -> 1.024 | T10: =COUNTIF(Milestones!$A:$A,$A10) -> 18 | U10: =COUNTIF(KPIs!$A:$A,$A10) -> 9 | V10: =COUNTIF(Risks!$A:$A,$A10) -> 0 | W10: =COUNTIF('Action Items'!$A:$A,$A10) -> 0 | X10: =COUNTIF('Status Updates'!$A:$A,$A10) -> 0
A11: EBR-1 | B11: MER Billing System Integration & Automation | C11: Eastbridge Region | D11: MER | E11: cost_reduction | F11: automation | G11: 3 | H11: green | I11: high | J11: Priya Nadkarni | K11: 46487 | L11: {=INDEX('Financial Summary'!$D:$J,MATCH($A11,'Financial Summary'!$A:$A,0)+0+IF($N$3="High",1,0),MATCH($L$3,'Financial Summary'!$D$2:$J$2,0))} -> 0 | M11: {=INDEX('Financial Summary'!$D:$J,MATCH($A11,'Financial Summary'!$A:$A,0)+3+IF($N$3="High",1,0),MATCH($L$3,'Financial Summary'!$D$2:$J$2,0))} -> 0.682 | N11: {=INDEX('Financial Summary'!$D:$J,MATCH($A11,'Financial Summary'!$A:$A,0)+7,MATCH($L$3,'Financial Summary'!$D$2:$J$2,0))} -> 0.066 | O11: {=INDEX('Financial Summary'!$D:$J,MATCH($A11,'Financial Summary'!$A:$A,0)+10+IF($N$3="High",1,0),MATCH($L$3,'Financial Summary'!$D$2:$J$2,0))} -> 0.616 | P11: {=INDEX('Financial Summary'!$D:$K,MATCH($A11,'Financial Summary'!$A:$A,0)+0,MATCH("FY25",'Financial Summary'!$D$2:$K$2,0))} -> 0 | Q11: {=INDEX('Financial Summary'!$D:$K,MATCH($A11,'Financial Summary'!$A:$A,0)+3,MATCH("FY25",'Financial Summary'!$D$2:$K$2,0))} -> 3.2 | R11: {=INDEX('Financial Summary'!$D:$K,MATCH($A11,'Financial Summary'!$A:$A,0)+7,MATCH("FY25",'Financial Summary'!$D$2:$K$2,0))} -> 0.261 | S11: {=INDEX('Financial Summary'!$D:$K,MATCH($A11,'Financial Summary'!$A:$A,0)+10,MATCH("FY25",'Financial Summary'!$D$2:$K$2,0))} -> 2.939 | T11: =COUNTIF(Milestones!$A:$A,$A11) -> 15 | U11: =COUNTIF(KPIs!$A:$A,$A11) -> 12 | V11: =COUNTIF(Risks!$A:$A,$A11) -> 3 | W11: =COUNTIF('Action Items'!$A:$A,$A11) -> 0 | X11: =COUNTIF('Status Updates'!$A:$A,$A11) -> 0
A12: EBR-2 | B12: Offshoring to Caldez SSC (+ Automation) - Payroll | C12: Eastbridge Region | D12: MER | E12: cost_reduction | F12: offshoring | G12: 3 | H12: green | I12: high | J12: Marcus Lee | K12: 46302 | L12: {=INDEX('Financial Summary'!$D:$J,MATCH($A12,'Financial Summary'!$A:$A,0)+0+IF($N$3="High",1,0),MATCH($L$3,'Financial Summary'!$D$2:$J$2,0))} -> 0 | M12: {=INDEX('Financial Summary'!$D:$J,MATCH($A12,'Financial Summary'!$A:$A,0)+3+IF($N$3="High",1,0),MATCH($L$3,'Financial Summary'!$D$2:$J$2,0))} -> 1.674 | N12: {=INDEX('Financial Summary'!$D:$J,MATCH($A12,'Financial Summary'!$A:$A,0)+7,MATCH($L$3,'Financial Summary'!$D$2:$J$2,0))} -> 0.09 | O12: {=INDEX('Financial Summary'!$D:$J,MATCH($A12,'Financial Summary'!$A:$A,0)+10+IF($N$3="High",1,0),MATCH($L$3,'Financial Summary'!$D$2:$J$2,0))} -> 1.584 | P12: {=INDEX('Financial Summary'!$D:$K,MATCH($A12,'Financial Summary'!$A:$A,0)+0,MATCH("FY25",'Financial Summary'!$D$2:$K$2,0))} -> 0 | Q12: {=INDEX('Financial Summary'!$D:$K,MATCH($A12,'Financial Summary'!$A:$A,0)+3,MATCH("FY25",'Financial Summary'!$D$2:$K$2,0))} -> 7.339 | R12: {=INDEX('Financial Summary'!$D:$K,MATCH($A12,'Financial Summary'!$A:$A,0)+7,MATCH("FY25",'Financial Summary'!$D$2:$K$2,0))} -> 0.322 | S12: {=INDEX('Financial Summary'!$D:$K,MATCH($A12,'Financial Summary'!$A:$A,0)+10,MATCH("FY25",'Financial Summary'!$D$2:$K$2,0))} -> 7.017 | T12: =COUNTIF(Milestones!$A:$A,$A12) -> 14 | U12: =COUNTIF(KPIs!$A:$A,$A12) -> 21 | V12: =COUNTIF(Risks!$A:$A,$A12) -> 3 | W12: =COUNTIF('Action Items'!$A:$A,$A12) -> 0 | X12: =COUNTIF('Status Updates'!$A:$A,$A12) -> 0
A13: EBR-3 | B13: Audit Practice - Cross-Border Expansion | C13: Eastbridge Region | D13: MER | E13: revenue | F13: commercial | G13: 3 | H13: green | I13: high | J13: Niels Berg | K13: 46585 | L13: {=INDEX('Financial Summary'!$D:$J,MATCH($A13,'Financial Summary'!$A:$A,0)+0+IF($N$3="High",1,0),MATCH($L$3,'Financial Summary'!$D$2:$J$2,0))} -> 2.829 | M13: {=INDEX('Financial Summary'!$D:$J,MATCH($A13,'Financial Summary'!$A:$A,0)+3+IF($N$3="High",1,0),MATCH($L$3,'Financial Summary'!$D$2:$J$2,0))} -> 1.633 | N13: {=INDEX('Financial Summary'!$D:$J,MATCH($A13,'Financial Summary'!$A:$A,0)+7,MATCH($L$3,'Financial Summary'!$D$2:$J$2,0))} -> 0 | O13: {=INDEX('Financial Summary'!$D:$J,MATCH($A13,'Financial Summary'!$A:$A,0)+10+IF($N$3="High",1,0),MATCH($L$3,'Financial Summary'!$D$2:$J$2,0))} -> 1.633 | P13: {=INDEX('Financial Summary'!$D:$K,MATCH($A13,'Financial Summary'!$A:$A,0)+0,MATCH("FY25",'Financial Summary'!$D$2:$K$2,0))} -> 12.722 | Q13: {=INDEX('Financial Summary'!$D:$K,MATCH($A13,'Financial Summary'!$A:$A,0)+3,MATCH("FY25",'Financial Summary'!$D$2:$K$2,0))} -> 7.592 | R13: {=INDEX('Financial Summary'!$D:$K,MATCH($A13,'Financial Summary'!$A:$A,0)+7,MATCH("FY25",'Financial Summary'!$D$2:$K$2,0))} -> 0 | S13: {=INDEX('Financial Summary'!$D:$K,MATCH($A13,'Financial Summary'!$A:$A,0)+10,MATCH("FY25",'Financial Summary'!$D$2:$K$2,0))} -> 7.592 | T13: =COUNTIF(Milestones!$A:$A,$A13) -> 10 | U13: =COUNTIF(KPIs!$A:$A,$A13) -> 9 | V13: =COUNTIF(Risks!$A:$A,$A13) -> 0 | W13: =COUNTIF('Action Items'!$A:$A,$A13) -> 0 | X13: =COUNTIF('Status Updates'!$A:$A,$A13) -> 0
A14: EBR-4 | B14: MER-RDG New Logos - Manufacturing | C14: Eastbridge Region | D14: RDG | E14: revenue | F14: commercial | G14: 3 | H14: green | I14: high | J14: Aisha Rahman | K14: 46632 | L14: {=INDEX('Financial Summary'!$D:$J,MATCH($A14,'Financial Summary'!$A:$A,0)+0+IF($N$3="High",1,0),MATCH($L$3,'Financial Summary'!$D$2:$J$2,0))} -> 0.935 | M14: {=INDEX('Financial Summary'!$D:$J,MATCH($A14,'Financial Summary'!$A:$A,0)+3+IF($N$3="High",1,0),MATCH($L$3,'Financial Summary'!$D$2:$J$2,0))} -> 0.612 | N14: {=INDEX('Financial Summary'!$D:$J,MATCH($A14,'Financial Summary'!$A:$A,0)+7,MATCH($L$3,'Financial Summary'!$D$2:$J$2,0))} -> 0.544 | O14: {=INDEX('Financial Summary'!$D:$J,MATCH($A14,'Financial Summary'!$A:$A,0)+10+IF($N$3="High",1,0),MATCH($L$3,'Financial Summary'!$D$2:$J$2,0))} -> 0.068 | P14: {=INDEX('Financial Summary'!$D:$K,MATCH($A14,'Financial Summary'!$A:$A,0)+0,MATCH("FY25",'Financial Summary'!$D$2:$K$2,0))} -> 3.967 | Q14: {=INDEX('Financial Summary'!$D:$K,MATCH($A14,'Financial Summary'!$A:$A,0)+3,MATCH("FY25",'Financial Summary'!$D$2:$K$2,0))} -> 2.337 | R14: {=INDEX('Financial Summary'!$D:$K,MATCH($A14,'Financial Summary'!$A:$A,0)+7,MATCH("FY25",'Financial Summary'!$D$2:$K$2,0))} -> 2.143 | S14: {=INDEX('Financial Summary'!$D:$K,MATCH($A14,'Financial Summary'!$A:$A,0)+10,MATCH("FY25",'Financial Summary'!$D$2:$K$2,0))} -> 0.194 | T14: =COUNTIF(Milestones!$A:$A,$A14) -> 10 | U14: =COUNTIF(KPIs!$A:$A,$A14) -> 9 | V14: =COUNTIF(Risks!$A:$A,$A14) -> 0 | W14: =COUNTIF('Action Items'!$A:$A,$A14) -> 0 | X14: =COUNTIF('Status Updates'!$A:$A,$A14) -> 0
A15: EBR-5 | B15: RDG Document Automation & OCR Rollout | C15: Eastbridge Region | D15: RDG | E15: cost_reduction | F15: automation | G15: 3 | H15: green | I15: high | J15: Elena Vasquez | K15: 46746 | L15: {=INDEX('Financial Summary'!$D:$J,MATCH($A15,'Financial Summary'!$A:$A,0)+0+IF($N$3="High",1,0),MATCH($L$3,'Financial Summary'!$D$2:$J$2,0))} -> 0 | M15: {=INDEX('Financial Summary'!$D:$J,MATCH($A15,'Financial Summary'!$A:$A,0)+3+IF($N$3="High",1,0),MATCH($L$3,'Financial Summary'!$D$2:$J$2,0))} -> 0.966 | N15: {=INDEX('Financial Summary'!$D:$J,MATCH($A15,'Financial Summary'!$A:$A,0)+7,MATCH($L$3,'Financial Summary'!$D$2:$J$2,0))} -> 0.105 | O15: {=INDEX('Financial Summary'!$D:$J,MATCH($A15,'Financial Summary'!$A:$A,0)+10+IF($N$3="High",1,0),MATCH($L$3,'Financial Summary'!$D$2:$J$2,0))} -> 0.861 | P15: {=INDEX('Financial Summary'!$D:$K,MATCH($A15,'Financial Summary'!$A:$A,0)+0,MATCH("FY25",'Financial Summary'!$D$2:$K$2,0))} -> 0 | Q15: {=INDEX('Financial Summary'!$D:$K,MATCH($A15,'Financial Summary'!$A:$A,0)+3,MATCH("FY25",'Financial Summary'!$D$2:$K$2,0))} -> 4.022 | R15: {=INDEX('Financial Summary'!$D:$K,MATCH($A15,'Financial Summary'!$A:$A,0)+7,MATCH("FY25",'Financial Summary'!$D$2:$K$2,0))} -> 0.323 | S15: {=INDEX('Financial Summary'!$D:$K,MATCH($A15,'Financial Summary'!$A:$A,0)+10,MATCH("FY25",'Financial Summary'!$D$2:$K$2,0))} -> 3.699 | T15: =COUNTIF(Milestones!$A:$A,$A15) -> 20 | U15: =COUNTIF(KPIs!$A:$A,$A15) -> 9 | V15: =COUNTIF(Risks!$A:$A,$A15) -> 3 | W15: =COUNTIF('Action Items'!$A:$A,$A15) -> 0 | X15: =COUNTIF('Status Updates'!$A:$A,$A15) -> 0
A16: NPK-1 | B16: FJD Reconciliation Automation (RPA) | C16: Northpeak Region | D16: FJD | E16: cost_reduction | F16: automation | G16: 3 | H16: green | I16: high | J16: Priya Nadkarni | K16: 46397 | L16: {=INDEX('Financial Summary'!$D:$J,MATCH($A16,'Financial Summary'!$A:$A,0)+0+IF($N$3="High",1,0),MATCH($L$3,'Financial Summary'!$D$2:$J$2,0))} -> 0 | M16: {=INDEX('Financial Summary'!$D:$J,MATCH($A16,'Financial Summary'!$A:$A,0)+3+IF($N$3="High",1,0),MATCH($L$3,'Financial Summary'!$D$2:$J$2,0))} -> 0.589 | N16: {=INDEX('Financial Summary'!$D:$J,MATCH($A16,'Financial Summary'!$A:$A,0)+7,MATCH($L$3,'Financial Summary'!$D$2:$J$2,0))} -> 0.057 | O16: {=INDEX('Financial Summary'!$D:$J,MATCH($A16,'Financial Summary'!$A:$A,0)+10+IF($N$3="High",1,0),MATCH($L$3,'Financial Summary'!$D$2:$J$2,0))} -> 0.532 | P16: {=INDEX('Financial Summary'!$D:$K,MATCH($A16,'Financial Summary'!$A:$A,0)+0,MATCH("FY25",'Financial Summary'!$D$2:$K$2,0))} -> 0 | Q16: {=INDEX('Financial Summary'!$D:$K,MATCH($A16,'Financial Summary'!$A:$A,0)+3,MATCH("FY25",'Financial Summary'!$D$2:$K$2,0))} -> 1.947 | R16: {=INDEX('Financial Summary'!$D:$K,MATCH($A16,'Financial Summary'!$A:$A,0)+7,MATCH("FY25",'Financial Summary'!$D$2:$K$2,0))} -> 0.253 | S16: {=INDEX('Financial Summary'!$D:$K,MATCH($A16,'Financial Summary'!$A:$A,0)+10,MATCH("FY25",'Financial Summary'!$D$2:$K$2,0))} -> 1.694 | T16: =COUNTIF(Milestones!$A:$A,$A16) -> 15 | U16: =COUNTIF(KPIs!$A:$A,$A16) -> 12 | V16: =COUNTIF(Risks!$A:$A,$A16) -> 3 | W16: =COUNTIF('Action Items'!$A:$A,$A16) -> 0 | X16: =COUNTIF('Status Updates'!$A:$A,$A16) -> 0
... A25: SGT-4 | B25: Advisory - Geographical Expansion (Vandor) | C25: Southgate Region | D25: VSC | E25: revenue | F25: commercial | G25: 3 | H25: green | I25: high | J25: Marco Bianchi | K25: 46426 | L25: {=INDEX('Financial Summary'!$D:$J,MATCH($A25,'Financial Summary'!$A:$A,0)+0+IF($N$3="High",1,0),MATCH($L$3,'Financial Summary'!$D$2:$J$2,0))} -> 2.337 | M25: {=INDEX('Financial Summary'!$D:$J,MATCH($A25,'Financial Summary'!$A:$A,0)+3+IF($N$3="High",1,0),MATCH($L$3,'Financial Summary'!$D$2:$J$2,0))} -> 1.349 | N25: {=INDEX('Financial Summary'!$D:$J,MATCH($A25,'Financial Summary'!$A:$A,0)+7,MATCH($L$3,'Financial Summary'!$D$2:$J$2,0))} -> 0 | O25: {=INDEX('Financial Summary'!$D:$J,MATCH($A25,'Financial Summary'!$A:$A,0)+10+IF($N$3="High",1,0),MATCH($L$3,'Financial Summary'!$D$2:$J$2,0))} -> 1.349 | P25: {=INDEX('Financial Summary'!$D:$K,MATCH($A25,'Financial Summary'!$A:$A,0)+0,MATCH("FY25",'Financial Summary'!$D$2:$K$2,0))} -> 11.006 | Q25: {=INDEX('Financial Summary'!$D:$K,MATCH($A25,'Financial Summary'!$A:$A,0)+3,MATCH("FY25",'Financial Summary'!$D$2:$K$2,0))} -> 4.587 | R25: {=INDEX('Financial Summary'!$D:$K,MATCH($A25,'Financial Summary'!$A:$A,0)+7,MATCH("FY25",'Financial Summary'!$D$2:$K$2,0))} -> 0 | S25: {=INDEX('Financial Summary'!$D:$K,MATCH($A25,'Financial Summary'!$A:$A,0)+10,MATCH("FY25",'Financial Summary'!$D$2:$K$2,0))} -> 4.587 | T25: =COUNTIF(Milestones!$A:$A,$A25) -> 10 | U25: =COUNTIF(KPIs!$A:$A,$A25) -> 9 | V25: =COUNTIF(Risks!$A:$A,$A25) -> 0 | W25: =COUNTIF('Action Items'!$A:$A,$A25) -> 0 | X25: =COUNTIF('Status Updates'!$A:$A,$A25) -> 0
A26: PORTFOLIO TOTAL | L26: =SUM(L5:L25) -> 15.004 | M26: =SUM(M5:M25) -> 21.633 | N26: =SUM(N5:N25) -> 3.56 | O26: =SUM(O5:O25) -> 18.073 | P26: =SUM(P5:P25) -> 67.466 | Q26: =SUM(Q5:Q25) -> 87.96 | R26: =SUM(R5:R25) -> 13.265 | S26: =SUM(S5:S25) -> 74.695 | ... X26: =SUM(X5:X25) -> 4

Sheet Charter Details
A1: Initiative Charter Details
A2: Field | B2: TOR-1 CAL Accounting System Integration & Automation | C2: TOR-2 CAL CoSec System Implementation, Integration & Automation | D2: TOR-3 Offshoring to Tavel SSC (+ Automation) - Tax | E2: TOR-4 Verland-Norvia New Logos - FDI | F2: TOR-5 Advisory - Geographical Expansion | G2: TOR-6 [GROUP] Revenue Retention: Reinvent CSM for Proactive Churn Management (Westmark) | H2: TOR-1 CAL Accounting System Integration & Automation | I2: TOR-3 Offshoring to Tavel SSC (+ Automation) - Tax | J2: TOR-5 Advisory - Geographical Expansion | K2: TOR-4 Verland-Norvia New Logos - FDI | L2: TOR-2 CAL CoSec System Implementation, Integration & Automation | M2: TOR-1 CAL Accounting System Integration & Automation | N2: TOR-3 Offshoring to Tavel SSC (+ Automation) - Tax | O2: TOR-5 Advisory - Geographical Expansion | P2: TOR-4 Verland-Norvia New Logos - FDI | Q2: TOR-2 CAL CoSec System Implementation, Integration & Automation | R2: TOR-6 [GROUP] Revenue Retention: Reinvent CSM for Proactive Churn Management (Westmark) | S2: TOR-1 CAL Accounting System Integration & Automation | T2: TOR-3 Offshoring to Tavel SSC (+ Automation) - Tax | U2: TOR-4 Verland-Norvia New Logos - FDI | V2: TOR-5 Advisory - Geographical Expansion
A3: Name | B3: CAL Accounting System Integration & Automation | C3: CAL CoSec System Implementation, Integration & Automation | D3: Offshoring to Tavel SSC (+ Automation) - Tax | E3: Verland-Norvia New Logos - FDI | F3: Advisory - Geographical Expansion | G3: [GROUP] Revenue Retention: Reinvent CSM for Proactive Churn Management (Westmark) | H3: MER Billing System Integration & Automation | I3: Offshoring to Caldez SSC (+ Automation) - Payroll | J3: Audit Practice - Cross-Border Expansion | K3: MER-RDG New Logos - Manufacturing | L3: RDG Document Automation & OCR Rollout | M3: FJD Reconciliation Automation (RPA) | N3: Offshoring to Solva SSC (+ Automation) - Bookkeeping | O3: Advisory - Energy Sector Expansion | P3: KLP New Logos - Public Sector | Q3: FJD CoSec Workflow Automation | R3: [GROUP] Revenue Retention: Proactive Churn Management (Northpeak) | S3: BNT Tax Compliance Automation | T3: Offshoring to Pravin SSC (+ Automation) - Audit Support | U3: VSC New Logos - Financial Services | V3: Advisory - Geographical Expansion (Vandor)
A4: Reference | B4: TOR-1 | C4: TOR-2 | D4: TOR-3 | E4: TOR-4 | F4: TOR-5 | G4: TOR-6 | H4: EBR-1 | I4: EBR-2 | J4: EBR-3 | K4: EBR-4 | L4: EBR-5 | M4: NPK-1 | N4: NPK-2 | O4: NPK-3 | P4: NPK-4 | Q4: NPK-5 | R4: NPK-6 | S4: SGT-1 | T4: SGT-2 | U4: SGT-3 | V4: SGT-4
A5: Stage gate | B5: Gate 3 | C5: Gate 3 | D5: Gate 3 | E5: Gate 3 | F5: Gate 3 | G5: Gate 3 | H5: Gate 3 | I5: Gate 3 | J5: Gate 3 | K5: Gate 3 | L5: Gate 3 | M5: Gate 3 | N5: Gate 3 | O5: Gate 3 | P5: Gate 3 | Q5: Gate 3 | R5: Gate 3 | S5: Gate 3 | T5: Gate 3 | U5: Gate 3 | V5: Gate 3
A6: RAG Status | B6: green | C6: green | D6: green | E6: green | F6: green | G6: green | H6: green | I6: green | J6: green | K6: green | L6: green | M6: green | N6: green | O6: green | P6: green | Q6: green | R6: green | S6: green | T6: green | U6: green | V6: green
A7: Priority | B7: high | C7: high | D7: high | E7: high | F7: high | G7: high | H7: high | I7: high | J7: high | K7: high | L7: high | M7: high | N7: high | O7: high | P7: high | Q7: high | R7: high | S7: high | T7: high | U7: high | V7: high
A8: Initiative Type | B8: cost_reduction | C8: cost_reduction | D8: cost_reduction | E8: revenue | F8: revenue | G8: revenue | H8: cost_reduction | I8: cost_reduction | J8: revenue | K8: revenue | L8: cost_reduction | M8: cost_reduction | N8: cost_reduction | O8: revenue | P8: revenue | Q8: cost_reduction | R8: revenue | S8: cost_reduction | T8: cost_reduction | U8: revenue | V8: revenue
A9: Initiative Tag | B9: automation | C9: automation | D9: offshoring | E9: commercial | F9: commercial | G9: commercial | H9: automation | I9: offshoring | J9: commercial | K9: commercial | L9: automation | M9: automation | N9: offshoring | O9: commercial | P9: commercial | Q9: automation | R9: commercial | S9: automation | T9: offshoring | U9: commercial | V9: commercial
A10: Business Units | B10: CAL | C10: CAL | D10: CAL | E10: VER | F10: CAL | G10: GROUP, CAL, VER | H10: MER | I10: MER | J10: MER | K10: RDG | L10: RDG | M10: FJD | N10: FJD | O10: KLP | P10: KLP | Q10: FJD | R10: GROUP, FJD, KLP | S10: BNT | T10: BNT | U10: VSC | V10: VSC
A11: Workstream | B11: Westmark Region | C11: Westmark Region | D11: Westmark Region | E11: Westmark Region | F11: Westmark Region | G11: Westmark Region | H11: Eastbridge Region | I11: Eastbridge Region | J11: Eastbridge Region | K11: Eastbridge Region | L11: Eastbridge Region | M11: Northpeak Region | N11: Northpeak Region | O11: Northpeak Region | P11: Northpeak Region | Q11: Northpeak Region | R11: Northpeak Region | S11: Southgate Region | T11: Southgate Region | U11: Southgate Region | V11: Southgate Region
A12: Owner | B12: Dana Reyes | C12: Olivia Tan | D12: Marcus Lee | E12: Lukas Brandt | F12: Grace Liang | G12: Julien Moreau | H12: Priya Nadkarni | I12: Marcus Lee | J12: Niels Berg | K12: Aisha Rahman | L12: Elena Vasquez | M12: Priya Nadkarni | N12: Aisha Rahman | O12: Niels Berg | P12: Marcus Lee | Q12: Wei Chen | R12: Omar Haddad | S12: Priya Nadkarni | T12: Grace Liang | U12: Aisha Rahman | V12: Marco Bianchi
A13: Workstream Lead
A14: Workstream Sponsor
A15: Planned Completion Date | B15: 46647 | C15: 46462 | D15: 46350 | E15: 46357 | F15: 46745 | G15: 46501 | H15: 46487 | I15: 46302 | J15: 46585 | K15: 46632 | L15: 46746 | M15: 46397 | N15: 46520 | O15: 46672 | P15: 46385 | Q15: 46541 | R15: 46624 | S15: 46699 | T15: 46556 | U15: 46329 | V15: 46426
A16: Actual Completion Date
A17: Description | B17: End‑to‑end accounting process automation by using CoreLedger (or an alternative software) as an enabling platform and/ or additional tools to minimize manual steps across the full workflow - from client data submission and document ingestion to automated posting and final deliverables | C17: Accelerate Helix implementation across NA, review implementation status across other markets, and enhance with additional automation use cases within and/ or on-top of the Bluemeg | D17: Start by offshoring standard tax compliance work to the Tavel SSC via the Apex platform, then progressively expand scope as capability matures. In parallel, deploy automation and training to improve throughput and quality, with a longer-term pathway to train SSC staff to support selected advisory work under onshore oversight | E17: Systematically develop the Norvia market targeting Verland FDI clients Build a repeatable GTM engine: target segment definition, channel/partner strategy (associations, conferences, intermediaries), content and sales enablement, and an accountable coverage model with clear KPI | F17: Expand advisory beyond CAL, starting with Marenza as the near-term growth engine Develop advisory offerings, upskill talent, create repeatable go-to-market motions leveraging existing client networks, and then extend playbook to additional geographies as appropriate | G17: Work with group commercial to execute 3 main pillars in the retention program: • Voice of Customer & Proactive Client Health Scores • Build a RAG-based health score for all Protect-tier accounts (>$100k FY25 billings, 30-50 per market) across three dimensions: relationship depth, commercial engagement, and service friction. • Attach risk flags to every Protect and Watch account: no recent commercial contact, open delivery escalation, single-service client, billing friction, contact risk, renewal <90 days, scope contraction. • Track a leading indicator — commercial coverage rate (% of Protect clients with a commercial touchpoint in the last 30 days). Target: 100%. - Build toward analytics-driven early warning system; manual RAG tracker is sufficient for Months 1-6. • Retention Cadence & Governance • Appoint a named Market Retention Owner per market — portfolio-level accountability, not account-level delivery. • Install a structured operating cadence: weekly portfolio hygiene (2 hrs), monthly health review with finance pull (half-day), quarterly reset with lost-client debrief (full day). • Embed trigger-based escalation protocols: delivery escalation on Protect account (24 hrs), scope reduction (1 week), key contact change (2 weeks), billing dispute (48 hrs), account owner departure (immediate). • Group Commercial fortnightly sync across all market retention owners — standing agenda: which Protect-tier accounts are at risk this week. • Joint RACI Clarity: Group, Market, CSM & Delivery • Define and ratify group-wide RACI for client retention across Group Commercial, Market Retention Owner, CSM, Account Owner, and Delivery Lead. • Reframe CSM from reactive NPS/support function to proactive retention taskforce for top clients. • Define delivery-to-commercial escalation SLAs so that service friction reaches commercial within defined timeframes — not after a contract is already at risk. • Embed RACI accountability into commercial scorecards (aligned with Pillar 6 — Incentives). | H17: End‑to‑end accounting process automation by using CoreLedger (or an alternative software) as an enabling platform and/ or additional tools to minimize manual steps across the full workflow - from client data submission and document ingestion to automated posting and final deliverables | I17: Start by offshoring standard tax compliance work to the Tavel SSC via the Apex platform, then progressively expand scope as capability matures. In parallel, deploy automation and training to improve throughput and quality, with a longer-term pathway to train SSC staff to support selected advisory work under onshore oversight | J17: Expand advisory beyond CAL, starting with Marenza as the near-term growth engine Develop advisory offerings, upskill talent, create repeatable go-to-market motions leveraging existing client networks, and then extend playbook to additional geographies as appropriate | K17: Systematically develop the Norvia market targeting Verland FDI clients Build a repeatable GTM engine: target segment definition, channel/partner strategy (associations, conferences, intermediaries), content and sales enablement, and an accountable coverage model with clear KPI | L17: Accelerate Helix implementation across NA, review implementation status across other markets, and enhance with additional automation use cases within and/ or on-top of the Bluemeg | M17: End‑to‑end accounting process automation by using CoreLedger (or an alternative software) as an enabling platform and/ or additional tools to minimize manual steps across the full workflow - from client data submission and document ingestion to automated posting and final deliverables | N17: Start by offshoring standard tax compliance work to the Tavel SSC via the Apex platform, then progressively expand scope as capability matures. In parallel, deploy automation and training to improve throughput and quality, with a longer-term pathway to train SSC staff to support selected advisory work under onshore oversight | O17: Expand advisory beyond CAL, starting with Marenza as the near-term growth engine Develop advisory offerings, upskill talent, create repeatable go-to-market motions leveraging existing client networks, and then extend playbook to additional geographies as appropriate | P17: Systematically develop the Norvia market targeting Verland FDI clients Build a repeatable GTM engine: target segment definition, channel/partner strategy (associations, conferences, intermediaries), content and sales enablement, and an accountable coverage model with clear KPI | Q17: Accelerate Helix implementation across NA, review implementation status across other markets, and enhance with additional automation use cases within and/ or on-top of the Bluemeg | R17: Work with group commercial to execute 3 main pillars in the retention program: • Voice of Customer & Proactive Client Health Scores • Build a RAG-based health score for all Protect-tier accounts (>$100k FY25 billings, 30-50 per market) across three dimensions: relationship depth, commercial engagement, and service friction. • Attach risk flags to every Protect and Watch account: no recent commercial contact, open delivery escalation, single-service client, billing friction, contact risk, renewal <90 days, scope contraction. • Track a leading indicator — commercial coverage rate (% of Protect clients with a commercial touchpoint in the last 30 days). Target: 100%. - Build toward analytics-driven early warning system; manual RAG tracker is sufficient for Months 1-6. • Retention Cadence & Governance • Appoint a named Market Retention Owner per market — portfolio-level accountability, not account-level delivery. • Install a structured operating cadence: weekly portfolio hygiene (2 hrs), monthly health review with finance pull (half-day), quarterly reset with lost-client debrief (full day). • Embed trigger-based escalation protocols: delivery escalation on Protect account (24 hrs), scope reduction (1 week), key contact change (2 weeks), billing dispute (48 hrs), account owner departure (immediate). • Group Commercial fortnightly sync across all market retention owners — standing agenda: which Protect-tier accounts are at risk this week. • Joint RACI Clarity: Group, Market, CSM & Delivery • Define and ratify group-wide RACI for client retention across Group Commercial, Market Retention Owner, CSM, Account Owner, and Delivery Lead. • Reframe CSM from reactive NPS/support function to proactive retention taskforce for top clients. • Define delivery-to-commercial escalation SLAs so that service friction reaches commercial within defined timeframes — not after a contract is already at risk. • Embed RACI accountability into commercial scorecards (aligned with Pillar 6 — Incentives). | S17: End‑to‑end accounting process automation by using CoreLedger (or an alternative software) as an enabling platform and/ or additional tools to minimize manual steps across the full workflow - from client data submission and document ingestion to automated posting and final deliverables | T17: Start by offshoring standard tax compliance work to the Tavel SSC via the Apex platform, then progressively expand scope as capability matures. In parallel, deploy automation and training to improve throughput and quality, with a longer-term pathway to train SSC staff to support selected advisory work under onshore oversight | U17: Systematically develop the Norvia market targeting Verland FDI clients Build a repeatable GTM engine: target segment definition, channel/partner strategy (associations, conferences, intermediaries), content and sales enablement, and an accountable coverage model with clear KPI | V17: Expand advisory beyond CAL, starting with Marenza as the near-term growth engine Develop advisory offerings, upskill talent, create repeatable go-to-market motions leveraging existing client networks, and then extend playbook to additional geographies as appropriate
A18: Context & Problem | B18: CAL Accounting teams currently operate across a mix of on‑premise tools and spreadsheets (e.g., OrchardBooks, GridSheet), with limited integration into the cloud platform (CoreLedger 360) Many core bookkeeping steps remain manual and time‑consuming (e.g., invoicing, data capture / data entry, reconciliations and preparation of end outputs), driving rework, errors and inconsistent turnaround times This constrains scalability and limits the ability to absorb growth without adding headcount, while also reducing standardisation and consistency across teams | C18: There are currently 4 different systems used by different teams (COS, CSA, VP1 and VP2) VP1 has been migrated to Helix, while VP2 and other teams remain in progress, facing technical issues during implementation due to resource constraints, Helix support issues | D18: Tax compliance work is relatively standardised and can be delivered from a lower-cost shared service centre. To unlock sustainable benefits, offshoring needs to be paired with technology, workflow discipline and targeted automation The Tavel SSC (via Apex platform) provides an established offshore delivery base that can be scaled with the right training and controls | E18: We would need to invest at least USD 200,000+ for hiring a new experienced BD Director by latest Q4 2026. However, currently no budget approved to hire. | G18: Northgate's overall churn rate is ~11% (89% retention rate) in FY25, which is lagging behind its peers average of 4-8%. Retention management today is fragmented and informal, with no structured framework in place to proactively track customer voice and pre-empt customer churn in a forward looking manner. Today, churn signals sits largely with service delivery team who are neither incentivised nor structured to escalate and act on them commercially. At the same time, commercial team are also not formally incentivised to be at the driving seat in retaining clients, and typically gets involved/informed only when a contract is already at risk. Structurally, there is no formal mechanisms and motions to track customer health in near real time, structured commercial cadence with clients, named owners, and no agreed RACI between commercial, CSM, and delivery. While there is rich internal data available (e.g. billing data) that could signal churn, they are underutilised and not translated into actions to manage churn risk pre-emptively | H18: CAL Accounting teams currently operate across a mix of on‑premise tools and spreadsheets (e.g., OrchardBooks, GridSheet), with limited integration into the cloud platform (CoreLedger 360) Many core bookkeeping steps remain manual and time‑consuming (e.g., invoicing, data capture / data entry, reconciliations and preparation of end outputs), driving rework, errors and inconsistent turnaround times This constrains scalability and limits the ability to absorb growth without adding headcount, while also reducing standardisation and consistency across teams | I18: Tax compliance work is relatively standardised and can be delivered from a lower-cost shared service centre. To unlock sustainable benefits, offshoring needs to be paired with technology, workflow discipline and targeted automation The Tavel SSC (via Apex platform) provides an established offshore delivery base that can be scaled with the right training and controls | K18: We would need to invest at least USD 200,000+ for hiring a new experienced BD Director by latest Q4 2026. However, currently no budget approved to hire. | L18: There are currently 4 different systems used by different teams (COS, CSA, VP1 and VP2) VP1 has been migrated to Helix, while VP2 and other teams remain in progress, facing technical issues during implementation due to resource constraints, Helix support issues | M18: CAL Accounting teams currently operate across a mix of on‑premise tools and spreadsheets (e.g., OrchardBooks, GridSheet), with limited integration into the cloud platform (CoreLedger 360) Many core bookkeeping steps remain manual and time‑consuming (e.g., invoicing, data capture / data entry, reconciliations and preparation of end outputs), driving rework, errors and inconsistent turnaround times This constrains scalability and limits the ability to absorb growth without adding headcount, while also reducing standardisation and consistency across teams | N18: Tax compliance work is relatively standardised and can be delivered from a lower-cost shared service centre. To unlock sustainable benefits, offshoring needs to be paired with technology, workflow discipline and targeted automation The Tavel SSC (via Apex platform) provides an established offshore delivery base that can be scaled with the right training and controls | P18: We would need to invest at least USD 200,000+ for hiring a new experienced BD Director by latest Q4 2026. However, currently no budget approved to hire. | Q18: There are currently 4 different systems used by different teams (COS, CSA, VP1 and VP2) VP1 has been migrated to Helix, while VP2 and other teams remain in progress, facing technical issues during implementation due to resource constraints, Helix support issues | R18: Northgate's overall churn rate is ~11% (89% retention rate) in FY25, which is lagging behind its peers average of 4-8%. Retention management today is fragmented and informal, with no structured framework in place to proactively track customer voice and pre-empt customer churn in a forward looking manner. Today, churn signals sits largely with service delivery team who are neither incentivised nor structured to escalate and act on them commercially. At the same time, commercial team are also not formally incentivised to be at the driving seat in retaining clients, and typically gets involved/informed only when a contract is already at risk. Structurally, there is no formal mechanisms and motions to track customer health in near real time, structured commercial cadence with clients, named owners, and no agreed RACI between commercial, CSM, and delivery. While there is rich internal data available (e.g. billing data) that could signal churn, they are underutilised and not translated into actions to manage churn risk pre-emptively | S18: CAL Accounting teams currently operate across a mix of on‑premise tools and spreadsheets (e.g., OrchardBooks, GridSheet), with limited integration into the cloud platform (CoreLedger 360) Many core bookkeeping steps remain manual and time‑consuming (e.g., invoicing, data capture / data entry, reconciliations and preparation of end outputs), driving rework, errors and inconsistent turnaround times This constrains scalability and limits the ability to absorb growth without adding headcount, while also reducing standardisation and consistency across teams | T18: Tax compliance work is relatively standardised and can be delivered from a lower-cost shared service centre. To unlock sustainable benefits, offshoring needs to be paired with technology, workflow discipline and targeted automation The Tavel SSC (via Apex platform) provides an established offshore delivery base that can be scaled with the right training and controls | U18: We would need to invest at least USD 200,000+ for hiring a new experienced BD Director by latest Q4 2026. However, currently no budget approved to hire.
A19: Value Logic / Assumptions | B19: 25–30% productivity uplift through system integration and targeted automation Gross margin improvement driven by revenue growth with fixed cost base, enabled by productivity gains | C19: 15–20% productivity uplift through system integration and targeted automation Gross margin improvement driven by revenue growth with fixed cost base, enabled by productivity gains | D19: 15–20% cost reduction on existing Tax Advisory team | E19: Additional FTEs to be invested with ramping up ACV targets | F19: ACV & Revenue uplift from new logo acquisition based on market share target assumptions | G19: • In FY25, VER's retention rate is 92% while CAL retained 89% (vs Northgate group average of ~89% retention) • External benchmark suggests best-in-class churn rates of 4-8% (implying retention of 92-96%.) • Overall target retention rate is 94–95%, representing a 5% uplift from group average retention rate • To achieve that, VER requires a ~1-2% improvement. CAL requires a ~5-6% improvement. | H19: 25–30% productivity uplift through system integration and targeted automation Gross margin improvement driven by revenue growth with fixed cost base, enabled by productivity gains | I19: 15–20% cost reduction on existing Tax Advisory team | J19: ACV & Revenue uplift from new logo acquisition based on market share target assumptions | K19: Additional FTEs to be invested with ramping up ACV targets | L19: 15–20% productivity uplift through system integration and targeted automation Gross margin improvement driven by revenue growth with fixed cost base, enabled by productivity gains | M19: 25–30% productivity uplift through system integration and targeted automation Gross margin improvement driven by revenue growth with fixed cost base, enabled by productivity gains | N19: 15–20% cost reduction on existing Tax Advisory team | O19: ACV & Revenue uplift from new logo acquisition based on market share target assumptions | P19: Additional FTEs to be invested with ramping up ACV targets | Q19: 15–20% productivity uplift through system integration and targeted automation Gross margin improvement driven by revenue growth with fixed cost base, enabled by productivity gains | R19: • In FY25, VER's retention rate is 92% while CAL retained 89% (vs Northgate group average of ~89% retention) • External benchmark suggests best-in-class churn rates of 4-8% (implying retention of 92-96%.) • Overall target retention rate is 94–95%, representing a 5% uplift from group average retention rate • To achieve that, VER requires a ~1-2% improvement. CAL requires a ~5-6% improvement. | S19: 25–30% productivity uplift through system integration and targeted automation Gross margin improvement driven by revenue growth with fixed cost base, enabled by productivity gains | T19: 15–20% cost reduction on existing Tax Advisory team | U19: Additional FTEs to be invested with ramping up ACV targets | V19: ACV & Revenue uplift from new logo acquisition based on market share target assumptions
A20: Initiative Value (Base, USD m) | B20: {=INDEX('Financial Summary'!$D:$J,MATCH(B$4,'Financial Summary'!$A:$A,0)+10,MATCH('Initiative Summary'!$L$3,'Financial Summary'!$D$2:$J$2,0))} -> 0.56 | C20: {=INDEX('Financial Summary'!$D:$J,MATCH(C$4,'Financial Summary'!$A:$A,0)+10,MATCH('Initiative Summary'!$L$3,'Financial Summary'!$D$2:$J$2,0))} -> 0.82 | D20: {=INDEX('Financial Summary'!$D:$J,MATCH(D$4,'Financial Summary'!$A:$A,0)+10,MATCH('Initiative Summary'!$L$3,'Financial Summary'!$D$2:$J$2,0))} -> 1.76 | E20: {=INDEX('Financial Summary'!$D:$J,MATCH(E$4,'Financial Summary'!$A:$A,0)+10,MATCH('Initiative Summary'!$L$3,'Financial Summary'!$D$2:$J$2,0))} -> 0.08 | F20: {=INDEX('Financial Summary'!$D:$J,MATCH(F$4,'Financial Summary'!$A:$A,0)+10,MATCH('Initiative Summary'!$L$3,'Financial Summary'!$D$2:$J$2,0))} -> 1.42 | G20: {=INDEX('Financial Summary'!$D:$J,MATCH(G$4,'Financial Summary'!$A:$A,0)+10,MATCH('Initiative Summary'!$L$3,'Financial Summary'!$D$2:$J$2,0))} -> 0.24 | H20: {=INDEX('Financial Summary'!$D:$J,MATCH(H$4,'Financial Summary'!$A:$A,0)+10,MATCH('Initiative Summary'!$L$3,'Financial Summary'!$D$2:$J$2,0))} -> 0.616 | I20: {=INDEX('Financial Summary'!$D:$J,MATCH(I$4,'Financial Summary'!$A:$A,0)+10,MATCH('Initiative Summary'!$L$3,'Financial Summary'!$D$2:$J$2,0))} -> 1.584 | ... V20: {=INDEX('Financial Summary'!$D:$J,MATCH(V$4,'Financial Summary'!$A:$A,0)+10,MATCH('Initiative Summary'!$L$3,'Financial Summary'!$D$2:$J$2,0))} -> 1.349
A21: Initiative Value (High, USD m) | B21: {=INDEX('Financial Summary'!$D:$J,MATCH(B$4,'Financial Summary'!$A:$A,0)+11,MATCH('Initiative Summary'!$L$3,'Financial Summary'!$D$2:$J$2,0))} -> 0.68 | C21: {=INDEX('Financial Summary'!$D:$J,MATCH(C$4,'Financial Summary'!$A:$A,0)+11,MATCH('Initiative Summary'!$L$3,'Financial Summary'!$D$2:$J$2,0))} -> 1.14 | D21: {=INDEX('Financial Summary'!$D:$J,MATCH(D$4,'Financial Summary'!$A:$A,0)+11,MATCH('Initiative Summary'!$L$3,'Financial Summary'!$D$2:$J$2,0))} -> 2.38 | E21: {=INDEX('Financial Summary'!$D:$J,MATCH(E$4,'Financial Summary'!$A:$A,0)+11,MATCH('Initiative Summary'!$L$3,'Financial Summary'!$D$2:$J$2,0))} -> 0.38 | F21: {=INDEX('Financial Summary'!$D:$J,MATCH(F$4,'Financial Summary'!$A:$A,0)+11,MATCH('Initiative Summary'!$L$3,'Financial Summary'!$D$2:$J$2,0))} -> 1.92 | G21: {=INDEX('Financial Summary'!$D:$J,MATCH(G$4,'Financial Summary'!$A:$A,0)+11,MATCH('Initiative Summary'!$L$3,'Financial Summary'!$D$2:$J$2,0))} -> 0.5 | H21: {=INDEX('Financial Summary'!$D:$J,MATCH(H$4,'Financial Summary'!$A:$A,0)+11,MATCH('Initiative Summary'!$L$3,'Financial Summary'!$D$2:$J$2,0))} -> 0.748 | I21: {=INDEX('Financial Summary'!$D:$J,MATCH(I$4,'Financial Summary'!$A:$A,0)+11,MATCH('Initiative Summary'!$L$3,'Financial Summary'!$D$2:$J$2,0))} -> 2.142 | ... V21: {=INDEX('Financial Summary'!$D:$J,MATCH(V$4,'Financial Summary'!$A:$A,0)+11,MATCH('Initiative Summary'!$L$3,'Financial Summary'!$D$2:$J$2,0))} -> 1.824

Sheet Financial Summary
A1: Financial Summary — Annual (USD m, plan basis) | K1: Baseline
A2: Reference | B2: Initiative | C2: Metric | D2: FY26 | E2: FY27 | F2: FY28 | G2: FY29 | H2: FY30 | I2: FY31 | J2: All Years | K2: FY25
A3: TOR-1 | B3: CAL Accounting System Integration & Automation | C3: Revenue Plan — Base (USD m) | D3: =SUMIFS(Benefits!$S:$S,Benefits!$A:$A,$A$3,Benefits!$E:$E,"Revenue",Benefits!$F:$F,"USD",Benefits!$D:$D,"Plan Base") -> 0 | E3: =SUMIFS(Benefits!$T:$T,Benefits!$A:$A,$A$3,Benefits!$E:$E,"Revenue",Benefits!$F:$F,"USD",Benefits!$D:$D,"Plan Base") -> 0 | F3: =SUMIFS(Benefits!$U:$U,Benefits!$A:$A,$A$3,Benefits!$E:$E,"Revenue",Benefits!$F:$F,"USD",Benefits!$D:$D,"Plan Base") -> 0 | G3: =SUMIFS(Benefits!$V:$V,Benefits!$A:$A,$A$3,Benefits!$E:$E,"Revenue",Benefits!$F:$F,"USD",Benefits!$D:$D,"Plan Base") -> 0 | H3: =SUMIFS(Benefits!$W:$W,Benefits!$A:$A,$A$3,Benefits!$E:$E,"Revenue",Benefits!$F:$F,"USD",Benefits!$D:$D,"Plan Base") -> 0 | I3: =H3 -> 0 | J3: =SUM(D3:I3) -> 0 | K3: 0
C4: Revenue Plan — High (USD m) | D4: =SUMIFS(Benefits!$S:$S,Benefits!$A:$A,$A$3,Benefits!$E:$E,"Revenue",Benefits!$F:$F,"USD",Benefits!$D:$D,"Plan High") -> 0 | E4: =SUMIFS(Benefits!$T:$T,Benefits!$A:$A,$A$3,Benefits!$E:$E,"Revenue",Benefits!$F:$F,"USD",Benefits!$D:$D,"Plan High") -> 0 | F4: =SUMIFS(Benefits!$U:$U,Benefits!$A:$A,$A$3,Benefits!$E:$E,"Revenue",Benefits!$F:$F,"USD",Benefits!$D:$D,"Plan High") -> 0 | G4: =SUMIFS(Benefits!$V:$V,Benefits!$A:$A,$A$3,Benefits!$E:$E,"Revenue",Benefits!$F:$F,"USD",Benefits!$D:$D,"Plan High") -> 0 | H4: =SUMIFS(Benefits!$W:$W,Benefits!$A:$A,$A$3,Benefits!$E:$E,"Revenue",Benefits!$F:$F,"USD",Benefits!$D:$D,"Plan High") -> 0 | I4: =H4 -> 0 | J4: =SUM(D4:I4) -> 0 | K4: 0
C5: Revenue Actual (USD m) | D5: =SUMIFS(Benefits!$S:$S,Benefits!$A:$A,$A$3,Benefits!$E:$E,"Revenue",Benefits!$F:$F,"USD",Benefits!$D:$D,"Actual") -> 0 | E5: =SUMIFS(Benefits!$T:$T,Benefits!$A:$A,$A$3,Benefits!$E:$E,"Revenue",Benefits!$F:$F,"USD",Benefits!$D:$D,"Actual") -> 0 | F5: =SUMIFS(Benefits!$U:$U,Benefits!$A:$A,$A$3,Benefits!$E:$E,"Revenue",Benefits!$F:$F,"USD",Benefits!$D:$D,"Actual") -> 0 | G5: =SUMIFS(Benefits!$V:$V,Benefits!$A:$A,$A$3,Benefits!$E:$E,"Revenue",Benefits!$F:$F,"USD",Benefits!$D:$D,"Actual") -> 0 | H5: =SUMIFS(Benefits!$W:$W,Benefits!$A:$A,$A$3,Benefits!$E:$E,"Revenue",Benefits!$F:$F,"USD",Benefits!$D:$D,"Actual") -> 0 | I5: =H5 -> 0 | J5: =SUM(D5:I5) -> 0 | K5: 0
C6: Gross Margin Plan — Base (USD m) | D6: =SUMIFS(Benefits!$S:$S,Benefits!$A:$A,$A$3,Benefits!$E:$E,"Gross Margin",Benefits!$F:$F,"USD",Benefits!$D:$D,"Plan Base") -> 0 | E6: =SUMIFS(Benefits!$T:$T,Benefits!$A:$A,$A$3,Benefits!$E:$E,"Gross Margin",Benefits!$F:$F,"USD",Benefits!$D:$D,"Plan Base") -> 0.42 | F6: =SUMIFS(Benefits!$U:$U,Benefits!$A:$A,$A$3,Benefits!$E:$E,"Gross Margin",Benefits!$F:$F,"USD",Benefits!$D:$D,"Plan Base") -> 0.62 | G6: =SUMIFS(Benefits!$V:$V,Benefits!$A:$A,$A$3,Benefits!$E:$E,"Gross Margin",Benefits!$F:$F,"USD",Benefits!$D:$D,"Plan Base") -> 0.62 | H6: =SUMIFS(Benefits!$W:$W,Benefits!$A:$A,$A$3,Benefits!$E:$E,"Gross Margin",Benefits!$F:$F,"USD",Benefits!$D:$D,"Plan Base") -> 0.62 | I6: =H6 -> 0.62 | J6: =SUM(D6:I6) -> 2.9 | K6: 2.192
C7: Gross Margin Plan — High (USD m) | D7: =SUMIFS(Benefits!$S:$S,Benefits!$A:$A,$A$3,Benefits!$E:$E,"Gross Margin",Benefits!$F:$F,"USD",Benefits!$D:$D,"Plan High") -> 0 | E7: =SUMIFS(Benefits!$T:$T,Benefits!$A:$A,$A$3,Benefits!$E:$E,"Gross Margin",Benefits!$F:$F,"USD",Benefits!$D:$D,"Plan High") -> 0.52 | F7: =SUMIFS(Benefits!$U:$U,Benefits!$A:$A,$A$3,Benefits!$E:$E,"Gross Margin",Benefits!$F:$F,"USD",Benefits!$D:$D,"Plan High") -> 0.74 | G7: =SUMIFS(Benefits!$V:$V,Benefits!$A:$A,$A$3,Benefits!$E:$E,"Gross Margin",Benefits!$F:$F,"USD",Benefits!$D:$D,"Plan High") -> 0.74 | H7: =SUMIFS(Benefits!$W:$W,Benefits!$A:$A,$A$3,Benefits!$E:$E,"Gross Margin",Benefits!$F:$F,"USD",Benefits!$D:$D,"Plan High") -> 0.74 | I7: =H7 -> 0.74 | J7: =SUM(D7:I7) -> 3.48
C8: Gross Margin Actual (USD m) | D8: =SUMIFS(Benefits!$S:$S,Benefits!$A:$A,$A$3,Benefits!$E:$E,"Gross Margin",Benefits!$F:$F,"USD",Benefits!$D:$D,"Actual") -> 0 | E8: =SUMIFS(Benefits!$T:$T,Benefits!$A:$A,$A$3,Benefits!$E:$E,"Gross Margin",Benefits!$F:$F,"USD",Benefits!$D:$D,"Actual") -> 0 | F8: =SUMIFS(Benefits!$U:$U,Benefits!$A:$A,$A$3,Benefits!$E:$E,"Gross Margin",Benefits!$F:$F,"USD",Benefits!$D:$D,"Actual") -> 0 | G8: =SUMIFS(Benefits!$V:$V,Benefits!$A:$A,$A$3,Benefits!$E:$E,"Gross Margin",Benefits!$F:$F,"USD",Benefits!$D:$D,"Actual") -> 0 | H8: =SUMIFS(Benefits!$W:$W,Benefits!$A:$A,$A$3,Benefits!$E:$E,"Gross Margin",Benefits!$F:$F,"USD",Benefits!$D:$D,"Actual") -> 0 | I8: =H8 -> 0 | J8: =SUM(D8:I8) -> 0
C9: COSTS
C10: Cost Plan (USD m) | D10: =SUMIFS(Costs!$AB:$AB,Costs!$A:$A,$A$3,Costs!$D:$D,"Plan") -> 0 | E10: =SUMIFS(Costs!$AC:$AC,Costs!$A:$A,$A$3,Costs!$D:$D,"Plan") -> 0.06 | F10: =SUMIFS(Costs!$AD:$AD,Costs!$A:$A,$A$3,Costs!$D:$D,"Plan") -> 0.06 | G10: =SUMIFS(Costs!$AE:$AE,Costs!$A:$A,$A$3,Costs!$D:$D,"Plan") -> 0.06 | H10: =SUMIFS(Costs!$AF:$AF,Costs!$A:$A,$A$3,Costs!$D:$D,"Plan") -> 0.06 | I10: =H10 -> 0.06 | J10: =SUM(D10:I10) -> 0.3 | K10: 0.295
C11: Cost Actual (USD m) | D11: =SUMIFS(Costs!$AB:$AB,Costs!$A:$A,$A$3,Costs!$D:$D,"Actual") -> 0 | E11: =SUMIFS(Costs!$AC:$AC,Costs!$A:$A,$A$3,Costs!$D:$D,"Actual") -> 0 | F11: =SUMIFS(Costs!$AD:$AD,Costs!$A:$A,$A$3,Costs!$D:$D,"Actual") -> 0 | G11: =SUMIFS(Costs!$AE:$AE,Costs!$A:$A,$A$3,Costs!$D:$D,"Actual") -> 0 | H11: =SUMIFS(Costs!$AF:$AF,Costs!$A:$A,$A$3,Costs!$D:$D,"Actual") -> 0 | I11: =H11 -> 0 | J11: =SUM(D11:I11) -> 0
C12: NET VALUE
C13: Net Value — Plan Base (USD m) | D13: =D6-D10 -> 0 | E13: =E6-E10 -> 0.36 | F13: =F6-F10 -> 0.56 | G13: =G6-G10 -> 0.56 | H13: =H6-H10 -> 0.56 | I13: =I6-I10 -> 0.56 | J13: =J6-J10 -> 2.6 | K13: =K6-K10 -> 1.897
C14: Net Value — Plan High (USD m) | D14: =D7-D10 -> 0 | E14: =E7-E10 -> 0.46 | F14: =F7-F10 -> 0.68 | G14: =G7-G10 -> 0.68 | H14: =H7-H10 -> 0.68 | I14: =I7-I10 -> 0.68 | J14: =J7-J10 -> 3.18
C15: Net Value — Actual (USD m) | D15: =D8-D11 -> 0 | E15: =E8-E11 -> 0 | F15: =F8-F11 -> 0 | G15: =G8-G11 -> 0 | H15: =H8-H11 -> 0 | I15: =I8-I11 -> 0 | J15: =J8-J11 -> 0
C16: ROI (Actual, %) | D16: =IFERROR(D15/D11,0) -> 0 | E16: =IFERROR(E15/E11,0) -> 0 | F16: =IFERROR(F15/F11,0) -> 0 | G16: =IFERROR(G15/G11,0) -> 0 | H16: =IFERROR(H15/H11,0) -> 0 | I16: =IFERROR(I15/I11,0) -> 0 | J16: =IFERROR(J15/J11,0) -> 0 | K16: =IFERROR(K15/K11,0) -> 0
A18: TOR-2 | B18: CAL CoSec System Implementation, Integration & Automation | C18: Revenue Plan — Base (USD m) | D18: =SUMIFS(Benefits!$S:$S,Benefits!$A:$A,$A$18,Benefits!$E:$E,"Revenue",Benefits!$F:$F,"USD",Benefits!$D:$D,"Plan Base") -> 0 | E18: =SUMIFS(Benefits!$T:$T,Benefits!$A:$A,$A$18,Benefits!$E:$E,"Revenue",Benefits!$F:$F,"USD",Benefits!$D:$D,"Plan Base") -> 0 | F18: =SUMIFS(Benefits!$U:$U,Benefits!$A:$A,$A$18,Benefits!$E:$E,"Revenue",Benefits!$F:$F,"USD",Benefits!$D:$D,"Plan Base") -> 0 | G18: =SUMIFS(Benefits!$V:$V,Benefits!$A:$A,$A$18,Benefits!$E:$E,"Revenue",Benefits!$F:$F,"USD",Benefits!$D:$D,"Plan Base") -> 0 | H18: =SUMIFS(Benefits!$W:$W,Benefits!$A:$A,$A$18,Benefits!$E:$E,"Revenue",Benefits!$F:$F,"USD",Benefits!$D:$D,"Plan Base") -> 0 | I18: =H18 -> 0 | J18: =SUM(D18:I18) -> 0 | K18: 0
C19: Revenue Plan — High (USD m) | D19: =SUMIFS(Benefits!$S:$S,Benefits!$A:$A,$A$18,Benefits!$E:$E,"Revenue",Benefits!$F:$F,"USD",Benefits!$D:$D,"Plan High") -> 0 | E19: =SUMIFS(Benefits!$T:$T,Benefits!$A:$A,$A$18,Benefits!$E:$E,"Revenue",Benefits!$F:$F,"USD",Benefits!$D:$D,"Plan High") -> 0 | F19: =SUMIFS(Benefits!$U:$U,Benefits!$A:$A,$A$18,Benefits!$E:$E,"Revenue",Benefits!$F:$F,"USD",Benefits!$D:$D,"Plan High") -> 0 | G19: =SUMIFS(Benefits!$V:$V,Benefits!$A:$A,$A$18,Benefits!$E:$E,"Revenue",Benefits!$F:$F,"USD",Benefits!$D:$D,"Plan High") -> 0 | H19: =SUMIFS(Benefits!$W:$W,Benefits!$A:$A,$A$18,Benefits!$E:$E,"Revenue",Benefits!$F:$F,"USD",Benefits!$D:$D,"Plan High") -> 0 | I19: =H19 -> 0 | J19: =SUM(D19:I19) -> 0 | K19: 0
C20: Revenue Actual (USD m) | D20: =SUMIFS(Benefits!$S:$S,Benefits!$A:$A,$A$18,Benefits!$E:$E,"Revenue",Benefits!$F:$F,"USD",Benefits!$D:$D,"Actual") -> 0 | E20: =SUMIFS(Benefits!$T:$T,Benefits!$A:$A,$A$18,Benefits!$E:$E,"Revenue",Benefits!$F:$F,"USD",Benefits!$D:$D,"Actual") -> 0 | F20: =SUMIFS(Benefits!$U:$U,Benefits!$A:$A,$A$18,Benefits!$E:$E,"Revenue",Benefits!$F:$F,"USD",Benefits!$D:$D,"Actual") -> 0 | G20: =SUMIFS(Benefits!$V:$V,Benefits!$A:$A,$A$18,Benefits!$E:$E,"Revenue",Benefits!$F:$F,"USD",Benefits!$D:$D,"Actual") -> 0 | H20: =SUMIFS(Benefits!$W:$W,Benefits!$A:$A,$A$18,Benefits!$E:$E,"Revenue",Benefits!$F:$F,"USD",Benefits!$D:$D,"Actual") -> 0 | I20: =H20 -> 0 | J20: =SUM(D20:I20) -> 0 | K20: 0
C21: Gross Margin Plan — Base (USD m) | D21: =SUMIFS(Benefits!$S:$S,Benefits!$A:$A,$A$18,Benefits!$E:$E,"Gross Margin",Benefits!$F:$F,"USD",Benefits!$D:$D,"Plan Base") -> 0 | E21: =SUMIFS(Benefits!$T:$T,Benefits!$A:$A,$A$18,Benefits!$E:$E,"Gross Margin",Benefits!$F:$F,"USD",Benefits!$D:$D,"Plan Base") -> 0.62 | F21: =SUMIFS(Benefits!$U:$U,Benefits!$A:$A,$A$18,Benefits!$E:$E,"Gross Margin",Benefits!$F:$F,"USD",Benefits!$D:$D,"Plan Base") -> 0.92 | G21: =SUMIFS(Benefits!$V:$V,Benefits!$A:$A,$A$18,Benefits!$E:$E,"Gross Margin",Benefits!$F:$F,"USD",Benefits!$D:$D,"Plan Base") -> 0.92 | H21: =SUMIFS(Benefits!$W:$W,Benefits!$A:$A,$A$18,Benefits!$E:$E,"Gross Margin",Benefits!$F:$F,"USD",Benefits!$D:$D,"Plan Base") -> 0.92 | I21: =H21 -> 0.92 | J21: =SUM(D21:I21) -> 4.3 | K21: 3.1
C22: Gross Margin Plan — High (USD m) | D22: =SUMIFS(Benefits!$S:$S,Benefits!$A:$A,$A$18,Benefits!$E:$E,"Gross Margin",Benefits!$F:$F,"USD",Benefits!$D:$D,"Plan High") -> 0 | E22: =SUMIFS(Benefits!$T:$T,Benefits!$A:$A,$A$18,Benefits!$E:$E,"Gross Margin",Benefits!$F:$F,"USD",Benefits!$D:$D,"Plan High") -> 0.84 | F22: =SUMIFS(Benefits!$U:$U,Benefits!$A:$A,$A$18,Benefits!$E:$E,"Gross Margin",Benefits!$F:$F,"USD",Benefits!$D:$D,"Plan High") -> 1.24 | G22: =SUMIFS(Benefits!$V:$V,Benefits!$A:$A,$A$18,Benefits!$E:$E,"Gross Margin",Benefits!$F:$F,"USD",Benefits!$D:$D,"Plan High") -> 1.24 | H22: =SUMIFS(Benefits!$W:$W,Benefits!$A:$A,$A$18,Benefits!$E:$E,"Gross Margin",Benefits!$F:$F,"USD",Benefits!$D:$D,"Plan High") -> 1.24 | I22: =H22 -> 1.24 | J22: =SUM(D22:I22) -> 5.8
C23: Gross Margin Actual (USD m) | D23: =SUMIFS(Benefits!$S:$S,Benefits!$A:$A,$A$18,Benefits!$E:$E,"Gross Margin",Benefits!$F:$F,"USD",Benefits!$D:$D,"Actual") -> 0 | E23: =SUMIFS(Benefits!$T:$T,Benefits!$A:$A,$A$18,Benefits!$E:$E,"Gross Margin",Benefits!$F:$F,"USD",Benefits!$D:$D,"Actual") -> 0 | F23: =SUMIFS(Benefits!$U:$U,Benefits!$A:$A,$A$18,Benefits!$E:$E,"Gross Margin",Benefits!$F:$F,"USD",Benefits!$D:$D,"Actual") -> 0 | G23: =SUMIFS(Benefits!$V:$V,Benefits!$A:$A,$A$18,Benefits!$E:$E,"Gross Margin",Benefits!$F:$F,"USD",Benefits!$D:$D,"Actual") -> 0 | H23: =SUMIFS(Benefits!$W:$W,Benefits!$A:$A,$A$18,Benefits!$E:$E,"Gross Margin",Benefits!$F:$F,"USD",Benefits!$D:$D,"Actual") -> 0 | I23: =H23 -> 0 | J23: =SUM(D23:I23) -> 0
C24: COSTS
C25: Cost Plan (USD m) | D25: =SUMIFS(Costs!$AB:$AB,Costs!$A:$A,$A$18,Costs!$D:$D,"Plan") -> 0 | E25: =SUMIFS(Costs!$AC:$AC,Costs!$A:$A,$A$18,Costs!$D:$D,"Plan") -> 0.1 | F25: =SUMIFS(Costs!$AD:$AD,Costs!$A:$A,$A$18,Costs!$D:$D,"Plan") -> 0.1 | G25: =SUMIFS(Costs!$AE:$AE,Costs!$A:$A,$A$18,Costs!$D:$D,"Plan") -> 0.1 | H25: =SUMIFS(Costs!$AF:$AF,Costs!$A:$A,$A$18,Costs!$D:$D,"Plan") -> 0.1 | I25: =H25 -> 0.1 | J25: =SUM(D25:I25) -> 0.5 | K25: 0.322
C26: Cost Actual (USD m) | D26: =SUMIFS(Costs!$AB:$AB,Costs!$A:$A,$A$18,Costs!$D:$D,"Actual") -> 0 | E26: =SUMIFS(Costs!$AC:$AC,Costs!$A:$A,$A$18,Costs!$D:$D,"Actual") -> 0 | F26: =SUMIFS(Costs!$AD:$AD,Costs!$A:$A,$A$18,Costs!$D:$D,"Actual") -> 0 | G26: =SUMIFS(Costs!$AE:$AE,Costs!$A:$A,$A$18,Costs!$D:$D,"Actual") -> 0 | H26: =SUMIFS(Costs!$AF:$AF,Costs!$A:$A,$A$18,Costs!$D:$D,"Actual") -> 0 | I26: =H26 -> 0 | J26: =SUM(D26:I26) -> 0
C27: NET VALUE
C28: Net Value — Plan Base (USD m) | D28: =D21-D25 -> 0 | E28: =E21-E25 -> 0.52 | F28: =F21-F25 -> 0.82 | G28: =G21-G25 -> 0.82 | H28: =H21-H25 -> 0.82 | I28: =I21-I25 -> 0.82 | J28: =J21-J25 -> 3.8 | K28: =K21-K25 -> 2.778
C29: Net Value — Plan High (USD m) | D29: =D22-D25 -> 0 | E29: =E22-E25 -> 0.74 | F29: =F22-F25 -> 1.14 | G29: =G22-G25 -> 1.14 | H29: =H22-H25 -> 1.14 | I29: =I22-I25 -> 1.14 | J29: =J22-J25 -> 5.3
C30: Net Value — Actual (USD m) | D30: =D23-D26 -> 0 | E30: =E23-E26 -> 0 | F30: =F23-F26 -> 0 | G30: =G23-G26 -> 0 | H30: =H23-H26 -> 0 | I30: =I23-I26 -> 0 | J30: =J23-J26 -> 0
C31: ROI (Actual, %) | D31: =IFERROR(D30/D26,0) -> 0 | E31: =IFERROR(E30/E26,0) -> 0 | F31: =IFERROR(F30/F26,0) -> 0 | G31: =IFERROR(G30/G26,0) -> 0 | H31: =IFERROR(H30/H26,0) -> 0 | I31: =IFERROR(I30/I26,0) -> 0 | J31: =IFERROR(J30/J26,0) -> 0 | K31: =IFERROR(K30/K26,0) -> 0
A33: TOR-3 | B33: Offshoring to Tavel SSC (+ Automation) - Tax | C33: Revenue Plan — Base (USD m) | D33: =SUMIFS(Benefits!$S:$S,Benefits!$A:$A,$A$33,Benefits!$E:$E,"Revenue",Benefits!$F:$F,"USD",Benefits!$D:$D,"Plan Base") -> 0 | E33: =SUMIFS(Benefits!$T:$T,Benefits!$A:$A,$A$33,Benefits!$E:$E,"Revenue",Benefits!$F:$F,"USD",Benefits!$D:$D,"Plan Base") -> 0 | F33: =SUMIFS(Benefits!$U:$U,Benefits!$A:$A,$A$33,Benefits!$E:$E,"Revenue",Benefits!$F:$F,"USD",Benefits!$D:$D,"Plan Base") -> 0 | G33: =SUMIFS(Benefits!$V:$V,Benefits!$A:$A,$A$33,Benefits!$E:$E,"Revenue",Benefits!$F:$F,"USD",Benefits!$D:$D,"Plan Base") -> 0 | H33: =SUMIFS(Benefits!$W:$W,Benefits!$A:$A,$A$33,Benefits!$E:$E,"Revenue",Benefits!$F:$F,"USD",Benefits!$D:$D,"Plan Base") -> 0 | I33: =H33 -> 0 | J33: =SUM(D33:I33) -> 0 | K33: 0
C34: Revenue Plan — High (USD m) | D34: =SUMIFS(Benefits!$S:$S,Benefits!$A:$A,$A$33,Benefits!$E:$E,"Revenue",Benefits!$F:$F,"USD",Benefits!$D:$D,"Plan High") -> 0 | E34: =SUMIFS(Benefits!$T:$T,Benefits!$A:$A,$A$33,Benefits!$E:$E,"Revenue",Benefits!$F:$F,"USD",Benefits!$D:$D,"Plan High") -> 0 | F34: =SUMIFS(Benefits!$U:$U,Benefits!$A:$A,$A$33,Benefits!$E:$E,"Revenue",Benefits!$F:$F,"USD",Benefits!$D:$D,"Plan High") -> 0 | G34: =SUMIFS(Benefits!$V:$V,Benefits!$A:$A,$A$33,Benefits!$E:$E,"Revenue",Benefits!$F:$F,"USD",Benefits!$D:$D,"Plan High") -> 0 | H34: =SUMIFS(Benefits!$W:$W,Benefits!$A:$A,$A$33,Benefits!$E:$E,"Revenue",Benefits!$F:$F,"USD",Benefits!$D:$D,"Plan High") -> 0 | I34: =H34 -> 0 | J34: =SUM(D34:I34) -> 0 | K34: 0
C35: Revenue Actual (USD m) | D35: =SUMIFS(Benefits!$S:$S,Benefits!$A:$A,$A$33,Benefits!$E:$E,"Revenue",Benefits!$F:$F,"USD",Benefits!$D:$D,"Actual") -> 0 | E35: =SUMIFS(Benefits!$T:$T,Benefits!$A:$A,$A$33,Benefits!$E:$E,"Revenue",Benefits!$F:$F,"USD",Benefits!$D:$D,"Actual") -> 0 | F35: =SUMIFS(Benefits!$U:$U,Benefits!$A:$A,$A$33,Benefits!$E:$E,"Revenue",Benefits!$F:$F,"USD",Benefits!$D:$D,"Actual") -> 0 | G35: =SUMIFS(Benefits!$V:$V,Benefits!$A:$A,$A$33,Benefits!$E:$E,"Revenue",Benefits!$F:$F,"USD",Benefits!$D:$D,"Actual") -> 0 | H35: =SUMIFS(Benefits!$W:$W,Benefits!$A:$A,$A$33,Benefits!$E:$E,"Revenue",Benefits!$F:$F,"USD",Benefits!$D:$D,"Actual") -> 0 | I35: =H35 -> 0 | J35: =SUM(D35:I35) -> 0 | K35: 0
C36: Gross Margin Plan — Base (USD m) | D36: =SUMIFS(Benefits!$S:$S,Benefits!$A:$A,$A$33,Benefits!$E:$E,"Gross Margin",Benefits!$F:$F,"USD",Benefits!$D:$D,"Plan Base") -> 1.24 | E36: =SUMIFS(Benefits!$T:$T,Benefits!$A:$A,$A$33,Benefits!$E:$E,"Gross Margin",Benefits!$F:$F,"USD",Benefits!$D:$D,"Plan Base") -> 1.86 | F36: =SUMIFS(Benefits!$U:$U,Benefits!$A:$A,$A$33,Benefits!$E:$E,"Gross Margin",Benefits!$F:$F,"USD",Benefits!$D:$D,"Plan Base") -> 1.86 | G36: =SUMIFS(Benefits!$V:$V,Benefits!$A:$A,$A$33,Benefits!$E:$E,"Gross Margin",Benefits!$F:$F,"USD",Benefits!$D:$D,"Plan Base") -> 1.86 | H36: =SUMIFS(Benefits!$W:$W,Benefits!$A:$A,$A$33,Benefits!$E:$E,"Gross Margin",Benefits!$F:$F,"USD",Benefits!$D:$D,"Plan Base") -> 1.86 | I36: =H36 -> 1.86 | J36: =SUM(D36:I36) -> 10.54 | K36: 8.652
C37: Gross Margin Plan — High (USD m) | D37: =SUMIFS(Benefits!$S:$S,Benefits!$A:$A,$A$33,Benefits!$E:$E,"Gross Margin",Benefits!$F:$F,"USD",Benefits!$D:$D,"Plan High") -> 1.66 | E37: =SUMIFS(Benefits!$T:$T,Benefits!$A:$A,$A$33,Benefits!$E:$E,"Gross Margin",Benefits!$F:$F,"USD",Benefits!$D:$D,"Plan High") -> 2.48 | F37: =SUMIFS(Benefits!$U:$U,Benefits!$A:$A,$A$33,Benefits!$E:$E,"Gross Margin",Benefits!$F:$F,"USD",Benefits!$D:$D,"Plan High") -> 2.48 | G37: =SUMIFS(Benefits!$V:$V,Benefits!$A:$A,$A$33,Benefits!$E:$E,"Gross Margin",Benefits!$F:$F,"USD",Benefits!$D:$D,"Plan High") -> 2.48 | H37: =SUMIFS(Benefits!$W:$W,Benefits!$A:$A,$A$33,Benefits!$E:$E,"Gross Margin",Benefits!$F:$F,"USD",Benefits!$D:$D,"Plan High") -> 2.48 | I37: =H37 -> 2.48 | J37: =SUM(D37:I37) -> 14.06
C38: Gross Margin Actual (USD m) | D38: =SUMIFS(Benefits!$S:$S,Benefits!$A:$A,$A$33,Benefits!$E:$E,"Gross Margin",Benefits!$F:$F,"USD",Benefits!$D:$D,"Actual") -> 0 | E38: =SUMIFS(Benefits!$T:$T,Benefits!$A:$A,$A$33,Benefits!$E:$E,"Gross Margin",Benefits!$F:$F,"USD",Benefits!$D:$D,"Actual") -> 0 | F38: =SUMIFS(Benefits!$U:$U,Benefits!$A:$A,$A$33,Benefits!$E:$E,"Gross Margin",Benefits!$F:$F,"USD",Benefits!$D:$D,"Actual") -> 0 | G38: =SUMIFS(Benefits!$V:$V,Benefits!$A:$A,$A$33,Benefits!$E:$E,"Gross Margin",Benefits!$F:$F,"USD",Benefits!$D:$D,"Actual") -> 0 | H38: =SUMIFS(Benefits!$W:$W,Benefits!$A:$A,$A$33,Benefits!$E:$E,"Gross Margin",Benefits!$F:$F,"USD",Benefits!$D:$D,"Actual") -> 0 | I38: =H38 -> 0 | J38: =SUM(D38:I38) -> 0
C39: COSTS
C40: Cost Plan (USD m) | D40: =SUMIFS(Costs!$AB:$AB,Costs!$A:$A,$A$33,Costs!$D:$D,"Plan") -> 0.1 | E40: =SUMIFS(Costs!$AC:$AC,Costs!$A:$A,$A$33,Costs!$D:$D,"Plan") -> 0.1 | F40: =SUMIFS(Costs!$AD:$AD,Costs!$A:$A,$A$33,Costs!$D:$D,"Plan") -> 0.1 | G40: =SUMIFS(Costs!$AE:$AE,Costs!$A:$A,$A$33,Costs!$D:$D,"Plan") -> 0.1 | H40: =SUMIFS(Costs!$AF:$AF,Costs!$A:$A,$A$33,Costs!$D:$D,"Plan") -> 0.1 | I40: =H40 -> 0.1 | J40: =SUM(D40:I40) -> 0.6 | K40: 0.406
C41: Cost Actual (USD m) | D41: =SUMIFS(Costs!$AB:$AB,Costs!$A:$A,$A$33,Costs!$D:$D,"Actual") -> 0 | E41: =SUMIFS(Costs!$AC:$AC,Costs!$A:$A,$A$33,Costs!$D:$D,"Actual") -> 0 | F41: =SUMIFS(Costs!$AD:$AD,Costs!$A:$A,$A$33,Costs!$D:$D,"Actual") -> 0 | G41: =SUMIFS(Costs!$AE:$AE,Costs!$A:$A,$A$33,Costs!$D:$D,"Actual") -> 0 | H41: =SUMIFS(Costs!$AF:$AF,Costs!$A:$A,$A$33,Costs!$D:$D,"Actual") -> 0 | I41: =H41 -> 0 | J41: =SUM(D41:I41) -> 0
C42: NET VALUE
C43: Net Value — Plan Base (USD m) | D43: =D36-D40 -> 1.14 | E43: =E36-E40 -> 1.76 | F43: =F36-F40 -> 1.76 | G43: =G36-G40 -> 1.76 | H43: =H36-H40 -> 1.76 | I43: =I36-I40 -> 1.76 | J43: =J36-J40 -> 9.94 | K43: =K36-K40 -> 8.246
C44: Net Value — Plan High (USD m) | D44: =D37-D40 -> 1.56 | E44: =E37-E40 -> 2.38 | F44: =F37-F40 -> 2.38 | G44: =G37-G40 -> 2.38 | H44: =H37-H40 -> 2.38 | I44: =I37-I40 -> 2.38 | J44: =J37-J40 -> 13.46
C45: Net Value — Actual (USD m) | D45: =D38-D41 -> 0 | E45: =E38-E41 -> 0 | F45: =F38-F41 -> 0 | G45: =G38-G41 -> 0 | H45: =H38-H41 -> 0 | I45: =I38-I41 -> 0 | J45: =J38-J41 -> 0
C46: ROI (Actual, %) | D46: =IFERROR(D45/D41,0) -> 0 | E46: =IFERROR(E45/E41,0) -> 0 | F46: =IFERROR(F45/F41,0) -> 0 | G46: =IFERROR(G45/G41,0) -> 0 | H46: =IFERROR(H45/H41,0) -> 0 | I46: =IFERROR(I45/I41,0) -> 0 | J46: =IFERROR(J45/J41,0) -> 0 | K46: =IFERROR(K45/K41,0) -> 0
A48: TOR-4 | B48: Verland-Norvia New Logos - FDI | C48: Revenue Plan — Base (USD m) | D48: =SUMIFS(Benefits!$S:$S,Benefits!$A:$A,$A$48,Benefits!$E:$E,"Revenue",Benefits!$F:$F,"USD",Benefits!$D:$D,"Plan Base") -> 0.52 | E48: =SUMIFS(Benefits!$T:$T,Benefits!$A:$A,$A$48,Benefits!$E:$E,"Revenue",Benefits!$F:$F,"USD",Benefits!$D:$D,"Plan Base") -> 1.1 | F48: =SUMIFS(Benefits!$U:$U,Benefits!$A:$A,$A$48,Benefits!$E:$E,"Revenue",Benefits!$F:$F,"USD",Benefits!$D:$D,"Plan Base") -> 1.1 | G48: =SUMIFS(Benefits!$V:$V,Benefits!$A:$A,$A$48,Benefits!$E:$E,"Revenue",Benefits!$F:$F,"USD",Benefits!$D:$D,"Plan Base") -> 1.1 | H48: =SUMIFS(Benefits!$W:$W,Benefits!$A:$A,$A$48,Benefits!$E:$E,"Revenue",Benefits!$F:$F,"USD",Benefits!$D:$D,"Plan Base") -> 1.1 | I48: =H48 -> 1.1 | J48: =SUM(D48:I48) -> 6.02 | K48: 3.961
C49: Revenue Plan — High (USD m) | D49: =SUMIFS(Benefits!$S:$S,Benefits!$A:$A,$A$48,Benefits!$E:$E,"Revenue",Benefits!$F:$F,"USD",Benefits!$D:$D,"Plan High") -> 0.78 | E49: =SUMIFS(Benefits!$T:$T,Benefits!$A:$A,$A$48,Benefits!$E:$E,"Revenue",Benefits!$F:$F,"USD",Benefits!$D:$D,"Plan High") -> 1.56 | F49: =SUMIFS(Benefits!$U:$U,Benefits!$A:$A,$A$48,Benefits!$E:$E,"Revenue",Benefits!$F:$F,"USD",Benefits!$D:$D,"Plan High") -> 1.56 | G49: =SUMIFS(Benefits!$V:$V,Benefits!$A:$A,$A$48,Benefits!$E:$E,"Revenue",Benefits!$F:$F,"USD",Benefits!$D:$D,"Plan High") -> 1.56 | H49: =SUMIFS(Benefits!$W:$W,Benefits!$A:$A,$A$48,Benefits!$E:$E,"Revenue",Benefits!$F:$F,"USD",Benefits!$D:$D,"Plan High") -> 1.56 | I49: =H49 -> 1.56 | J49: =SUM(D49:I49) -> 8.58
C50: Revenue Actual (USD m) | D50: =SUMIFS(Benefits!$S:$S,Benefits!$A:$A,$A$48,Benefits!$E:$E,"Revenue",Benefits!$F:$F,"USD",Benefits!$D:$D,"Actual") -> 0 | E50: =SUMIFS(Benefits!$T:$T,Benefits!$A:$A,$A$48,Benefits!$E:$E,"Revenue",Benefits!$F:$F,"USD",Benefits!$D:$D,"Actual") -> 0 | F50: =SUMIFS(Benefits!$U:$U,Benefits!$A:$A,$A$48,Benefits!$E:$E,"Revenue",Benefits!$F:$F,"USD",Benefits!$D:$D,"Actual") -> 0 | G50: =SUMIFS(Benefits!$V:$V,Benefits!$A:$A,$A$48,Benefits!$E:$E,"Revenue",Benefits!$F:$F,"USD",Benefits!$D:$D,"Actual") -> 0 | H50: =SUMIFS(Benefits!$W:$W,Benefits!$A:$A,$A$48,Benefits!$E:$E,"Revenue",Benefits!$F:$F,"USD",Benefits!$D:$D,"Actual") -> 0 | I50: =H50 -> 0 | J50: =SUM(D50:I50) -> 0
C51: Gross Margin Plan — Base (USD m) | D51: =SUMIFS(Benefits!$S:$S,Benefits!$A:$A,$A$48,Benefits!$E:$E,"Gross Margin",Benefits!$F:$F,"USD",Benefits!$D:$D,"Plan Base") -> 0.28 | E51: =SUMIFS(Benefits!$T:$T,Benefits!$A:$A,$A$48,Benefits!$E:$E,"Gross Margin",Benefits!$F:$F,"USD",Benefits!$D:$D,"Plan Base") -> 0.72 | F51: =SUMIFS(Benefits!$U:$U,Benefits!$A:$A,$A$48,Benefits!$E:$E,"Gross Margin",Benefits!$F:$F,"USD",Benefits!$D:$D,"Plan Base") -> 0.72 | G51: =SUMIFS(Benefits!$V:$V,Benefits!$A:$A,$A$48,Benefits!$E:$E,"Gross Margin",Benefits!$F:$F,"USD",Benefits!$D:$D,"Plan Base") -> 0.72 | H51: =SUMIFS(Benefits!$W:$W,Benefits!$A:$A,$A$48,Benefits!$E:$E,"Gross Margin",Benefits!$F:$F,"USD",Benefits!$D:$D,"Plan Base") -> 0.72 | I51: =H51 -> 0.72 | J51: =SUM(D51:I51) -> 3.88 | K51: 3.016
C52: Gross Margin Plan — High (USD m) | D52: =SUMIFS(Benefits!$S:$S,Benefits!$A:$A,$A$48,Benefits!$E:$E,"Gross Margin",Benefits!$F:$F,"USD",Benefits!$D:$D,"Plan High") -> 0.36 | E52: =SUMIFS(Benefits!$T:$T,Benefits!$A:$A,$A$48,Benefits!$E:$E,"Gross Margin",Benefits!$F:$F,"USD",Benefits!$D:$D,"Plan High") -> 1.02 | F52: =SUMIFS(Benefits!$U:$U,Benefits!$A:$A,$A$48,Benefits!$E:$E,"Gross Margin",Benefits!$F:$F,"USD",Benefits!$D:$D,"Plan High") -> 1.02 | G52: =SUMIFS(Benefits!$V:$V,Benefits!$A:$A,$A$48,Benefits!$E:$E,"Gross Margin",Benefits!$F:$F,"USD",Benefits!$D:$D,"Plan High") -> 1.02 | H52: =SUMIFS(Benefits!$W:$W,Benefits!$A:$A,$A$48,Benefits!$E:$E,"Gross Margin",Benefits!$F:$F,"USD",Benefits!$D:$D,"Plan High") -> 1.02 | I52: =H52 -> 1.02 | J52: =SUM(D52:I52) -> 5.46
C53: Gross Margin Actual (USD m) | D53: =SUMIFS(Benefits!$S:$S,Benefits!$A:$A,$A$48,Benefits!$E:$E,"Gross Margin",Benefits!$F:$F,"USD",Benefits!$D:$D,"Actual") -> 0 | E53: =SUMIFS(Benefits!$T:$T,Benefits!$A:$A,$A$48,Benefits!$E:$E,"Gross Margin",Benefits!$F:$F,"USD",Benefits!$D:$D,"Actual") -> 0 | F53: =SUMIFS(Benefits!$U:$U,Benefits!$A:$A,$A$48,Benefits!$E:$E,"Gross Margin",Benefits!$F:$F,"USD",Benefits!$D:$D,"Actual") -> 0 | G53: =SUMIFS(Benefits!$V:$V,Benefits!$A:$A,$A$48,Benefits!$E:$E,"Gross Margin",Benefits!$F:$F,"USD",Benefits!$D:$D,"Actual") -> 0 | H53: =SUMIFS(Benefits!$W:$W,Benefits!$A:$A,$A$48,Benefits!$E:$E,"Gross Margin",Benefits!$F:$F,"USD",Benefits!$D:$D,"Actual") -> 0 | I53: =H53 -> 0 | J53: =SUM(D53:I53) -> 0
C54: COSTS
C55: Cost Plan (USD m) | D55: =SUMIFS(Costs!$AB:$AB,Costs!$A:$A,$A$48,Costs!$D:$D,"Plan") -> 0.62 | E55: =SUMIFS(Costs!$AC:$AC,Costs!$A:$A,$A$48,Costs!$D:$D,"Plan") -> 0.64 | F55: =SUMIFS(Costs!$AD:$AD,Costs!$A:$A,$A$48,Costs!$D:$D,"Plan") -> 0.64 | G55: =SUMIFS(Costs!$AE:$AE,Costs!$A:$A,$A$48,Costs!$D:$D,"Plan") -> 0.64 | H55: =SUMIFS(Costs!$AF:$AF,Costs!$A:$A,$A$48,Costs!$D:$D,"Plan") -> 0.64 | I55: =H55 -> 0.64 | J55: =SUM(D55:I55) -> 3.82 | K55: 1.961
C56: Cost Actual (USD m) | D56: =SUMIFS(Costs!$AB:$AB,Costs!$A:$A,$A$48,Costs!$D:$D,"Actual") -> 0 | E56: =SUMIFS(Costs!$AC:$AC,Costs!$A:$A,$A$48,Costs!$D:$D,"Actual") -> 0 | F56: =SUMIFS(Costs!$AD:$AD,Costs!$A:$A,$A$48,Costs!$D:$D,"Actual") -> 0 | G56: =SUMIFS(Costs!$AE:$AE,Costs!$A:$A,$A$48,Costs!$D:$D,"Actual") -> 0 | H56: =SUMIFS(Costs!$AF:$AF,Costs!$A:$A,$A$48,Costs!$D:$D,"Actual") -> 0 | I56: =H56 -> 0 | J56: =SUM(D56:I56) -> 0
C57: NET VALUE
C58: Net Value — Plan Base (USD m) | D58: =D51-D55 -> -0.34 | E58: =E51-E55 -> 0.08 | F58: =F51-F55 -> 0.08 | G58: =G51-G55 -> 0.08 | H58: =H51-H55 -> 0.08 | I58: =I51-I55 -> 0.08 | J58: =J51-J55 -> 0.06 | K58: =K51-K55 -> 1.055
C59: Net Value — Plan High (USD m) | D59: =D52-D55 -> -0.26 | E59: =E52-E55 -> 0.38 | F59: =F52-F55 -> 0.38 | G59: =G52-G55 -> 0.38 | H59: =H52-H55 -> 0.38 | I59: =I52-I55 -> 0.38 | J59: =J52-J55 -> 1.64
C60: Net Value — Actual (USD m) | D60: =D53-D56 -> 0 | E60: =E53-E56 -> 0 | F60: =F53-F56 -> 0 | G60: =G53-G56 -> 0 | H60: =H53-H56 -> 0 | I60: =I53-I56 -> 0 | J60: =J53-J56 -> 0
C61: ROI (Actual, %) | D61: =IFERROR(D60/D56,0) -> 0 | E61: =IFERROR(E60/E56,0) -> 0 | F61: =IFERROR(F60/F56,0) -> 0 | G61: =IFERROR(G60/G56,0) -> 0 | H61: =IFERROR(H60/H56,0) -> 0 | I61: =IFERROR(I60/I56,0) -> 0 | J61: =IFERROR(J60/J56,0) -> 0 | K61: =IFERROR(K60/K56,0) -> 0
A63: TOR-5 | B63: Advisory - Geographical Expansion | C63: Revenue Plan — Base (USD m) | D63: =SUMIFS(Benefits!$S:$S,Benefits!$A:$A,$A$63,Benefits!$E:$E,"Revenue",Benefits!$F:$F,"USD",Benefits!$D:$D,"Plan Base") -> 0 | E63: =SUMIFS(Benefits!$T:$T,Benefits!$A:$A,$A$63,Benefits!$E:$E,"Revenue",Benefits!$F:$F,"USD",Benefits!$D:$D,"Plan Base") -> 0.82 | F63: =SUMIFS(Benefits!$U:$U,Benefits!$A:$A,$A$63,Benefits!$E:$E,"Revenue",Benefits!$F:$F,"USD",Benefits!$D:$D,"Plan Base") -> 2.46 | G63: =SUMIFS(Benefits!$V:$V,Benefits!$A:$A,$A$63,Benefits!$E:$E,"Revenue",Benefits!$F:$F,"USD",Benefits!$D:$D,"Plan Base") -> 2.46 | H63: =SUMIFS(Benefits!$W:$W,Benefits!$A:$A,$A$63,Benefits!$E:$E,"Revenue",Benefits!$F:$F,"USD",Benefits!$D:$D,"Plan Base") -> 2.46 | I63: =H63 -> 2.46 | J63: =SUM(D63:I63) -> 10.66 | K63: 10.967
C64: Revenue Plan — High (USD m) | D64: =SUMIFS(Benefits!$S:$S,Benefits!$A:$A,$A$63,Benefits!$E:$E,"Revenue",Benefits!$F:$F,"USD",Benefits!$D:$D,"Plan High") -> 0 | E64: =SUMIFS(Benefits!$T:$T,Benefits!$A:$A,$A$63,Benefits!$E:$E,"Revenue",Benefits!$F:$F,"USD",Benefits!$D:$D,"Plan High") -> 1.02 | F64: =SUMIFS(Benefits!$U:$U,Benefits!$A:$A,$A$63,Benefits!$E:$E,"Revenue",Benefits!$F:$F,"USD",Benefits!$D:$D,"Plan High") -> 3.08 | G64: =SUMIFS(Benefits!$V:$V,Benefits!$A:$A,$A$63,Benefits!$E:$E,"Revenue",Benefits!$F:$F,"USD",Benefits!$D:$D,"Plan High") -> 3.08 | H64: =SUMIFS(Benefits!$W:$W,Benefits!$A:$A,$A$63,Benefits!$E:$E,"Revenue",Benefits!$F:$F,"USD",Benefits!$D:$D,"Plan High") -> 3.08 | I64: =H64 -> 3.08 | J64: =SUM(D64:I64) -> 13.34
C65: Revenue Actual (USD m) | D65: =SUMIFS(Benefits!$S:$S,Benefits!$A:$A,$A$63,Benefits!$E:$E,"Revenue",Benefits!$F:$F,"USD",Benefits!$D:$D,"Actual") -> 0 | E65: =SUMIFS(Benefits!$T:$T,Benefits!$A:$A,$A$63,Benefits!$E:$E,"Revenue",Benefits!$F:$F,"USD",Benefits!$D:$D,"Actual") -> 0 | F65: =SUMIFS(Benefits!$U:$U,Benefits!$A:$A,$A$63,Benefits!$E:$E,"Revenue",Benefits!$F:$F,"USD",Benefits!$D:$D,"Actual") -> 0 | G65: =SUMIFS(Benefits!$V:$V,Benefits!$A:$A,$A$63,Benefits!$E:$E,"Revenue",Benefits!$F:$F,"USD",Benefits!$D:$D,"Actual") -> 0 | H65: =SUMIFS(Benefits!$W:$W,Benefits!$A:$A,$A$63,Benefits!$E:$E,"Revenue",Benefits!$F:$F,"USD",Benefits!$D:$D,"Actual") -> 0 | I65: =H65 -> 0 | J65: =SUM(D65:I65) -> 0
C66: Gross Margin Plan — Base (USD m) | D66: =SUMIFS(Benefits!$S:$S,Benefits!$A:$A,$A$63,Benefits!$E:$E,"Gross Margin",Benefits!$F:$F,"USD",Benefits!$D:$D,"Plan Base") -> 0 | E66: =SUMIFS(Benefits!$T:$T,Benefits!$A:$A,$A$63,Benefits!$E:$E,"Gross Margin",Benefits!$F:$F,"USD",Benefits!$D:$D,"Plan Base") -> 0.48 | F66: =SUMIFS(Benefits!$U:$U,Benefits!$A:$A,$A$63,Benefits!$E:$E,"Gross Margin",Benefits!$F:$F,"USD",Benefits!$D:$D,"Plan Base") -> 1.42 | G66: =SUMIFS(Benefits!$V:$V,Benefits!$A:$A,$A$63,Benefits!$E:$E,"Gross Margin",Benefits!$F:$F,"USD",Benefits!$D:$D,"Plan Base") -> 1.42 | H66: =SUMIFS(Benefits!$W:$W,Benefits!$A:$A,$A$63,Benefits!$E:$E,"Gross Margin",Benefits!$F:$F,"USD",Benefits!$D:$D,"Plan Base") -> 1.42 | I66: =H66 -> 1.42 | J66: =SUM(D66:I66) -> 6.16 | K66: 6.12
C67: Gross Margin Plan — High (USD m) | D67: =SUMIFS(Benefits!$S:$S,Benefits!$A:$A,$A$63,Benefits!$E:$E,"Gross Margin",Benefits!$F:$F,"USD",Benefits!$D:$D,"Plan High") -> 0 | E67: =SUMIFS(Benefits!$T:$T,Benefits!$A:$A,$A$63,Benefits!$E:$E,"Gross Margin",Benefits!$F:$F,"USD",Benefits!$D:$D,"Plan High") -> 0.64 | F67: =SUMIFS(Benefits!$U:$U,Benefits!$A:$A,$A$63,Benefits!$E:$E,"Gross Margin",Benefits!$F:$F,"USD",Benefits!$D:$D,"Plan High") -> 1.92 | G67: =SUMIFS(Benefits!$V:$V,Benefits!$A:$A,$A$63,Benefits!$E:$E,"Gross Margin",Benefits!$F:$F,"USD",Benefits!$D:$D,"Plan High") -> 1.92 | H67: =SUMIFS(Benefits!$W:$W,Benefits!$A:$A,$A$63,Benefits!$E:$E,"Gross Margin",Benefits!$F:$F,"USD",Benefits!$D:$D,"Plan High") -> 1.92 | I67: =H67 -> 1.92 | J67: =SUM(D67:I67) -> 8.32
C68: Gross Margin Actual (USD m) | D68: =SUMIFS(Benefits!$S:$S,Benefits!$A:$A,$A$63,Benefits!$E:$E,"Gross Margin",Benefits!$F:$F,"USD",Benefits!$D:$D,"Actual") -> 0 | E68: =SUMIFS(Benefits!$T:$T,Benefits!$A:$A,$A$63,Benefits!$E:$E,"Gross Margin",Benefits!$F:$F,"USD",Benefits!$D:$D,"Actual") -> 0 | F68: =SUMIFS(Benefits!$U:$U,Benefits!$A:$A,$A$63,Benefits!$E:$E,"Gross Margin",Benefits!$F:$F,"USD",Benefits!$D:$D,"Actual") -> 0 | G68: =SUMIFS(Benefits!$V:$V,Benefits!$A:$A,$A$63,Benefits!$E:$E,"Gross Margin",Benefits!$F:$F,"USD",Benefits!$D:$D,"Actual") -> 0 | H68: =SUMIFS(Benefits!$W:$W,Benefits!$A:$A,$A$63,Benefits!$E:$E,"Gross Margin",Benefits!$F:$F,"USD",Benefits!$D:$D,"Actual") -> 0 | I68: =H68 -> 0 | J68: =SUM(D68:I68) -> 0
C69: COSTS
C70: Cost Plan (USD m) | D70: =SUMIFS(Costs!$AB:$AB,Costs!$A:$A,$A$63,Costs!$D:$D,"Plan") -> 0 | E70: =SUMIFS(Costs!$AC:$AC,Costs!$A:$A,$A$63,Costs!$D:$D,"Plan") -> 0 | F70: =SUMIFS(Costs!$AD:$AD,Costs!$A:$A,$A$63,Costs!$D:$D,"Plan") -> 0 | G70: =SUMIFS(Costs!$AE:$AE,Costs!$A:$A,$A$63,Costs!$D:$D,"Plan") -> 0 | H70: =SUMIFS(Costs!$AF:$AF,Costs!$A:$A,$A$63,Costs!$D:$D,"Plan") -> 0 | I70: =H70 -> 0 | J70: =SUM(D70:I70) -> 0 | K70: 0
C71: Cost Actual (USD m) | D71: =SUMIFS(Costs!$AB:$AB,Costs!$A:$A,$A$63,Costs!$D:$D,"Actual") -> 0 | E71: =SUMIFS(Costs!$AC:$AC,Costs!$A:$A,$A$63,Costs!$D:$D,"Actual") -> 0 | F71: =SUMIFS(Costs!$AD:$AD,Costs!$A:$A,$A$63,Costs!$D:$D,"Actual") -> 0 | G71: =SUMIFS(Costs!$AE:$AE,Costs!$A:$A,$A$63,Costs!$D:$D,"Actual") -> 0 | H71: =SUMIFS(Costs!$AF:$AF,Costs!$A:$A,$A$63,Costs!$D:$D,"Actual") -> 0 | I71: =H71 -> 0 | J71: =SUM(D71:I71) -> 0
C72: NET VALUE
C73: Net Value — Plan Base (USD m) | D73: =D66-D70 -> 0 | E73: =E66-E70 -> 0.48 | F73: =F66-F70 -> 1.42 | G73: =G66-G70 -> 1.42 | H73: =H66-H70 -> 1.42 | I73: =I66-I70 -> 1.42 | J73: =J66-J70 -> 6.16 | K73: =K66-K70 -> 6.12
C74: Net Value — Plan High (USD m) | D74: =D67-D70 -> 0 | E74: =E67-E70 -> 0.64 | F74: =F67-F70 -> 1.92 | G74: =G67-G70 -> 1.92 | H74: =H67-H70 -> 1.92 | I74: =I67-I70 -> 1.92 | J74: =J67-J70 -> 8.32
C75: Net Value — Actual (USD m) | D75: =D68-D71 -> 0 | E75: =E68-E71 -> 0 | F75: =F68-F71 -> 0 | G75: =G68-G71 -> 0 | H75: =H68-H71 -> 0 | I75: =I68-I71 -> 0 | J75: =J68-J71 -> 0
C76: ROI (Actual, %) | D76: =IFERROR(D75/D71,0) -> 0 | E76: =IFERROR(E75/E71,0) -> 0 | F76: =IFERROR(F75/F71,0) -> 0 | G76: =IFERROR(G75/G71,0) -> 0 | H76: =IFERROR(H75/H71,0) -> 0 | I76: =IFERROR(I75/I71,0) -> 0 | J76: =IFERROR(J75/J71,0) -> 0 | K76: =IFERROR(K75/K71,0) -> 0
A78: TOR-6 | B78: [GROUP] Revenue Retention: Reinvent CSM for Proactive Churn Management (Westmark) | C78: Revenue Plan — Base (USD m) | D78: =SUMIFS(Benefits!$S:$S,Benefits!$A:$A,$A$78,Benefits!$E:$E,"Revenue",Benefits!$F:$F,"USD",Benefits!$D:$D,"Plan Base") -> 0 | E78: =SUMIFS(Benefits!$T:$T,Benefits!$A:$A,$A$78,Benefits!$E:$E,"Revenue",Benefits!$F:$F,"USD",Benefits!$D:$D,"Plan Base") -> 0.4 | F78: =SUMIFS(Benefits!$U:$U,Benefits!$A:$A,$A$78,Benefits!$E:$E,"Revenue",Benefits!$F:$F,"USD",Benefits!$D:$D,"Plan Base") -> 0.4 | G78: =SUMIFS(Benefits!$V:$V,Benefits!$A:$A,$A$78,Benefits!$E:$E,"Revenue",Benefits!$F:$F,"USD",Benefits!$D:$D,"Plan Base") -> 0.4 | H78: =SUMIFS(Benefits!$W:$W,Benefits!$A:$A,$A$78,Benefits!$E:$E,"Revenue",Benefits!$F:$F,"USD",Benefits!$D:$D,"Plan Base") -> 0.4 | I78: =H78 -> 0.4 | J78: =SUM(D78:I78) -> 2 | K78: 1.545
C79: Revenue Plan — High (USD m) | D79: =SUMIFS(Benefits!$S:$S,Benefits!$A:$A,$A$78,Benefits!$E:$E,"Revenue",Benefits!$F:$F,"USD",Benefits!$D:$D,"Plan High") -> 0 | E79: =SUMIFS(Benefits!$T:$T,Benefits!$A:$A,$A$78,Benefits!$E:$E,"Revenue",Benefits!$F:$F,"USD",Benefits!$D:$D,"Plan High") -> 0.8 | F79: =SUMIFS(Benefits!$U:$U,Benefits!$A:$A,$A$78,Benefits!$E:$E,"Revenue",Benefits!$F:$F,"USD",Benefits!$D:$D,"Plan High") -> 0.8 | G79: =SUMIFS(Benefits!$V:$V,Benefits!$A:$A,$A$78,Benefits!$E:$E,"Revenue",Benefits!$F:$F,"USD",Benefits!$D:$D,"Plan High") -> 0.8 | H79: =SUMIFS(Benefits!$W:$W,Benefits!$A:$A,$A$78,Benefits!$E:$E,"Revenue",Benefits!$F:$F,"USD",Benefits!$D:$D,"Plan High") -> 0.8 | I79: =H79 -> 0.8 | J79: =SUM(D79:I79) -> 4
C80: Revenue Actual (USD m) | D80: =SUMIFS(Benefits!$S:$S,Benefits!$A:$A,$A$78,Benefits!$E:$E,"Revenue",Benefits!$F:$F,"USD",Benefits!$D:$D,"Actual") -> 0 | E80: =SUMIFS(Benefits!$T:$T,Benefits!$A:$A,$A$78,Benefits!$E:$E,"Revenue",Benefits!$F:$F,"USD",Benefits!$D:$D,"Actual") -> 0 | F80: =SUMIFS(Benefits!$U:$U,Benefits!$A:$A,$A$78,Benefits!$E:$E,"Revenue",Benefits!$F:$F,"USD",Benefits!$D:$D,"Actual") -> 0 | G80: =SUMIFS(Benefits!$V:$V,Benefits!$A:$A,$A$78,Benefits!$E:$E,"Revenue",Benefits!$F:$F,"USD",Benefits!$D:$D,"Actual") -> 0 | H80: =SUMIFS(Benefits!$W:$W,Benefits!$A:$A,$A$78,Benefits!$E:$E,"Revenue",Benefits!$F:$F,"USD",Benefits!$D:$D,"Actual") -> 0 | I80: =H80 -> 0 | J80: =SUM(D80:I80) -> 0
C81: Gross Margin Plan — Base (USD m) | D81: =SUMIFS(Benefits!$S:$S,Benefits!$A:$A,$A$78,Benefits!$E:$E,"Gross Margin",Benefits!$F:$F,"USD",Benefits!$D:$D,"Plan Base") -> 0 | E81: =SUMIFS(Benefits!$T:$T,Benefits!$A:$A,$A$78,Benefits!$E:$E,"Gross Margin",Benefits!$F:$F,"USD",Benefits!$D:$D,"Plan Base") -> 0.24 | F81: =SUMIFS(Benefits!$U:$U,Benefits!$A:$A,$A$78,Benefits!$E:$E,"Gross Margin",Benefits!$F:$F,"USD",Benefits!$D:$D,"Plan Base") -> 0.24 | G81: =SUMIFS(Benefits!$V:$V,Benefits!$A:$A,$A$78,Benefits!$E:$E,"Gross Margin",Benefits!$F:$F,"USD",Benefits!$D:$D,"Plan Base") -> 0.24 | H81: =SUMIFS(Benefits!$W:$W,Benefits!$A:$A,$A$78,Benefits!$E:$E,"Gross Margin",Benefits!$F:$F,"USD",Benefits!$D:$D,"Plan Base") -> 0.24 | I81: =H81 -> 0.24 | J81: =SUM(D81:I81) -> 1.2 | K81: 1.024
C82: Gross Margin Plan — High (USD m) | D82: =SUMIFS(Benefits!$S:$S,Benefits!$A:$A,$A$78,Benefits!$E:$E,"Gross Margin",Benefits!$F:$F,"USD",Benefits!$D:$D,"Plan High") -> 0 | E82: =SUMIFS(Benefits!$T:$T,Benefits!$A:$A,$A$78,Benefits!$E:$E,"Gross Margin",Benefits!$F:$F,"USD",Benefits!$D:$D,"Plan High") -> 0.5 | F82: =SUMIFS(Benefits!$U:$U,Benefits!$A:$A,$A$78,Benefits!$E:$E,"Gross Margin",Benefits!$F:$F,"USD",Benefits!$D:$D,"Plan High") -> 0.5 | G82: =SUMIFS(Benefits!$V:$V,Benefits!$A:$A,$A$78,Benefits!$E:$E,"Gross Margin",Benefits!$F:$F,"USD",Benefits!$D:$D,"Plan High") -> 0.5 | H82: =SUMIFS(Benefits!$W:$W,Benefits!$A:$A,$A$78,Benefits!$E:$E,"Gross Margin",Benefits!$F:$F,"USD",Benefits!$D:$D,"Plan High") -> 0.5 | I82: =H82 -> 0.5 | J82: =SUM(D82:I82) -> 2.5
C83: Gross Margin Actual (USD m) | D83: =SUMIFS(Benefits!$S:$S,Benefits!$A:$A,$A$78,Benefits!$E:$E,"Gross Margin",Benefits!$F:$F,"USD",Benefits!$D:$D,"Actual") -> 0 | E83: =SUMIFS(Benefits!$T:$T,Benefits!$A:$A,$A$78,Benefits!$E:$E,"Gross Margin",Benefits!$F:$F,"USD",Benefits!$D:$D,"Actual") -> 0 | F83: =SUMIFS(Benefits!$U:$U,Benefits!$A:$A,$A$78,Benefits!$E:$E,"Gross Margin",Benefits!$F:$F,"USD",Benefits!$D:$D,"Actual") -> 0 | G83: =SUMIFS(Benefits!$V:$V,Benefits!$A:$A,$A$78,Benefits!$E:$E,"Gross Margin",Benefits!$F:$F,"USD",Benefits!$D:$D,"Actual") -> 0 | H83: =SUMIFS(Benefits!$W:$W,Benefits!$A:$A,$A$78,Benefits!$E:$E,"Gross Margin",Benefits!$F:$F,"USD",Benefits!$D:$D,"Actual") -> 0 | I83: =H83 -> 0 | J83: =SUM(D83:I83) -> 0
C84: COSTS
C85: Cost Plan (USD m) | D85: =SUMIFS(Costs!$AB:$AB,Costs!$A:$A,$A$78,Costs!$D:$D,"Plan") -> 0 | E85: =SUMIFS(Costs!$AC:$AC,Costs!$A:$A,$A$78,Costs!$D:$D,"Plan") -> 0 | F85: =SUMIFS(Costs!$AD:$AD,Costs!$A:$A,$A$78,Costs!$D:$D,"Plan") -> 0 | G85: =SUMIFS(Costs!$AE:$AE,Costs!$A:$A,$A$78,Costs!$D:$D,"Plan") -> 0 | H85: =SUMIFS(Costs!$AF:$AF,Costs!$A:$A,$A$78,Costs!$D:$D,"Plan") -> 0 | I85: =H85 -> 0 | J85: =SUM(D85:I85) -> 0 | K85: 0
C86: Cost Actual (USD m) | D86: =SUMIFS(Costs!$AB:$AB,Costs!$A:$A,$A$78,Costs!$D:$D,"Actual") -> 0 | E86: =SUMIFS(Costs!$AC:$AC,Costs!$A:$A,$A$78,Costs!$D:$D,"Actual") -> 0 | F86: =SUMIFS(Costs!$AD:$AD,Costs!$A:$A,$A$78,Costs!$D:$D,"Actual") -> 0 | G86: =SUMIFS(Costs!$AE:$AE,Costs!$A:$A,$A$78,Costs!$D:$D,"Actual") -> 0 | H86: =SUMIFS(Costs!$AF:$AF,Costs!$A:$A,$A$78,Costs!$D:$D,"Actual") -> 0 | I86: =H86 -> 0 | J86: =SUM(D86:I86) -> 0
C87: NET VALUE
C88: Net Value — Plan Base (USD m) | D88: =D81-D85 -> 0 | E88: =E81-E85 -> 0.24 | F88: =F81-F85 -> 0.24 | G88: =G81-G85 -> 0.24 | H88: =H81-H85 -> 0.24 | I88: =I81-I85 -> 0.24 | J88: =J81-J85 -> 1.2 | K88: =K81-K85 -> 1.024
C89: Net Value — Plan High (USD m) | D89: =D82-D85 -> 0 | E89: =E82-E85 -> 0.5 | F89: =F82-F85 -> 0.5 | G89: =G82-G85 -> 0.5 | H89: =H82-H85 -> 0.5 | I89: =I82-I85 -> 0.5 | J89: =J82-J85 -> 2.5
C90: Net Value — Actual (USD m) | D90: =D83-D86 -> 0 | E90: =E83-E86 -> 0 | F90: =F83-F86 -> 0 | G90: =G83-G86 -> 0 | H90: =H83-H86 -> 0 | I90: =I83-I86 -> 0 | J90: =J83-J86 -> 0
C91: ROI (Actual, %) | D91: =IFERROR(D90/D86,0) -> 0 | E91: =IFERROR(E90/E86,0) -> 0 | F91: =IFERROR(F90/F86,0) -> 0 | G91: =IFERROR(G90/G86,0) -> 0 | H91: =IFERROR(H90/H86,0) -> 0 | I91: =IFERROR(I90/I86,0) -> 0 | J91: =IFERROR(J90/J86,0) -> 0 | K91: =IFERROR(K90/K86,0) -> 0
A93: EBR-1 | B93: MER Billing System Integration & Automation | C93: Revenue Plan — Base (USD m) | D93: =SUMIFS(Benefits!$S:$S,Benefits!$A:$A,$A$93,Benefits!$E:$E,"Revenue",Benefits!$F:$F,"USD",Benefits!$D:$D,"Plan Base") -> 0 | E93: =SUMIFS(Benefits!$T:$T,Benefits!$A:$A,$A$93,Benefits!$E:$E,"Revenue",Benefits!$F:$F,"USD",Benefits!$D:$D,"Plan Base") -> 0 | F93: =SUMIFS(Benefits!$U:$U,Benefits!$A:$A,$A$93,Benefits!$E:$E,"Revenue",Benefits!$F:$F,"USD",Benefits!$D:$D,"Plan Base") -> 0 | G93: =SUMIFS(Benefits!$V:$V,Benefits!$A:$A,$A$93,Benefits!$E:$E,"Revenue",Benefits!$F:$F,"USD",Benefits!$D:$D,"Plan Base") -> 0 | H93: =SUMIFS(Benefits!$W:$W,Benefits!$A:$A,$A$93,Benefits!$E:$E,"Revenue",Benefits!$F:$F,"USD",Benefits!$D:$D,"Plan Base") -> 0 | I93: =H93 -> 0 | J93: =SUM(D93:I93) -> 0 | K93: 0
C94: Revenue Plan — High (USD m) | D94: =SUMIFS(Benefits!$S:$S,Benefits!$A:$A,$A$93,Benefits!$E:$E,"Revenue",Benefits!$F:$F,"USD",Benefits!$D:$D,"Plan High") -> 0 | E94: =SUMIFS(Benefits!$T:$T,Benefits!$A:$A,$A$93,Benefits!$E:$E,"Revenue",Benefits!$F:$F,"USD",Benefits!$D:$D,"Plan High") -> 0 | F94: =SUMIFS(Benefits!$U:$U,Benefits!$A:$A,$A$93,Benefits!$E:$E,"Revenue",Benefits!$F:$F,"USD",Benefits!$D:$D,"Plan High") -> 0 | G94: =SUMIFS(Benefits!$V:$V,Benefits!$A:$A,$A$93,Benefits!$E:$E,"Revenue",Benefits!$F:$F,"USD",Benefits!$D:$D,"Plan High") -> 0 | H94: =SUMIFS(Benefits!$W:$W,Benefits!$A:$A,$A$93,Benefits!$E:$E,"Revenue",Benefits!$F:$F,"USD",Benefits!$D:$D,"Plan High") -> 0 | I94: =H94 -> 0 | J94: =SUM(D94:I94) -> 0 | K94: 0
C95: Revenue Actual (USD m) | D95: =SUMIFS(Benefits!$S:$S,Benefits!$A:$A,$A$93,Benefits!$E:$E,"Revenue",Benefits!$F:$F,"USD",Benefits!$D:$D,"Actual") -> 0 | E95: =SUMIFS(Benefits!$T:$T,Benefits!$A:$A,$A$93,Benefits!$E:$E,"Revenue",Benefits!$F:$F,"USD",Benefits!$D:$D,"Actual") -> 0 | F95: =SUMIFS(Benefits!$U:$U,Benefits!$A:$A,$A$93,Benefits!$E:$E,"Revenue",Benefits!$F:$F,"USD",Benefits!$D:$D,"Actual") -> 0 | G95: =SUMIFS(Benefits!$V:$V,Benefits!$A:$A,$A$93,Benefits!$E:$E,"Revenue",Benefits!$F:$F,"USD",Benefits!$D:$D,"Actual") -> 0 | H95: =SUMIFS(Benefits!$W:$W,Benefits!$A:$A,$A$93,Benefits!$E:$E,"Revenue",Benefits!$F:$F,"USD",Benefits!$D:$D,"Actual") -> 0 | I95: =H95 -> 0 | J95: =SUM(D95:I95) -> 0 | K95: 0
C96: Gross Margin Plan — Base (USD m) | D96: =SUMIFS(Benefits!$S:$S,Benefits!$A:$A,$A$93,Benefits!$E:$E,"Gross Margin",Benefits!$F:$F,"USD",Benefits!$D:$D,"Plan Base") -> 0 | E96: =SUMIFS(Benefits!$T:$T,Benefits!$A:$A,$A$93,Benefits!$E:$E,"Gross Margin",Benefits!$F:$F,"USD",Benefits!$D:$D,"Plan Base") -> 0.462 | F96: =SUMIFS(Benefits!$U:$U,Benefits!$A:$A,$A$93,Benefits!$E:$E,"Gross Margin",Benefits!$F:$F,"USD",Benefits!$D:$D,"Plan Base") -> 0.682 | G96: =SUMIFS(Benefits!$V:$V,Benefits!$A:$A,$A$93,Benefits!$E:$E,"Gross Margin",Benefits!$F:$F,"USD",Benefits!$D:$D,"Plan Base") -> 0.682 | H96: =SUMIFS(Benefits!$W:$W,Benefits!$A:$A,$A$93,Benefits!$E:$E,"Gross Margin",Benefits!$F:$F,"USD",Benefits!$D:$D,"Plan Base") -> 0.682 | I96: =H96 -> 0.682 | J96: =SUM(D96:I96) -> 3.19 | K96: 3.2
C97: Gross Margin Plan — High (USD m) | D97: =SUMIFS(Benefits!$S:$S,Benefits!$A:$A,$A$93,Benefits!$E:$E,"Gross Margin",Benefits!$F:$F,"USD",Benefits!$D:$D,"Plan High") -> 0 | E97: =SUMIFS(Benefits!$T:$T,Benefits!$A:$A,$A$93,Benefits!$E:$E,"Gross Margin",Benefits!$F:$F,"USD",Benefits!$D:$D,"Plan High") -> 0.572 | F97: =SUMIFS(Benefits!$U:$U,Benefits!$A:$A,$A$93,Benefits!$E:$E,"Gross Margin",Benefits!$F:$F,"USD",Benefits!$D:$D,"Plan High") -> 0.814 | G97: =SUMIFS(Benefits!$V:$V,Benefits!$A:$A,$A$93,Benefits!$E:$E,"Gross Margin",Benefits!$F:$F,"USD",Benefits!$D:$D,"Plan High") -> 0.814 | H97: =SUMIFS(Benefits!$W:$W,Benefits!$A:$A,$A$93,Benefits!$E:$E,"Gross Margin",Benefits!$F:$F,"USD",Benefits!$D:$D,"Plan High") -> 0.814 | I97: =H97 -> 0.814 | J97: =SUM(D97:I97) -> 3.828
C98: Gross Margin Actual (USD m) | D98: =SUMIFS(Benefits!$S:$S,Benefits!$A:$A,$A$93,Benefits!$E:$E,"Gross Margin",Benefits!$F:$F,"USD",Benefits!$D:$D,"Actual") -> 0 | E98: =SUMIFS(Benefits!$T:$T,Benefits!$A:$A,$A$93,Benefits!$E:$E,"Gross Margin",Benefits!$F:$F,"USD",Benefits!$D:$D,"Actual") -> 0 | F98: =SUMIFS(Benefits!$U:$U,Benefits!$A:$A,$A$93,Benefits!$E:$E,"Gross Margin",Benefits!$F:$F,"USD",Benefits!$D:$D,"Actual") -> 0 | G98: =SUMIFS(Benefits!$V:$V,Benefits!$A:$A,$A$93,Benefits!$E:$E,"Gross Margin",Benefits!$F:$F,"USD",Benefits!$D:$D,"Actual") -> 0 | H98: =SUMIFS(Benefits!$W:$W,Benefits!$A:$A,$A$93,Benefits!$E:$E,"Gross Margin",Benefits!$F:$F,"USD",Benefits!$D:$D,"Actual") -> 0 | I98: =H98 -> 0 | J98: =SUM(D98:I98) -> 0
C99: COSTS
C100: Cost Plan (USD m) | D100: =SUMIFS(Costs!$AB:$AB,Costs!$A:$A,$A$93,Costs!$D:$D,"Plan") -> 0 | E100: =SUMIFS(Costs!$AC:$AC,Costs!$A:$A,$A$93,Costs!$D:$D,"Plan") -> 0.066 | F100: =SUMIFS(Costs!$AD:$AD,Costs!$A:$A,$A$93,Costs!$D:$D,"Plan") -> 0.066 | G100: =SUMIFS(Costs!$AE:$AE,Costs!$A:$A,$A$93,Costs!$D:$D,"Plan") -> 0.066 | H100: =SUMIFS(Costs!$AF:$AF,Costs!$A:$A,$A$93,Costs!$D:$D,"Plan") -> 0.066 | I100: =H100 -> 0.066 | J100: =SUM(D100:I100) -> 0.33 | K100: 0.261
C101: Cost Actual (USD m) | D101: =SUMIFS(Costs!$AB:$AB,Costs!$A:$A,$A$93,Costs!$D:$D,"Actual") -> 0 | E101: =SUMIFS(Costs!$AC:$AC,Costs!$A:$A,$A$93,Costs!$D:$D,"Actual") -> 0 | F101: =SUMIFS(Costs!$AD:$AD,Costs!$A:$A,$A$93,Costs!$D:$D,"Actual") -> 0 | G101: =SUMIFS(Costs!$AE:$AE,Costs!$A:$A,$A$93,Costs!$D:$D,"Actual") -> 0 | H101: =SUMIFS(Costs!$AF:$AF,Costs!$A:$A,$A$93,Costs!$D:$D,"Actual") -> 0 | I101: =H101 -> 0 | J101: =SUM(D101:I101) -> 0
C102: NET VALUE
C103: Net Value — Plan Base (USD m) | D103: =D96-D100 -> 0 | E103: =E96-E100 -> 0.396 | F103: =F96-F100 -> 0.616 | G103: =G96-G100 -> 0.616 | H103: =H96-H100 -> 0.616 | I103: =I96-I100 -> 0.616 | J103: =J96-J100 -> 2.86 | K103: =K96-K100 -> 2.939
C104: Net Value — Plan High (USD m) | D104: =D97-D100 -> 0 | E104: =E97-E100 -> 0.506 | F104: =F97-F100 -> 0.748 | G104: =G97-G100 -> 0.748 | H104: =H97-H100 -> 0.748 | I104: =I97-I100 -> 0.748 | J104: =J97-J100 -> 3.498
C105: Net Value — Actual (USD m) | D105: =D98-D101 -> 0 | E105: =E98-E101 -> 0 | F105: =F98-F101 -> 0 | G105: =G98-G101 -> 0 | H105: =H98-H101 -> 0 | I105: =I98-I101 -> 0 | J105: =J98-J101 -> 0
C106: ROI (Actual, %) | D106: =IFERROR(D105/D101,0) -> 0 | E106: =IFERROR(E105/E101,0) -> 0 | F106: =IFERROR(F105/F101,0) -> 0 | G106: =IFERROR(G105/G101,0) -> 0 | H106: =IFERROR(H105/H101,0) -> 0 | I106: =IFERROR(I105/I101,0) -> 0 | J106: =IFERROR(J105/J101,0) -> 0 | K106: =IFERROR(K105/K101,0) -> 0
...

Sheet Benefits
A1: Benefits
A2: Reference | B2: Initiative | C2: Name | D2: Lane | E2: Benefit Type | F2: Denomination | G2: P&L Line | H2: Impact Type | I2: Timing | J2: Confidence | K2: Description | L2: _id | M2: _value_translation | N2: _sort_order | O2: _is_draft | P2: _metadata | Q2: _created_at | R2: _updated_at | S2: FY26 | T2: FY27 | U2: FY28 | V2: FY29 | W2: FY30 | X2: FY26-Jan | Y2: FY26-Feb | Z2: FY26-Mar | AA2: FY26-Apr | AB2: FY26-May | AC2: FY26-Jun | AD2: FY26-Jul | AE2: FY26-Aug | AF2: FY26-Sep | AG2: FY26-Oct | AH2: FY26-Nov | AI2: FY26-Dec | AJ2: FY27-Jan | AK2: FY27-Feb | AL2: FY27-Mar | AM2: FY27-Apr | AN2: FY27-May | AO2: FY27-Jun | AP2: FY27-Jul | AQ2: FY27-Aug | AR2: FY27-Sep | AS2: FY27-Oct | AT2: FY27-Nov | AU2: FY27-Dec | AV2: FY28-Jan | AW2: FY28-Feb | AX2: FY28-Mar | AY2: FY28-Apr | AZ2: FY28-May | BA2: FY28-Jun | BB2: FY28-Jul | BC2: FY28-Aug | BD2: FY28-Sep | BE2: FY28-Oct | BF2: FY28-Nov | BG2: FY28-Dec | BH2: FY29-Jan | BI2: FY29-Feb | BJ2: FY29-Mar | BK2: FY29-Apr | BL2: FY29-May | BM2: FY29-Jun | BN2: FY29-Jul | BO2: FY29-Aug | BP2: FY29-Sep | BQ2: FY29-Oct | BR2: FY29-Nov | BS2: FY29-Dec | BT2: FY30-Jan | BU2: FY30-Feb | BV2: FY30-Mar | BW2: FY30-Apr | BX2: FY30-May | BY2: FY30-Jun | BZ2: FY30-Jul | CA2: FY30-Aug | CB2: FY30-Sep | CC2: FY30-Oct | CD2: FY30-Nov | CE2: FY30-Dec | CF2: FY31 | CG2: FY31-Jan | CH2: FY31-Feb | CI2: FY31-Mar | CJ2: FY31-Apr | CK2: FY31-May | CL2: FY31-Jun | CM2: FY31-Jul | CN2: FY31-Aug | CO2: FY31-Sep | CP2: FY31-Oct | CQ2: FY31-Nov | CR2: FY31-Dec | CS2: Workstream
A3: TOR-1 | B3: CAL Accounting System Integration & Automation | C3: Revenue Uplift | D3: Plan Base | E3: Revenue | F3: USD | L3: 398b9357-10b7-4338-8cb9-f65eb9c47aa4 | M3: {"mode":"none"} | N3: 0 | O3: FALSE | P3: {"show_in_summary":true} | Q3: 2026-04-27T10:23:44.167183+00:00 | R3: 2026-04-27T10:23:44.167183+00:00 | S3: 0 | T3: 0 | U3: 0 | V3: 0 | W3: 0 | X3: 0 | Y3: 0 | Z3: 0 | AA3: 0 | AB3: 0 | AC3: 0 | AD3: 0 | AE3: 0 | AF3: 0 | AG3: 0 | AH3: 0 | AI3: 0 | AJ3: 0 | AK3: 0 | AL3: 0 | AM3: 0 | AN3: 0 | AO3: 0 | AP3: 0 | AQ3: 0 | AR3: 0 | AS3: 0 | AT3: 0 | AU3: 0 | AV3: 0 | AW3: 0 | AX3: 0 | AY3: 0 | AZ3: 0 | BA3: 0 | BB3: 0 | BC3: 0 | BD3: 0 | BE3: 0 | BF3: 0 | BG3: 0 | BH3: 0 | BI3: 0 | BJ3: 0 | BK3: 0 | BL3: 0 | BM3: 0 | BN3: 0 | BO3: 0 | BP3: 0 | BQ3: 0 | BR3: 0 | BS3: 0 | BT3: 0 | BU3: 0 | BV3: 0 | BW3: 0 | BX3: 0 | BY3: 0 | BZ3: 0 | CA3: 0 | CB3: 0 | CC3: 0 | CD3: 0 | CE3: 0 | CF3: 0 | CG3: 0 | CH3: 0 | CI3: 0 | CJ3: 0 | CK3: 0 | CL3: 0 | CM3: 0 | CN3: 0 | CO3: 0 | CP3: 0 | CQ3: 0 | CR3: 0 | CS3: =IFERROR(INDEX('Initiative Summary'!$C$5:$C$25,MATCH($A3,'Initiative Summary'!$A$5:$A$25,0)),"") -> Westmark Region
A4: TOR-1 | B4: CAL Accounting System Integration & Automation | C4: Revenue Uplift | D4: Plan High | E4: Revenue | F4: USD | L4: 398b9357-10b7-4338-8cb9-f65eb9c47aa4 | M4: {"mode":"none"} | N4: 0 | O4: FALSE | P4: {"show_in_summary":true} | Q4: 2026-04-27T10:23:44.167183+00:00 | R4: 2026-04-27T10:23:44.167183+00:00 | S4: 0 | T4: 0 | U4: 0 | V4: 0 | W4: 0 | X4: 0 | Y4: 0 | Z4: 0 | AA4: 0 | AB4: 0 | AC4: 0 | AD4: 0 | AE4: 0 | AF4: 0 | AG4: 0 | AH4: 0 | AI4: 0 | AJ4: 0 | AK4: 0 | AL4: 0 | AM4: 0 | AN4: 0 | AO4: 0 | AP4: 0 | AQ4: 0 | AR4: 0 | AS4: 0 | AT4: 0 | AU4: 0 | AV4: 0 | AW4: 0 | AX4: 0 | AY4: 0 | AZ4: 0 | BA4: 0 | BB4: 0 | BC4: 0 | BD4: 0 | BE4: 0 | BF4: 0 | BG4: 0 | BH4: 0 | BI4: 0 | BJ4: 0 | BK4: 0 | BL4: 0 | BM4: 0 | BN4: 0 | BO4: 0 | BP4: 0 | BQ4: 0 | BR4: 0 | BS4: 0 | BT4: 0 | BU4: 0 | BV4: 0 | BW4: 0 | BX4: 0 | BY4: 0 | BZ4: 0 | CA4: 0 | CB4: 0 | CC4: 0 | CD4: 0 | CE4: 0 | CF4: 0 | CG4: 0 | CH4: 0 | CI4: 0 | CJ4: 0 | CK4: 0 | CL4: 0 | CM4: 0 | CN4: 0 | CO4: 0 | CP4: 0 | CQ4: 0 | CR4: 0 | CS4: =IFERROR(INDEX('Initiative Summary'!$C$5:$C$25,MATCH($A4,'Initiative Summary'!$A$5:$A$25,0)),"") -> Westmark Region
A5: TOR-1 | B5: CAL Accounting System Integration & Automation | C5: Revenue Uplift | D5: Actual | E5: Revenue | F5: USD | L5: 398b9357-10b7-4338-8cb9-f65eb9c47aa4 | M5: {"mode":"none"} | N5: 0 | O5: FALSE | P5: {"show_in_summary":true} | Q5: 2026-04-27T10:23:44.167183+00:00 | R5: 2026-04-27T10:23:44.167183+00:00 | S5: 0 | T5: 0 | U5: 0 | V5: 0 | W5: 0 | X5: 0 | Y5: 0 | Z5: 0 | AA5: 0 | AB5: 0 | AC5: 0 | AD5: 0 | AE5: 0 | AF5: 0 | AG5: 0 | AH5: 0 | AI5: 0 | AJ5: 0 | AK5: 0 | AL5: 0 | AM5: 0 | AN5: 0 | AO5: 0 | AP5: 0 | AQ5: 0 | AR5: 0 | AS5: 0 | AT5: 0 | AU5: 0 | AV5: 0 | AW5: 0 | AX5: 0 | AY5: 0 | AZ5: 0 | BA5: 0 | BB5: 0 | BC5: 0 | BD5: 0 | BE5: 0 | BF5: 0 | BG5: 0 | BH5: 0 | BI5: 0 | BJ5: 0 | BK5: 0 | BL5: 0 | BM5: 0 | BN5: 0 | BO5: 0 | BP5: 0 | BQ5: 0 | BR5: 0 | BS5: 0 | BT5: 0 | BU5: 0 | BV5: 0 | BW5: 0 | BX5: 0 | BY5: 0 | BZ5: 0 | CA5: 0 | CB5: 0 | CC5: 0 | CD5: 0 | CE5: 0 | CF5: 0 | CG5: 0 | CH5: 0 | CI5: 0 | CJ5: 0 | CK5: 0 | CL5: 0 | CM5: 0 | CN5: 0 | CO5: 0 | CP5: 0 | CQ5: 0 | CR5: 0 | CS5: =IFERROR(INDEX('Initiative Summary'!$C$5:$C$25,MATCH($A5,'Initiative Summary'!$A$5:$A$25,0)),"") -> Westmark Region
A6: TOR-1 | B6: CAL Accounting System Integration & Automation | C6: Gross Margin Uplift | D6: Plan Base | E6: Gross Margin | F6: % | L6: 708ab643-5017-484d-8f3b-35ac0e05f00b | M6: {"mode":"none"} | N6: 3 | O6: FALSE | P6: {"show_in_summary":true} | Q6: 2026-04-27T10:23:44.167183+00:00 | R6: 2026-04-27T10:23:44.167183+00:00 | T6: 10.34 | U6: 14.98 | V6: 14.98 | W6: 14.98 | X6: 0 | Y6: 0 | Z6: 0 | AA6: 0 | AB6: 0 | AC6: 0 | AD6: 0 | AE6: 0 | AF6: 0 | AG6: 0 | AH6: 0 | AI6: 0 | AJ6: 0 | AK6: 0 | AL6: 0 | AM6: 0 | AN6: 0 | AO6: 0 | AP6: 0 | AQ6: 0 | AR6: 10.34 | AS6: 10.34 | AT6: 10.34 | AU6: 10.34 | AV6: 14.98 | AW6: 14.98 | AX6: 14.98 | AY6: 14.98 | AZ6: 14.98 | BA6: 14.98 | BB6: 14.98 | BC6: 14.98 | BD6: 14.98 | BE6: 14.98 | BF6: 14.98 | BG6: 14.98 | BH6: 14.98 | BI6: 14.98 | BJ6: 14.98 | BK6: 14.98 | BL6: 14.98 | BM6: 14.98 | BN6: 14.98 | BO6: 14.98 | BP6: 14.98 | BQ6: 14.98 | BR6: 14.98 | BS6: 14.98 | BT6: 14.98 | BU6: 14.98 | BV6: 14.98 | BW6: 14.98 | BX6: 14.98 | BY6: 14.98 | BZ6: 14.98 | CA6: 14.98 | CB6: 14.98 | CC6: 14.98 | CD6: 14.98 | CE6: 14.98 | CF6: 14.98 | CG6: 14.98 | CH6: 14.98 | CI6: 14.98 | CJ6: 14.98 | CK6: 14.98 | CL6: 14.98 | CM6: 14.98 | CN6: 14.98 | CO6: 14.98 | CP6: 14.98 | CQ6: 14.98 | CR6: 14.98 | CS6: =IFERROR(INDEX('Initiative Summary'!$C$5:$C$25,MATCH($A6,'Initiative Summary'!$A$5:$A$25,0)),"") -> Westmark Region
